Workbook
Name Filename: Bitacora!#REF!
Name Filename: #REF!

Sheet Maestro
A1: On Hold | C1: BL ERRADO | E1: COMERCIAL | H1: POD | I1: Código de puerto
A2: Released | C2: CAMBIO DE CLIENTE | E2: GESTOR DOCUMENTAL | H2: USPHL | I2: 4000224852
C3: CAMBIO DE CONSIGNEE | E3: NAVIERA | H3: USLGB | I3: 4000224850
C4: CAMBIO DE PRECIO | E4: OPERADOR LOGISTICO | H4: USMIA | I4: 4000287585
C5: CAMBIO DE PUERTO DE DESTINO | E5: SENASA | H5: USNTD | I5: 4000224850
C6: CARTAS ERRADAS | E6: SOP | H6: USLAX | I6: 4000224850
C7: CERTIFICADO ORGANICO ERRADO | E7: TRADING | H7: USGLC | I7: 4000224852
C8: CO ERRADO | E8: TERCERO
C9: DATOS ERRADOS EN CONSOLIDADOS (JORDIE/TALSA) | E9: TI
C10: DEMORA EN LA EMISIÓN DEL CERTIFICADO FITOSANITARIO | E10: EXPORTACIONES
C11: ENVIO DE SET DOCUMENTAL TARDIO | E11: FOOD SAFETY
C12: FITOSANITARIO ERRADO | E12: NOMINACIÓN
C13: ISF ERRADO | E13: GESTOR SENASA
C14: ROLEO DE NAVE
C15: OTROS
C16: DEMORA EN LA FACTURA
C17: DEMORA EN PAGO DE BL FLETADO
C18: COI ERRADO
C19: PENDIENTE PHYTO
C20: PENDIENTE FULLDOC NWT
C21: DEMORA EN ENVIO DHL FAMEX | H21: ISF
C22: BL A DESTIEMPO | H22: X | I22: FECHA
H23: NO | I23: 3 DIAS ANTES AMARILLO = PENDIENTE
H24: NO | I24: 2 DIAS ANTES NARANJA = URGENTE
H25: NO | I25: 1 DIA ANTES ROJO = MUY URGENTE
H26: SI | I26: ENVIADO = VERDE

Sheet Bitacora
A1: Key | B1: WK | C1: Fecha de carga | D1: WK Arribo | E1: Mercado | F1: POD | G1: Origen | H1: Exportador | I1: Clase Expedición | J1: Especie | K1: Manejo | L1: N° PO | M1: Contenedor | N1: Consignee | O1: Cliente | P1: Line | Q1: Nave + Viaje | R1: ETD Real | S1: ETA Real | T1: OL | U1: ETA Doc | V1: ETD Doc | W1: ATA DOC | X1: % OBTENCIÓN | Y1: % ANTICIPACIÓN | Z1: GUÍA DHL | AA1: PHYTO | AB1: CARTAS | AC1: INVOICE | AD1: BL / Gaérea | AE1: PL | AF1: ISF | AG1: COI | AH1: CO | AI1: ISF Status | AJ1: FULL DOCUMENT | AK1: Columna1 | AL1: Responsable | AM1: Clase de Exportador | AN1: Status Documental | AO1: Status Container | AP1: Release Date | AQ1: Container Status | AR1: Comments (Status container)
A2: PO00000050459HFPEARANCONV497-24313730 | B2: 19 | C2: 46150 | D2: 20 | E2: LATAM | F2: BOG | G2: PE | H2: HFPE | I2: AIR | J2: ARAN | K2: CONV | L2: PO00000050459 | M2: 497-24313730 | N2: HORTIFRUT COLOMBIA SAS | O2: HORTIFRUT COLOMBIA SAS | P2: AERCARIBE | Q2: 24 | R2: 46154 | S2: 46154 | T2: HELLMANN | U2: =+IF(Bitacora_2[[#This Row],[ATA DOC]]<>"",Bitacora_2[[#This Row],[ATA DOC]], IF(Bitacora_2[[#This Row],[Clase Expedición]]="AIR",Bitacora_2[[#This Row],[ETD Real]], IF(AND(Bitacora_2[[#This Row],[Clase Expedición]]="SEA",Bitacora_2[[#This Row],[Mercado]]="LATAM"), Bitacora_2[[#This Row],[ETD Real]]+3, IF(AND(Bitacora_2[[#This Row],[Clase Expedición]]="SEA",Bitacora_2[[#This Row],[Mercado]]="EUROPE"), Bitacora_2[[#This Row],[ETD Real]]+8, IF(AND(Bitacora_2[[#This Row],[Clase Expedición]]="SEA",Bitacora_2[[#This Row],[Mercado]]="UK"), Bitacora_2[[#This Row],[ETD Real]]+11, IF(AND(Bitacora_2[[#This Row],[Clase Expedición]]="SEA",OR(Bitacora_2[[#This Row],[Mercado]]="ASIA",Bitacora_2[[#This Row],[Mercado]]="ASIA CN + HK")), Bitacora_2[[#This Row],[ETD Real]]+14, IF(AND(Bitacora_2[[#This Row],[Clase Expedición]]="SEA",OR(Bitacora_2[[#This Row],[Mercado]]="US EAST",Bitacora_2[[#This Row],[Mercado]]="US WEST",Bitacora_2[[#This Row],[Mercado]]="US SOUTH")), Bitacora_2[[#This Row],[ETD Real]]+8,""))))))) -> 46154 | X2: =IF(OR(Bitacora_2[[#This Row],[ETD Real]]="",Bitacora_2[[#This Row],[ETD Doc]]=""),"",Bitacora_2[[#This Row],[ETD Doc]]-Bitacora_2[[#This Row],[ETD Real]]) | Y2: =IF(OR(Bitacora_2[[#This Row],[ATA DOC]]="",Bitacora_2[[#This Row],[ETA Real]]=""),"",Bitacora_2[[#This Row],[ETA Real]]-Bitacora_2[[#This Row],[ATA DOC]]) | AI2: =IF(AND(OR(E2="US EAST",E2="US WEST",E2="US SOUTH"),I2="SEA",Bitacora_2[[#This Row],[ETD Real]]-TODAY()>=3,Bitacora_2[[#This Row],[ISF]]<>"X"),"Pending", IF(AND(OR(E2="US EAST",E2="US WEST",E2="US SOUTH"),I2="SEA",Bitacora_2[[#This Row],[ETD Real]]-TODAY()=2,Bitacora_2[[#This Row],[ISF]]<>"X"),"Urgente", IF(AND(OR(E2="US EAST",E2="US WEST",E2="US SOUTH"),I2="SEA",Bitacora_2[[#This Row],[ETD Real]]-TODAY()<=1,Bitacora_2[[#This Row],[ISF]]<>"X"),"Muy Urgente", IF(AND(OR(E2="US EAST",E2="US WEST",E2="US SOUTH"),I2="SEA",Bitacora_2[[#This Row],[ISF]]="X"),"Sent","")))) | AJ2: =IF(AND(OR(Bitacora_2[[#This Row],[Clase Expedición]]="AIR",Bitacora_2[[#This Row],[Clase Expedición]]="TRK")),"Complete", IF(AND(Bitacora_2[[#This Row],[Mercado]]="LATAM",COUNTA(Bitacora_2[[#This Row],[PHYTO]:[ISF]],Bitacora_2[[#This Row],[CO]])=7,Bitacora_2[[#This Row],[Clase Expedición]]<>"TRK"), "Complete", IF(AND(Bitacora_2[[#This Row],[Mercado]]="LATAM",COUNTA(Bitacora_2[[#This Row],[PHYTO]:[PL ]],Bitacora_2[[#This Row],[CO]])=6,Bitacora_2[[#This Row],[Clase Expedición]]="SEA"), "Complete", IF(AND(OR(Bitacora_2[[#This Row],[Mercado]]="EUROPE",Bitacora_2[[#This Row],[Mercado]]="UK"),COUNTA(Bitacora_2[[#This Row],[PHYTO]],Bitacora_2[[#This Row],[INVOICE]:[PL ]],Bitacora_2[[#This Row],[COI]])=5,Bitacora_2[[#This Row],[Clase Expedición]]="SEA",Bitacora_2[[#This Row],[Manejo]]="ORG"), "Complete", IF(AND(OR(Bitacora_2[[#This Row],[Mercado]]="EUROPE",Bitacora_2[[#This Row],[Mercado]]="UK"),COUNTA(Bitacora_2[[#This Row],[PHYTO]],Bitacora_2[[#This Row],[INVOICE]:[PL ]])=4,Bitacora_2[[#This Row],[Clase Expedición]]="SEA",Bitacora_2[[#This Row],[Manejo]]="CONV"), "Complete", IF(AND(OR(Bitacora_2[[#This Row],[Mercado]]="US WEST",Bitacora_2[[#This Row],[Mercado]]="US EAST",Bitacora_2[[#This Row],[Mercado]]="US SOUTH"),COUNTA(Bitacora_2[[#This Row],[PHYTO]:[ISF]],Bitacora_2[[#This Row],[CO]])=7,Bitacora_2[[#This Row],[Clase Expedición]]="SEA",Bitacora_2[[#This Row],[Exportador]]="ECHF"), "Complete", IF(AND(OR(Bitacora_2[[#This Row],[Mercado]]="US WEST",Bitacora_2[[#This Row],[Mercado]]="US EAST",Bitacora_2[[#This Row],[Mercado]]="US SOUTH"),COUNTA(Bitacora_2[[#This Row],[PHYTO]:[ISF]])=6,Bitacora_2[[#This Row],[Clase Expedición]]="SEA",Bitacora_2[[#This Row],[Exportador]]<>"ECHF"), "Complete", IF(AND(OR(Bitacora_2[[#This Row],[Mercado]]="ASIA",Bitacora_2[[#This Row],[Mercado]]="ASIA CN + HK"),COUNTA(Bitacora_2[[#This Row],[PHYTO]:[PL ]],Bitacora_2[[#This Row],[CO]])=6), "Complete","Incomplete")))))))) -> Complete | AM2: =+IF(OR(Bitacora_2[[#This Row],[Exportador]]="INVERSIONES JORDIE",Bitacora_2[[#This Row],[Exportador]]="TAL S.A."), "Tercero", "Propio") -> Propio | AN2: =IF(AND(Bitacora_2[[#This Row],[Clase Expedición]]="AIR",OR(Bitacora_2[[#This Row],[Mercado]]="US EAST",Bitacora_2[[#This Row],[Mercado]]="US WEST",Bitacora_2[[#This Row],[Mercado]]="US SOUTH")),IF(Bitacora_2[[#This Row],[ETD Doc]]<>"","Delivered","Pending"), IF(Bitacora_2[[#This Row],[Clase Expedición]]="AIR","Delivered", IF(AND(Bitacora_2[[#This Row],[ETD Doc]]="",Bitacora_2[[#This Row],[ATA DOC]]=""),"Pending", IF(AND(Bitacora_2[[#This Row],[ETD Doc]]<>"",Bitacora_2[[#This Row],[ATA DOC]]=""),"In transit", IF(AND(Bitacora_2[[#This Row],[ETD Doc]]<>"",Bitacora_2[[#This Row],[ATA DOC]]<>""),"Delivered",""))))) -> Delivered | AQ2: =IF(I2="SEA",IF(AP2="","On Hold","Released"),"")
A3: PO00000050458HFPEARANCONVPE691300300 | B3: 20 | C3: 46154 | D3: 22 | E3: LATAM | F3: BAR | G3: PE | H3: HFPE | I3: TRK | J3: ARAN | K3: CONV | L3: PO00000050458 | M3: PE691300300 | N3: BERRYGOOD COM. IMP. E DISTRIBUICAO | O3: BERRYGOOD | P3: TERRESTRE | R3: 46167 | S3: 46167 | T3: MILTEX | U3: =+IF(Bitacora_2[[#This Row],[ATA DOC]]<>"",Bitacora_2[[#This Row],[ATA DOC]], IF(Bitacora_2[[#This Row],[Clase Expedición]]="AIR",Bitacora_2[[#This Row],[ETD Real]], IF(AND(Bitacora_2[[#This Row],[Clase Expedición]]="SEA",Bitacora_2[[#This Row],[Mercado]]="LATAM"), Bitacora_2[[#This Row],[ETD Real]]+3, IF(AND(Bitacora_2[[#This Row],[Clase Expedición]]="SEA",Bitacora_2[[#This Row],[Mercado]]="EUROPE"), Bitacora_2[[#This Row],[ETD Real]]+8, IF(AND(Bitacora_2[[#This Row],[Clase Expedición]]="SEA",Bitacora_2[[#This Row],[Mercado]]="UK"), Bitacora_2[[#This Row],[ETD Real]]+11, IF(AND(Bitacora_2[[#This Row],[Clase Expedición]]="SEA",OR(Bitacora_2[[#This Row],[Mercado]]="ASIA",Bitacora_2[[#This Row],[Mercado]]="ASIA CN + HK")), Bitacora_2[[#This Row],[ETD Real]]+14, IF(AND(Bitacora_2[[#This Row],[Clase Expedición]]="SEA",OR(Bitacora_2[[#This Row],[Mercado]]="US EAST",Bitacora_2[[#This Row],[Mercado]]="US WEST",Bitacora_2[[#This Row],[Mercado]]="US SOUTH")), Bitacora_2[[#This Row],[ETD Real]]+8,""))))))) | X3: =IF(OR(Bitacora_2[[#This Row],[ETD Real]]="",Bitacora_2[[#This Row],[ETD Doc]]=""),"",Bitacora_2[[#This Row],[ETD Doc]]-Bitacora_2[[#This Row],[ETD Real]]) | Y3: =IF(OR(Bitacora_2[[#This Row],[ATA DOC]]="",Bitacora_2[[#This Row],[ETA Real]]=""),"",Bitacora_2[[#This Row],[ETA Real]]-Bitacora_2[[#This Row],[ATA DOC]]) | AI3: =IF(AND(OR(E3="US EAST",E3="US WEST",E3="US SOUTH"),I3="SEA",Bitacora_2[[#This Row],[ETD Real]]-TODAY()>=3,Bitacora_2[[#This Row],[ISF]]<>"X"),"Pending", IF(AND(OR(E3="US EAST",E3="US WEST",E3="US SOUTH"),I3="SEA",Bitacora_2[[#This Row],[ETD Real]]-TODAY()=2,Bitacora_2[[#This Row],[ISF]]<>"X"),"Urgente", IF(AND(OR(E3="US EAST",E3="US WEST",E3="US SOUTH"),I3="SEA",Bitacora_2[[#This Row],[ETD Real]]-TODAY()<=1,Bitacora_2[[#This Row],[ISF]]<>"X"),"Muy Urgente", IF(AND(OR(E3="US EAST",E3="US WEST",E3="US SOUTH"),I3="SEA",Bitacora_2[[#This Row],[ISF]]="X"),"Sent","")))) | AJ3: =IF(AND(OR(Bitacora_2[[#This Row],[Clase Expedición]]="AIR",Bitacora_2[[#This Row],[Clase Expedición]]="TRK")),"Complete", IF(AND(Bitacora_2[[#This Row],[Mercado]]="LATAM",COUNTA(Bitacora_2[[#This Row],[PHYTO]:[ISF]],Bitacora_2[[#This Row],[CO]])=7,Bitacora_2[[#This Row],[Clase Expedición]]<>"TRK"), "Complete", IF(AND(Bitacora_2[[#This Row],[Mercado]]="LATAM",COUNTA(Bitacora_2[[#This Row],[PHYTO]:[PL ]],Bitacora_2[[#This Row],[CO]])=6,Bitacora_2[[#This Row],[Clase Expedición]]="SEA"), "Complete", IF(AND(OR(Bitacora_2[[#This Row],[Mercado]]="EUROPE",Bitacora_2[[#This Row],[Mercado]]="UK"),COUNTA(Bitacora_2[[#This Row],[PHYTO]],Bitacora_2[[#This Row],[INVOICE]:[PL ]],Bitacora_2[[#This Row],[COI]])=5,Bitacora_2[[#This Row],[Clase Expedición]]="SEA",Bitacora_2[[#This Row],[Manejo]]="ORG"), "Complete", IF(AND(OR(Bitacora_2[[#This Row],[Mercado]]="EUROPE",Bitacora_2[[#This Row],[Mercado]]="UK"),COUNTA(Bitacora_2[[#This Row],[PHYTO]],Bitacora_2[[#This Row],[INVOICE]:[PL ]])=4,Bitacora_2[[#This Row],[Clase Expedición]]="SEA",Bitacora_2[[#This Row],[Manejo]]="CONV"), "Complete", IF(AND(OR(Bitacora_2[[#This Row],[Mercado]]="US WEST",Bitacora_2[[#This Row],[Mercado]]="US EAST",Bitacora_2[[#This Row],[Mercado]]="US SOUTH"),COUNTA(Bitacora_2[[#This Row],[PHYTO]:[ISF]],Bitacora_2[[#This Row],[CO]])=7,Bitacora_2[[#This Row],[Clase Expedición]]="SEA",Bitacora_2[[#This Row],[Exportador]]="ECHF"), "Complete", IF(AND(OR(Bitacora_2[[#This Row],[Mercado]]="US WEST",Bitacora_2[[#This Row],[Mercado]]="US EAST",Bitacora_2[[#This Row],[Mercado]]="US SOUTH"),COUNTA(Bitacora_2[[#This Row],[PHYTO]:[ISF]])=6,Bitacora_2[[#This Row],[Clase Expedición]]="SEA",Bitacora_2[[#This Row],[Exportador]]<>"ECHF"), "Complete", IF(AND(OR(Bitacora_2[[#This Row],[Mercado]]="ASIA",Bitacora_2[[#This Row],[Mercado]]="ASIA CN + HK"),COUNTA(Bitacora_2[[#This Row],[PHYTO]:[PL ]],Bitacora_2[[#This Row],[CO]])=6), "Complete","Incomplete")))))))) -> Complete | AM3: =+IF(OR(Bitacora_2[[#This Row],[Exportador]]="INVERSIONES JORDIE",Bitacora_2[[#This Row],[Exportador]]="TAL S.A."), "Tercero", "Propio") -> Propio | AN3: =IF(AND(Bitacora_2[[#This Row],[Clase Expedición]]="AIR",OR(Bitacora_2[[#This Row],[Mercado]]="US EAST",Bitacora_2[[#This Row],[Mercado]]="US WEST",Bitacora_2[[#This Row],[Mercado]]="US SOUTH")),IF(Bitacora_2[[#This Row],[ETD Doc]]<>"","Delivered","Pending"), IF(Bitacora_2[[#This Row],[Clase Expedición]]="AIR","Delivered", IF(AND(Bitacora_2[[#This Row],[ETD Doc]]="",Bitacora_2[[#This Row],[ATA DOC]]=""),"Pending", IF(AND(Bitacora_2[[#This Row],[ETD Doc]]<>"",Bitacora_2[[#This Row],[ATA DOC]]=""),"In transit", IF(AND(Bitacora_2[[#This Row],[ETD Doc]]<>"",Bitacora_2[[#This Row],[ATA DOC]]<>""),"Delivered",""))))) -> Pending | AQ3: =IF(I3="SEA",IF(AP3="","On Hold","Released"),"")
A4: PO00000050664HFPEARANCONV145-12060720 | B4: 20 | C4: 46158 | D4: 21 | E4: LATAM | F4: BOG | G4: PE | H4: HFPE | I4: AIR | J4: ARAN | K4: CONV | L4: PO00000050664 | M4: 145-12060720 | N4: HORTIFRUT COLOMBIA SAS | O4: HORTIFRUT COLOMBIA | P4: LATAM | Q4: 24 | R4: 46161 | S4: 46161 | T4: HELLMANN | U4: =+IF(Bitacora_2[[#This Row],[ATA DOC]]<>"",Bitacora_2[[#This Row],[ATA DOC]], IF(Bitacora_2[[#This Row],[Clase Expedición]]="AIR",Bitacora_2[[#This Row],[ETD Real]], IF(AND(Bitacora_2[[#This Row],[Clase Expedición]]="SEA",Bitacora_2[[#This Row],[Mercado]]="LATAM"), Bitacora_2[[#This Row],[ETD Real]]+3, IF(AND(Bitacora_2[[#This Row],[Clase Expedición]]="SEA",Bitacora_2[[#This Row],[Mercado]]="EUROPE"), Bitacora_2[[#This Row],[ETD Real]]+8, IF(AND(Bitacora_2[[#This Row],[Clase Expedición]]="SEA",Bitacora_2[[#This Row],[Mercado]]="UK"), Bitacora_2[[#This Row],[ETD Real]]+11, IF(AND(Bitacora_2[[#This Row],[Clase Expedición]]="SEA",OR(Bitacora_2[[#This Row],[Mercado]]="ASIA",Bitacora_2[[#This Row],[Mercado]]="ASIA CN + HK")), Bitacora_2[[#This Row],[ETD Real]]+14, IF(AND(Bitacora_2[[#This Row],[Clase Expedición]]="SEA",OR(Bitacora_2[[#This Row],[Mercado]]="US EAST",Bitacora_2[[#This Row],[Mercado]]="US WEST",Bitacora_2[[#This Row],[Mercado]]="US SOUTH")), Bitacora_2[[#This Row],[ETD Real]]+8,""))))))) -> 46161 | X4: =IF(OR(Bitacora_2[[#This Row],[ETD Real]]="",Bitacora_2[[#This Row],[ETD Doc]]=""),"",Bitacora_2[[#This Row],[ETD Doc]]-Bitacora_2[[#This Row],[ETD Real]]) | Y4: =IF(OR(Bitacora_2[[#This Row],[ATA DOC]]="",Bitacora_2[[#This Row],[ETA Real]]=""),"",Bitacora_2[[#This Row],[ETA Real]]-Bitacora_2[[#This Row],[ATA DOC]]) | AI4: =IF(AND(OR(E4="US EAST",E4="US WEST",E4="US SOUTH"),I4="SEA",Bitacora_2[[#This Row],[ETD Real]]-TODAY()>=3,Bitacora_2[[#This Row],[ISF]]<>"X"),"Pending", IF(AND(OR(E4="US EAST",E4="US WEST",E4="US SOUTH"),I4="SEA",Bitacora_2[[#This Row],[ETD Real]]-TODAY()=2,Bitacora_2[[#This Row],[ISF]]<>"X"),"Urgente", IF(AND(OR(E4="US EAST",E4="US WEST",E4="US SOUTH"),I4="SEA",Bitacora_2[[#This Row],[ETD Real]]-TODAY()<=1,Bitacora_2[[#This Row],[ISF]]<>"X"),"Muy Urgente", IF(AND(OR(E4="US EAST",E4="US WEST",E4="US SOUTH"),I4="SEA",Bitacora_2[[#This Row],[ISF]]="X"),"Sent","")))) | AJ4: =IF(AND(OR(Bitacora_2[[#This Row],[Clase Expedición]]="AIR",Bitacora_2[[#This Row],[Clase Expedición]]="TRK")),"Complete", IF(AND(Bitacora_2[[#This Row],[Mercado]]="LATAM",COUNTA(Bitacora_2[[#This Row],[PHYTO]:[ISF]],Bitacora_2[[#This Row],[CO]])=7,Bitacora_2[[#This Row],[Clase Expedición]]<>"TRK"), "Complete", IF(AND(Bitacora_2[[#This Row],[Mercado]]="LATAM",COUNTA(Bitacora_2[[#This Row],[PHYTO]:[PL ]],Bitacora_2[[#This Row],[CO]])=6,Bitacora_2[[#This Row],[Clase Expedición]]="SEA"), "Complete", IF(AND(OR(Bitacora_2[[#This Row],[Mercado]]="EUROPE",Bitacora_2[[#This Row],[Mercado]]="UK"),COUNTA(Bitacora_2[[#This Row],[PHYTO]],Bitacora_2[[#This Row],[INVOICE]:[PL ]],Bitacora_2[[#This Row],[COI]])=5,Bitacora_2[[#This Row],[Clase Expedición]]="SEA",Bitacora_2[[#This Row],[Manejo]]="ORG"), "Complete", IF(AND(OR(Bitacora_2[[#This Row],[Mercado]]="EUROPE",Bitacora_2[[#This Row],[Mercado]]="UK"),COUNTA(Bitacora_2[[#This Row],[PHYTO]],Bitacora_2[[#This Row],[INVOICE]:[PL ]])=4,Bitacora_2[[#This Row],[Clase Expedición]]="SEA",Bitacora_2[[#This Row],[Manejo]]="CONV"), "Complete", IF(AND(OR(Bitacora_2[[#This Row],[Mercado]]="US WEST",Bitacora_2[[#This Row],[Mercado]]="US EAST",Bitacora_2[[#This Row],[Mercado]]="US SOUTH"),COUNTA(Bitacora_2[[#This Row],[PHYTO]:[ISF]],Bitacora_2[[#This Row],[CO]])=7,Bitacora_2[[#This Row],[Clase Expedición]]="SEA",Bitacora_2[[#This Row],[Exportador]]="ECHF"), "Complete", IF(AND(OR(Bitacora_2[[#This Row],[Mercado]]="US WEST",Bitacora_2[[#This Row],[Mercado]]="US EAST",Bitacora_2[[#This Row],[Mercado]]="US SOUTH"),COUNTA(Bitacora_2[[#This Row],[PHYTO]:[ISF]])=6,Bitacora_2[[#This Row],[Clase Expedición]]="SEA",Bitacora_2[[#This Row],[Exportador]]<>"ECHF"), "Complete", IF(AND(OR(Bitacora_2[[#This Row],[Mercado]]="ASIA",Bitacora_2[[#This Row],[Mercado]]="ASIA CN + HK"),COUNTA(Bitacora_2[[#This Row],[PHYTO]:[PL ]],Bitacora_2[[#This Row],[CO]])=6), "Complete","Incomplete")))))))) -> Complete | AM4: =+IF(OR(Bitacora_2[[#This Row],[Exportador]]="INVERSIONES JORDIE",Bitacora_2[[#This Row],[Exportador]]="TAL S.A."), "Tercero", "Propio") -> Propio | AN4: =IF(AND(Bitacora_2[[#This Row],[Clase Expedición]]="AIR",OR(Bitacora_2[[#This Row],[Mercado]]="US EAST",Bitacora_2[[#This Row],[Mercado]]="US WEST",Bitacora_2[[#This Row],[Mercado]]="US SOUTH")),IF(Bitacora_2[[#This Row],[ETD Doc]]<>"","Delivered","Pending"), IF(Bitacora_2[[#This Row],[Clase Expedición]]="AIR","Delivered", IF(AND(Bitacora_2[[#This Row],[ETD Doc]]="",Bitacora_2[[#This Row],[ATA DOC]]=""),"Pending", IF(AND(Bitacora_2[[#This Row],[ETD Doc]]<>"",Bitacora_2[[#This Row],[ATA DOC]]=""),"In transit", IF(AND(Bitacora_2[[#This Row],[ETD Doc]]<>"",Bitacora_2[[#This Row],[ATA DOC]]<>""),"Delivered",""))))) -> Delivered | AQ4: =IF(I4="SEA",IF(AP4="","On Hold","Released"),"")
A5: PO00000050665HFPEARANCONV145-12060926 | B5: 20 | C5: 46158 | D5: 21 | E5: LATAM | F5: GRU | G5: PE | H5: HFPE | I5: AIR | J5: ARAN | K5: CONV | L5: PO00000050665 | M5: 145-12060926 | N5: BERRYGOOD COM. IMP. E DISTRIBUICAO | O5: BERRYGOOD | P5: LATAM | Q5: 24 | R5: 46162 | S5: 46162 | T5: HELLMANN | U5: =+IF(Bitacora_2[[#This Row],[ATA DOC]]<>"",Bitacora_2[[#This Row],[ATA DOC]], IF(Bitacora_2[[#This Row],[Clase Expedición]]="AIR",Bitacora_2[[#This Row],[ETD Real]], IF(AND(Bitacora_2[[#This Row],[Clase Expedición]]="SEA",Bitacora_2[[#This Row],[Mercado]]="LATAM"), Bitacora_2[[#This Row],[ETD Real]]+3, IF(AND(Bitacora_2[[#This Row],[Clase Expedición]]="SEA",Bitacora_2[[#This Row],[Mercado]]="EUROPE"), Bitacora_2[[#This Row],[ETD Real]]+8, IF(AND(Bitacora_2[[#This Row],[Clase Expedición]]="SEA",Bitacora_2[[#This Row],[Mercado]]="UK"), Bitacora_2[[#This Row],[ETD Real]]+11, IF(AND(Bitacora_2[[#This Row],[Clase Expedición]]="SEA",OR(Bitacora_2[[#This Row],[Mercado]]="ASIA",Bitacora_2[[#This Row],[Mercado]]="ASIA CN + HK")), Bitacora_2[[#This Row],[ETD Real]]+14, IF(AND(Bitacora_2[[#This Row],[Clase Expedición]]="SEA",OR(Bitacora_2[[#This Row],[Mercado]]="US EAST",Bitacora_2[[#This Row],[Mercado]]="US WEST",Bitacora_2[[#This Row],[Mercado]]="US SOUTH")), Bitacora_2[[#This Row],[ETD Real]]+8,""))))))) -> 46162 | X5: =IF(OR(Bitacora_2[[#This Row],[ETD Real]]="",Bitacora_2[[#This Row],[ETD Doc]]=""),"",Bitacora_2[[#This Row],[ETD Doc]]-Bitacora_2[[#This Row],[ETD Real]]) | Y5: =IF(OR(Bitacora_2[[#This Row],[ATA DOC]]="",Bitacora_2[[#This Row],[ETA Real]]=""),"",Bitacora_2[[#This Row],[ETA Real]]-Bitacora_2[[#This Row],[ATA DOC]]) | AI5: =IF(AND(OR(E5="US EAST",E5="US WEST",E5="US SOUTH"),I5="SEA",Bitacora_2[[#This Row],[ETD Real]]-TODAY()>=3,Bitacora_2[[#This Row],[ISF]]<>"X"),"Pending", IF(AND(OR(E5="US EAST",E5="US WEST",E5="US SOUTH"),I5="SEA",Bitacora_2[[#This Row],[ETD Real]]-TODAY()=2,Bitacora_2[[#This Row],[ISF]]<>"X"),"Urgente", IF(AND(OR(E5="US EAST",E5="US WEST",E5="US SOUTH"),I5="SEA",Bitacora_2[[#This Row],[ETD Real]]-TODAY()<=1,Bitacora_2[[#This Row],[ISF]]<>"X"),"Muy Urgente", IF(AND(OR(E5="US EAST",E5="US WEST",E5="US SOUTH"),I5="SEA",Bitacora_2[[#This Row],[ISF]]="X"),"Sent","")))) | AJ5: =IF(AND(OR(Bitacora_2[[#This Row],[Clase Expedición]]="AIR",Bitacora_2[[#This Row],[Clase Expedición]]="TRK")),"Complete", IF(AND(Bitacora_2[[#This Row],[Mercado]]="LATAM",COUNTA(Bitacora_2[[#This Row],[PHYTO]:[ISF]],Bitacora_2[[#This Row],[CO]])=7,Bitacora_2[[#This Row],[Clase Expedición]]<>"TRK"), "Complete", IF(AND(Bitacora_2[[#This Row],[Mercado]]="LATAM",COUNTA(Bitacora_2[[#This Row],[PHYTO]:[PL ]],Bitacora_2[[#This Row],[CO]])=6,Bitacora_2[[#This Row],[Clase Expedición]]="SEA"), "Complete", IF(AND(OR(Bitacora_2[[#This Row],[Mercado]]="EUROPE",Bitacora_2[[#This Row],[Mercado]]="UK"),COUNTA(Bitacora_2[[#This Row],[PHYTO]],Bitacora_2[[#This Row],[INVOICE]:[PL ]],Bitacora_2[[#This Row],[COI]])=5,Bitacora_2[[#This Row],[Clase Expedición]]="SEA",Bitacora_2[[#This Row],[Manejo]]="ORG"), "Complete", IF(AND(OR(Bitacora_2[[#This Row],[Mercado]]="EUROPE",Bitacora_2[[#This Row],[Mercado]]="UK"),COUNTA(Bitacora_2[[#This Row],[PHYTO]],Bitacora_2[[#This Row],[INVOICE]:[PL ]])=4,Bitacora_2[[#This Row],[Clase Expedición]]="SEA",Bitacora_2[[#This Row],[Manejo]]="CONV"), "Complete", IF(AND(OR(Bitacora_2[[#This Row],[Mercado]]="US WEST",Bitacora_2[[#This Row],[Mercado]]="US EAST",Bitacora_2[[#This Row],[Mercado]]="US SOUTH"),COUNTA(Bitacora_2[[#This Row],[PHYTO]:[ISF]],Bitacora_2[[#This Row],[CO]])=7,Bitacora_2[[#This Row],[Clase Expedición]]="SEA",Bitacora_2[[#This Row],[Exportador]]="ECHF"), "Complete", IF(AND(OR(Bitacora_2[[#This Row],[Mercado]]="US WEST",Bitacora_2[[#This Row],[Mercado]]="US EAST",Bitacora_2[[#This Row],[Mercado]]="US SOUTH"),COUNTA(Bitacora_2[[#This Row],[PHYTO]:[ISF]])=6,Bitacora_2[[#This Row],[Clase Expedición]]="SEA",Bitacora_2[[#This Row],[Exportador]]<>"ECHF"), "Complete", IF(AND(OR(Bitacora_2[[#This Row],[Mercado]]="ASIA",Bitacora_2[[#This Row],[Mercado]]="ASIA CN + HK"),COUNTA(Bitacora_2[[#This Row],[PHYTO]:[PL ]],Bitacora_2[[#This Row],[CO]])=6), "Complete","Incomplete")))))))) -> Complete | AM5: =+IF(OR(Bitacora_2[[#This Row],[Exportador]]="INVERSIONES JORDIE",Bitacora_2[[#This Row],[Exportador]]="TAL S.A."), "Tercero", "Propio") -> Propio | AN5: =IF(AND(Bitacora_2[[#This Row],[Clase Expedición]]="AIR",OR(Bitacora_2[[#This Row],[Mercado]]="US EAST",Bitacora_2[[#This Row],[Mercado]]="US WEST",Bitacora_2[[#This Row],[Mercado]]="US SOUTH")),IF(Bitacora_2[[#This Row],[ETD Doc]]<>"","Delivered","Pending"), IF(Bitacora_2[[#This Row],[Clase Expedición]]="AIR","Delivered", IF(AND(Bitacora_2[[#This Row],[ETD Doc]]="",Bitacora_2[[#This Row],[ATA DOC]]=""),"Pending", IF(AND(Bitacora_2[[#This Row],[ETD Doc]]<>"",Bitacora_2[[#This Row],[ATA DOC]]=""),"In transit", IF(AND(Bitacora_2[[#This Row],[ETD Doc]]<>"",Bitacora_2[[#This Row],[ATA DOC]]<>""),"Delivered",""))))) -> Delivered | AQ5: =IF(I5="SEA",IF(AP5="","On Hold","Released"),"")
A6: PO00000050778HFPEARANCONV145-12061221 | B6: 21 | C6: 46164 | D6: 22 | E6: LATAM | F6: BOG | G6: PE | H6: HFPE | I6: AIR | J6: ARAN | K6: CONV | L6: PO00000050778 | M6: 145-12061221 | N6: HORTIFRUT COLOMBIA SAS | O6: HORTIFRUT COLOMBIA | P6: LATAM | Q6: 24 | R6: 46168 | S6: 46168 | T6: HELLMANN | U6: =+IF(Bitacora_2[[#This Row],[ATA DOC]]<>"",Bitacora_2[[#This Row],[ATA DOC]], IF(Bitacora_2[[#This Row],[Clase Expedición]]="AIR",Bitacora_2[[#This Row],[ETD Real]], IF(AND(Bitacora_2[[#This Row],[Clase Expedición]]="SEA",Bitacora_2[[#This Row],[Mercado]]="LATAM"), Bitacora_2[[#This Row],[ETD Real]]+3, IF(AND(Bitacora_2[[#This Row],[Clase Expedición]]="SEA",Bitacora_2[[#This Row],[Mercado]]="EUROPE"), Bitacora_2[[#This Row],[ETD Real]]+8, IF(AND(Bitacora_2[[#This Row],[Clase Expedición]]="SEA",Bitacora_2[[#This Row],[Mercado]]="UK"), Bitacora_2[[#This Row],[ETD Real]]+11, IF(AND(Bitacora_2[[#This Row],[Clase Expedición]]="SEA",OR(Bitacora_2[[#This Row],[Mercado]]="ASIA",Bitacora_2[[#This Row],[Mercado]]="ASIA CN + HK")), Bitacora_2[[#This Row],[ETD Real]]+14, IF(AND(Bitacora_2[[#This Row],[Clase Expedición]]="SEA",OR(Bitacora_2[[#This Row],[Mercado]]="US EAST",Bitacora_2[[#This Row],[Mercado]]="US WEST",Bitacora_2[[#This Row],[Mercado]]="US SOUTH")), Bitacora_2[[#This Row],[ETD Real]]+8,""))))))) -> 46168 | X6: =IF(OR(Bitacora_2[[#This Row],[ETD Real]]="",Bitacora_2[[#This Row],[ETD Doc]]=""),"",Bitacora_2[[#This Row],[ETD Doc]]-Bitacora_2[[#This Row],[ETD Real]]) | Y6: =IF(OR(Bitacora_2[[#This Row],[ATA DOC]]="",Bitacora_2[[#This Row],[ETA Real]]=""),"",Bitacora_2[[#This Row],[ETA Real]]-Bitacora_2[[#This Row],[ATA DOC]]) | AI6: =IF(AND(OR(E6="US EAST",E6="US WEST",E6="US SOUTH"),I6="SEA",Bitacora_2[[#This Row],[ETD Real]]-TODAY()>=3,Bitacora_2[[#This Row],[ISF]]<>"X"),"Pending", IF(AND(OR(E6="US EAST",E6="US WEST",E6="US SOUTH"),I6="SEA",Bitacora_2[[#This Row],[ETD Real]]-TODAY()=2,Bitacora_2[[#This Row],[ISF]]<>"X"),"Urgente", IF(AND(OR(E6="US EAST",E6="US WEST",E6="US SOUTH"),I6="SEA",Bitacora_2[[#This Row],[ETD Real]]-TODAY()<=1,Bitacora_2[[#This Row],[ISF]]<>"X"),"Muy Urgente", IF(AND(OR(E6="US EAST",E6="US WEST",E6="US SOUTH"),I6="SEA",Bitacora_2[[#This Row],[ISF]]="X"),"Sent","")))) | AJ6: =IF(AND(OR(Bitacora_2[[#This Row],[Clase Expedición]]="AIR",Bitacora_2[[#This Row],[Clase Expedición]]="TRK")),"Complete", IF(AND(Bitacora_2[[#This Row],[Mercado]]="LATAM",COUNTA(Bitacora_2[[#This Row],[PHYTO]:[ISF]],Bitacora_2[[#This Row],[CO]])=7,Bitacora_2[[#This Row],[Clase Expedición]]<>"TRK"), "Complete", IF(AND(Bitacora_2[[#This Row],[Mercado]]="LATAM",COUNTA(Bitacora_2[[#This Row],[PHYTO]:[PL ]],Bitacora_2[[#This Row],[CO]])=6,Bitacora_2[[#This Row],[Clase Expedición]]="SEA"), "Complete", IF(AND(OR(Bitacora_2[[#This Row],[Mercado]]="EUROPE",Bitacora_2[[#This Row],[Mercado]]="UK"),COUNTA(Bitacora_2[[#This Row],[PHYTO]],Bitacora_2[[#This Row],[INVOICE]:[PL ]],Bitacora_2[[#This Row],[COI]])=5,Bitacora_2[[#This Row],[Clase Expedición]]="SEA",Bitacora_2[[#This Row],[Manejo]]="ORG"), "Complete", IF(AND(OR(Bitacora_2[[#This Row],[Mercado]]="EUROPE",Bitacora_2[[#This Row],[Mercado]]="UK"),COUNTA(Bitacora_2[[#This Row],[PHYTO]],Bitacora_2[[#This Row],[INVOICE]:[PL ]])=4,Bitacora_2[[#This Row],[Clase Expedición]]="SEA",Bitacora_2[[#This Row],[Manejo]]="CONV"), "Complete", IF(AND(OR(Bitacora_2[[#This Row],[Mercado]]="US WEST",Bitacora_2[[#This Row],[Mercado]]="US EAST",Bitacora_2[[#This Row],[Mercado]]="US SOUTH"),COUNTA(Bitacora_2[[#This Row],[PHYTO]:[ISF]],Bitacora_2[[#This Row],[CO]])=7,Bitacora_2[[#This Row],[Clase Expedición]]="SEA",Bitacora_2[[#This Row],[Exportador]]="ECHF"), "Complete", IF(AND(OR(Bitacora_2[[#This Row],[Mercado]]="US WEST",Bitacora_2[[#This Row],[Mercado]]="US EAST",Bitacora_2[[#This Row],[Mercado]]="US SOUTH"),COUNTA(Bitacora_2[[#This Row],[PHYTO]:[ISF]])=6,Bitacora_2[[#This Row],[Clase Expedición]]="SEA",Bitacora_2[[#This Row],[Exportador]]<>"ECHF"), "Complete", IF(AND(OR(Bitacora_2[[#This Row],[Mercado]]="ASIA",Bitacora_2[[#This Row],[Mercado]]="ASIA CN + HK"),COUNTA(Bitacora_2[[#This Row],[PHYTO]:[PL ]],Bitacora_2[[#This Row],[CO]])=6), "Complete","Incomplete")))))))) -> Complete | AM6: =+IF(OR(Bitacora_2[[#This Row],[Exportador]]="INVERSIONES JORDIE",Bitacora_2[[#This Row],[Exportador]]="TAL S.A."), "Tercero", "Propio") -> Propio | AN6: =IF(AND(Bitacora_2[[#This Row],[Clase Expedición]]="AIR",OR(Bitacora_2[[#This Row],[Mercado]]="US EAST",Bitacora_2[[#This Row],[Mercado]]="US WEST",Bitacora_2[[#This Row],[Mercado]]="US SOUTH")),IF(Bitacora_2[[#This Row],[ETD Doc]]<>"","Delivered","Pending"), IF(Bitacora_2[[#This Row],[Clase Expedición]]="AIR","Delivered", IF(AND(Bitacora_2[[#This Row],[ETD Doc]]="",Bitacora_2[[#This Row],[ATA DOC]]=""),"Pending", IF(AND(Bitacora_2[[#This Row],[ETD Doc]]<>"",Bitacora_2[[#This Row],[ATA DOC]]=""),"In transit", IF(AND(Bitacora_2[[#This Row],[ETD Doc]]<>"",Bitacora_2[[#This Row],[ATA DOC]]<>""),"Delivered",""))))) -> Delivered | AQ6: =IF(I6="SEA",IF(AP6="","On Hold","Released"),"")
A7: PO00000050779HFPEARANCONV145-12061232 | B7: 21 | C7: 46164 | D7: 22 | E7: LATAM | F7: BOG | G7: PE | H7: HFPE | I7: AIR | J7: ARAN | K7: CONV | L7: PO00000050779 | M7: 145-12061232 | N7: HORTIFRUT COLOMBIA SAS | O7: HORTIFRUT COLOMBIA | P7: LATAM | Q7: 24 | R7: 46168 | S7: 46168 | T7: HELLMANN | U7: =+IF(Bitacora_2[[#This Row],[ATA DOC]]<>"",Bitacora_2[[#This Row],[ATA DOC]], IF(Bitacora_2[[#This Row],[Clase Expedición]]="AIR",Bitacora_2[[#This Row],[ETD Real]], IF(AND(Bitacora_2[[#This Row],[Clase Expedición]]="SEA",Bitacora_2[[#This Row],[Mercado]]="LATAM"), Bitacora_2[[#This Row],[ETD Real]]+3, IF(AND(Bitacora_2[[#This Row],[Clase Expedición]]="SEA",Bitacora_2[[#This Row],[Mercado]]="EUROPE"), Bitacora_2[[#This Row],[ETD Real]]+8, IF(AND(Bitacora_2[[#This Row],[Clase Expedición]]="SEA",Bitacora_2[[#This Row],[Mercado]]="UK"), Bitacora_2[[#This Row],[ETD Real]]+11, IF(AND(Bitacora_2[[#This Row],[Clase Expedición]]="SEA",OR(Bitacora_2[[#This Row],[Mercado]]="ASIA",Bitacora_2[[#This Row],[Mercado]]="ASIA CN + HK")), Bitacora_2[[#This Row],[ETD Real]]+14, IF(AND(Bitacora_2[[#This Row],[Clase Expedición]]="SEA",OR(Bitacora_2[[#This Row],[Mercado]]="US EAST",Bitacora_2[[#This Row],[Mercado]]="US WEST",Bitacora_2[[#This Row],[Mercado]]="US SOUTH")), Bitacora_2[[#This Row],[ETD Real]]+8,""))))))) -> 46168 | X7: =IF(OR(Bitacora_2[[#This Row],[ETD Real]]="",Bitacora_2[[#This Row],[ETD Doc]]=""),"",Bitacora_2[[#This Row],[ETD Doc]]-Bitacora_2[[#This Row],[ETD Real]]) | Y7: =IF(OR(Bitacora_2[[#This Row],[ATA DOC]]="",Bitacora_2[[#This Row],[ETA Real]]=""),"",Bitacora_2[[#This Row],[ETA Real]]-Bitacora_2[[#This Row],[ATA DOC]]) | AI7: =IF(AND(OR(E7="US EAST",E7="US WEST",E7="US SOUTH"),I7="SEA",Bitacora_2[[#This Row],[ETD Real]]-TODAY()>=3,Bitacora_2[[#This Row],[ISF]]<>"X"),"Pending", IF(AND(OR(E7="US EAST",E7="US WEST",E7="US SOUTH"),I7="SEA",Bitacora_2[[#This Row],[ETD Real]]-TODAY()=2,Bitacora_2[[#This Row],[ISF]]<>"X"),"Urgente", IF(AND(OR(E7="US EAST",E7="US WEST",E7="US SOUTH"),I7="SEA",Bitacora_2[[#This Row],[ETD Real]]-TODAY()<=1,Bitacora_2[[#This Row],[ISF]]<>"X"),"Muy Urgente", IF(AND(OR(E7="US EAST",E7="US WEST",E7="US SOUTH"),I7="SEA",Bitacora_2[[#This Row],[ISF]]="X"),"Sent","")))) | AJ7: =IF(AND(OR(Bitacora_2[[#This Row],[Clase Expedición]]="AIR",Bitacora_2[[#This Row],[Clase Expedición]]="TRK")),"Complete", IF(AND(Bitacora_2[[#This Row],[Mercado]]="LATAM",COUNTA(Bitacora_2[[#This Row],[PHYTO]:[ISF]],Bitacora_2[[#This Row],[CO]])=7,Bitacora_2[[#This Row],[Clase Expedición]]<>"TRK"), "Complete", IF(AND(Bitacora_2[[#This Row],[Mercado]]="LATAM",COUNTA(Bitacora_2[[#This Row],[PHYTO]:[PL ]],Bitacora_2[[#This Row],[CO]])=6,Bitacora_2[[#This Row],[Clase Expedición]]="SEA"), "Complete", IF(AND(OR(Bitacora_2[[#This Row],[Mercado]]="EUROPE",Bitacora_2[[#This Row],[Mercado]]="UK"),COUNTA(Bitacora_2[[#This Row],[PHYTO]],Bitacora_2[[#This Row],[INVOICE]:[PL ]],Bitacora_2[[#This Row],[COI]])=5,Bitacora_2[[#This Row],[Clase Expedición]]="SEA",Bitacora_2[[#This Row],[Manejo]]="ORG"), "Complete", IF(AND(OR(Bitacora_2[[#This Row],[Mercado]]="EUROPE",Bitacora_2[[#This Row],[Mercado]]="UK"),COUNTA(Bitacora_2[[#This Row],[PHYTO]],Bitacora_2[[#This Row],[INVOICE]:[PL ]])=4,Bitacora_2[[#This Row],[Clase Expedición]]="SEA",Bitacora_2[[#This Row],[Manejo]]="CONV"), "Complete", IF(AND(OR(Bitacora_2[[#This Row],[Mercado]]="US WEST",Bitacora_2[[#This Row],[Mercado]]="US EAST",Bitacora_2[[#This Row],[Mercado]]="US SOUTH"),COUNTA(Bitacora_2[[#This Row],[PHYTO]:[ISF]],Bitacora_2[[#This Row],[CO]])=7,Bitacora_2[[#This Row],[Clase Expedición]]="SEA",Bitacora_2[[#This Row],[Exportador]]="ECHF"), "Complete", IF(AND(OR(Bitacora_2[[#This Row],[Mercado]]="US WEST",Bitacora_2[[#This Row],[Mercado]]="US EAST",Bitacora_2[[#This Row],[Mercado]]="US SOUTH"),COUNTA(Bitacora_2[[#This Row],[PHYTO]:[ISF]])=6,Bitacora_2[[#This Row],[Clase Expedición]]="SEA",Bitacora_2[[#This Row],[Exportador]]<>"ECHF"), "Complete", IF(AND(OR(Bitacora_2[[#This Row],[Mercado]]="ASIA",Bitacora_2[[#This Row],[Mercado]]="ASIA CN + HK"),COUNTA(Bitacora_2[[#This Row],[PHYTO]:[PL ]],Bitacora_2[[#This Row],[CO]])=6), "Complete","Incomplete")))))))) -> Complete | AM7: =+IF(OR(Bitacora_2[[#This Row],[Exportador]]="INVERSIONES JORDIE",Bitacora_2[[#This Row],[Exportador]]="TAL S.A."), "Tercero", "Propio") -> Propio | AN7: =IF(AND(Bitacora_2[[#This Row],[Clase Expedición]]="AIR",OR(Bitacora_2[[#This Row],[Mercado]]="US EAST",Bitacora_2[[#This Row],[Mercado]]="US WEST",Bitacora_2[[#This Row],[Mercado]]="US SOUTH")),IF(Bitacora_2[[#This Row],[ETD Doc]]<>"","Delivered","Pending"), IF(Bitacora_2[[#This Row],[Clase Expedición]]="AIR","Delivered", IF(AND(Bitacora_2[[#This Row],[ETD Doc]]="",Bitacora_2[[#This Row],[ATA DOC]]=""),"Pending", IF(AND(Bitacora_2[[#This Row],[ETD Doc]]<>"",Bitacora_2[[#This Row],[ATA DOC]]=""),"In transit", IF(AND(Bitacora_2[[#This Row],[ETD Doc]]<>"",Bitacora_2[[#This Row],[ATA DOC]]<>""),"Delivered",""))))) -> Delivered | AQ7: =IF(I7="SEA",IF(AP7="","On Hold","Released"),"")
A8: RC-3547TTAL S.A.ARANCONV145-12061206 | B8: 21 | C8: 46165 | D8: 22 | E8: LATAM | F8: GRU | G8: PE | H8: TAL S.A. | I8: AIR | J8: ARAN | K8: CONV | L8: RC-3547T | M8: 145-12061206 | O8: BERRYGOOD | P8: LATAM | R8: 46167 | S8: 46167 | U8: =+IF(Bitacora_2[[#This Row],[ATA DOC]]<>"",Bitacora_2[[#This Row],[ATA DOC]], IF(Bitacora_2[[#This Row],[Clase Expedición]]="AIR",Bitacora_2[[#This Row],[ETD Real]], IF(AND(Bitacora_2[[#This Row],[Clase Expedición]]="SEA",Bitacora_2[[#This Row],[Mercado]]="LATAM"), Bitacora_2[[#This Row],[ETD Real]]+3, IF(AND(Bitacora_2[[#This Row],[Clase Expedición]]="SEA",Bitacora_2[[#This Row],[Mercado]]="EUROPE"), Bitacora_2[[#This Row],[ETD Real]]+8, IF(AND(Bitacora_2[[#This Row],[Clase Expedición]]="SEA",Bitacora_2[[#This Row],[Mercado]]="UK"), Bitacora_2[[#This Row],[ETD Real]]+11, IF(AND(Bitacora_2[[#This Row],[Clase Expedición]]="SEA",OR(Bitacora_2[[#This Row],[Mercado]]="ASIA",Bitacora_2[[#This Row],[Mercado]]="ASIA CN + HK")), Bitacora_2[[#This Row],[ETD Real]]+14, IF(AND(Bitacora_2[[#This Row],[Clase Expedición]]="SEA",OR(Bitacora_2[[#This Row],[Mercado]]="US EAST",Bitacora_2[[#This Row],[Mercado]]="US WEST",Bitacora_2[[#This Row],[Mercado]]="US SOUTH")), Bitacora_2[[#This Row],[ETD Real]]+8,""))))))) -> 46167 | X8: =IF(OR(Bitacora_2[[#This Row],[ETD Real]]="",Bitacora_2[[#This Row],[ETD Doc]]=""),"",Bitacora_2[[#This Row],[ETD Doc]]-Bitacora_2[[#This Row],[ETD Real]]) | Y8: =IF(OR(Bitacora_2[[#This Row],[ATA DOC]]="",Bitacora_2[[#This Row],[ETA Real]]=""),"",Bitacora_2[[#This Row],[ETA Real]]-Bitacora_2[[#This Row],[ATA DOC]]) | AI8: =IF(AND(OR(E8="US EAST",E8="US WEST",E8="US SOUTH"),I8="SEA",Bitacora_2[[#This Row],[ETD Real]]-TODAY()>=3,Bitacora_2[[#This Row],[ISF]]<>"X"),"Pending", IF(AND(OR(E8="US EAST",E8="US WEST",E8="US SOUTH"),I8="SEA",Bitacora_2[[#This Row],[ETD Real]]-TODAY()=2,Bitacora_2[[#This Row],[ISF]]<>"X"),"Urgente", IF(AND(OR(E8="US EAST",E8="US WEST",E8="US SOUTH"),I8="SEA",Bitacora_2[[#This Row],[ETD Real]]-TODAY()<=1,Bitacora_2[[#This Row],[ISF]]<>"X"),"Muy Urgente", IF(AND(OR(E8="US EAST",E8="US WEST",E8="US SOUTH"),I8="SEA",Bitacora_2[[#This Row],[ISF]]="X"),"Sent","")))) | AJ8: =IF(AND(OR(Bitacora_2[[#This Row],[Clase Expedición]]="AIR",Bitacora_2[[#This Row],[Clase Expedición]]="TRK")),"Complete", IF(AND(Bitacora_2[[#This Row],[Mercado]]="LATAM",COUNTA(Bitacora_2[[#This Row],[PHYTO]:[ISF]],Bitacora_2[[#This Row],[CO]])=7,Bitacora_2[[#This Row],[Clase Expedición]]<>"TRK"), "Complete", IF(AND(Bitacora_2[[#This Row],[Mercado]]="LATAM",COUNTA(Bitacora_2[[#This Row],[PHYTO]:[PL ]],Bitacora_2[[#This Row],[CO]])=6,Bitacora_2[[#This Row],[Clase Expedición]]="SEA"), "Complete", IF(AND(OR(Bitacora_2[[#This Row],[Mercado]]="EUROPE",Bitacora_2[[#This Row],[Mercado]]="UK"),COUNTA(Bitacora_2[[#This Row],[PHYTO]],Bitacora_2[[#This Row],[INVOICE]:[PL ]],Bitacora_2[[#This Row],[COI]])=5,Bitacora_2[[#This Row],[Clase Expedición]]="SEA",Bitacora_2[[#This Row],[Manejo]]="ORG"), "Complete", IF(AND(OR(Bitacora_2[[#This Row],[Mercado]]="EUROPE",Bitacora_2[[#This Row],[Mercado]]="UK"),COUNTA(Bitacora_2[[#This Row],[PHYTO]],Bitacora_2[[#This Row],[INVOICE]:[PL ]])=4,Bitacora_2[[#This Row],[Clase Expedición]]="SEA",Bitacora_2[[#This Row],[Manejo]]="CONV"), "Complete", IF(AND(OR(Bitacora_2[[#This Row],[Mercado]]="US WEST",Bitacora_2[[#This Row],[Mercado]]="US EAST",Bitacora_2[[#This Row],[Mercado]]="US SOUTH"),COUNTA(Bitacora_2[[#This Row],[PHYTO]:[ISF]],Bitacora_2[[#This Row],[CO]])=7,Bitacora_2[[#This Row],[Clase Expedición]]="SEA",Bitacora_2[[#This Row],[Exportador]]="ECHF"), "Complete", IF(AND(OR(Bitacora_2[[#This Row],[Mercado]]="US WEST",Bitacora_2[[#This Row],[Mercado]]="US EAST",Bitacora_2[[#This Row],[Mercado]]="US SOUTH"),COUNTA(Bitacora_2[[#This Row],[PHYTO]:[ISF]])=6,Bitacora_2[[#This Row],[Clase Expedición]]="SEA",Bitacora_2[[#This Row],[Exportador]]<>"ECHF"), "Complete", IF(AND(OR(Bitacora_2[[#This Row],[Mercado]]="ASIA",Bitacora_2[[#This Row],[Mercado]]="ASIA CN + HK"),COUNTA(Bitacora_2[[#This Row],[PHYTO]:[PL ]],Bitacora_2[[#This Row],[CO]])=6), "Complete","Incomplete")))))))) -> Complete | AM8: =+IF(OR(Bitacora_2[[#This Row],[Exportador]]="INVERSIONES JORDIE",Bitacora_2[[#This Row],[Exportador]]="TAL S.A."), "Tercero", "Propio") -> Tercero | AN8: =IF(AND(Bitacora_2[[#This Row],[Clase Expedición]]="AIR",OR(Bitacora_2[[#This Row],[Mercado]]="US EAST",Bitacora_2[[#This Row],[Mercado]]="US WEST",Bitacora_2[[#This Row],[Mercado]]="US SOUTH")),IF(Bitacora_2[[#This Row],[ETD Doc]]<>"","Delivered","Pending"), IF(Bitacora_2[[#This Row],[Clase Expedición]]="AIR","Delivered", IF(AND(Bitacora_2[[#This Row],[ETD Doc]]="",Bitacora_2[[#This Row],[ATA DOC]]=""),"Pending", IF(AND(Bitacora_2[[#This Row],[ETD Doc]]<>"",Bitacora_2[[#This Row],[ATA DOC]]=""),"In transit", IF(AND(Bitacora_2[[#This Row],[ETD Doc]]<>"",Bitacora_2[[#This Row],[ATA DOC]]<>""),"Delivered",""))))) -> Delivered | AQ8: =IF(I8="SEA",IF(AP8="","On Hold","Released"),"")
A9: PO00000050807HFPEARANCONVOERU4327243 | B9: 22 | C9: 46168 | D9: 26 | E9: LATAM | F9: CLSAI | G9: PE | H9: HFPE | I9: SEA | J9: ARAN | K9: CONV | L9: PO00000050807 | M9: OERU4327243 | N9: HORTIFRUT COMERCIAL S.A. | O9: HORTIFRUT CHILE | P9: COSCO | Q9: COSCO MALAYSIA 109W | R9: 46189 | S9: 46194 | T9: NWT | U9: =+IF(Bitacora_2[[#This Row],[ATA DOC]]<>"",Bitacora_2[[#This Row],[ATA DOC]], IF(Bitacora_2[[#This Row],[Clase Expedición]]="AIR",Bitacora_2[[#This Row],[ETD Real]], IF(AND(Bitacora_2[[#This Row],[Clase Expedición]]="SEA",Bitacora_2[[#This Row],[Mercado]]="LATAM"), Bitacora_2[[#This Row],[ETD Real]]+3, IF(AND(Bitacora_2[[#This Row],[Clase Expedición]]="SEA",Bitacora_2[[#This Row],[Mercado]]="EUROPE"), Bitacora_2[[#This Row],[ETD Real]]+8, IF(AND(Bitacora_2[[#This Row],[Clase Expedición]]="SEA",Bitacora_2[[#This Row],[Mercado]]="UK"), Bitacora_2[[#This Row],[ETD Real]]+11, IF(AND(Bitacora_2[[#This Row],[Clase Expedición]]="SEA",OR(Bitacora_2[[#This Row],[Mercado]]="ASIA",Bitacora_2[[#This Row],[Mercado]]="ASIA CN + HK")), Bitacora_2[[#This Row],[ETD Real]]+14, IF(AND(Bitacora_2[[#This Row],[Clase Expedición]]="SEA",OR(Bitacora_2[[#This Row],[Mercado]]="US EAST",Bitacora_2[[#This Row],[Mercado]]="US WEST",Bitacora_2[[#This Row],[Mercado]]="US SOUTH")), Bitacora_2[[#This Row],[ETD Real]]+8,""))))))) -> 46182 | V9: 46177 | W9: 46182 | X9: =IF(OR(Bitacora_2[[#This Row],[ETD Real]]="",Bitacora_2[[#This Row],[ETD Doc]]=""),"",Bitacora_2[[#This Row],[ETD Doc]]-Bitacora_2[[#This Row],[ETD Real]]) -> -12 | Y9: =IF(OR(Bitacora_2[[#This Row],[ATA DOC]]="",Bitacora_2[[#This Row],[ETA Real]]=""),"",Bitacora_2[[#This Row],[ETA Real]]-Bitacora_2[[#This Row],[ATA DOC]]) -> 12 | Z9: 2393622070 | AA9: X | AB9: X | AC9: X | AD9: X | AE9: X | AH9: X | AI9: =IF(AND(OR(E9="US EAST",E9="US WEST",E9="US SOUTH"),I9="SEA",Bitacora_2[[#This Row],[ETD Real]]-TODAY()>=3,Bitacora_2[[#This Row],[ISF]]<>"X"),"Pending", IF(AND(OR(E9="US EAST",E9="US WEST",E9="US SOUTH"),I9="SEA",Bitacora_2[[#This Row],[ETD Real]]-TODAY()=2,Bitacora_2[[#This Row],[ISF]]<>"X"),"Urgente", IF(AND(OR(E9="US EAST",E9="US WEST",E9="US SOUTH"),I9="SEA",Bitacora_2[[#This Row],[ETD Real]]-TODAY()<=1,Bitacora_2[[#This Row],[ISF]]<>"X"),"Muy Urgente", IF(AND(OR(E9="US EAST",E9="US WEST",E9="US SOUTH"),I9="SEA",Bitacora_2[[#This Row],[ISF]]="X"),"Sent","")))) | AJ9: =IF(AND(OR(Bitacora_2[[#This Row],[Clase Expedición]]="AIR",Bitacora_2[[#This Row],[Clase Expedición]]="TRK")),"Complete", IF(AND(Bitacora_2[[#This Row],[Mercado]]="LATAM",COUNTA(Bitacora_2[[#This Row],[PHYTO]:[ISF]],Bitacora_2[[#This Row],[CO]])=7,Bitacora_2[[#This Row],[Clase Expedición]]<>"TRK"), "Complete", IF(AND(Bitacora_2[[#This Row],[Mercado]]="LATAM",COUNTA(Bitacora_2[[#This Row],[PHYTO]:[PL ]],Bitacora_2[[#This Row],[CO]])=6,Bitacora_2[[#This Row],[Clase Expedición]]="SEA"), "Complete", IF(AND(OR(Bitacora_2[[#This Row],[Mercado]]="EUROPE",Bitacora_2[[#This Row],[Mercado]]="UK"),COUNTA(Bitacora_2[[#This Row],[PHYTO]],Bitacora_2[[#This Row],[INVOICE]:[PL ]],Bitacora_2[[#This Row],[COI]])=5,Bitacora_2[[#This Row],[Clase Expedición]]="SEA",Bitacora_2[[#This Row],[Manejo]]="ORG"), "Complete", IF(AND(OR(Bitacora_2[[#This Row],[Mercado]]="EUROPE",Bitacora_2[[#This Row],[Mercado]]="UK"),COUNTA(Bitacora_2[[#This Row],[PHYTO]],Bitacora_2[[#This Row],[INVOICE]:[PL ]])=4,Bitacora_2[[#This Row],[Clase Expedición]]="SEA",Bitacora_2[[#This Row],[Manejo]]="CONV"), "Complete", IF(AND(OR(Bitacora_2[[#This Row],[Mercado]]="US WEST",Bitacora_2[[#This Row],[Mercado]]="US EAST",Bitacora_2[[#This Row],[Mercado]]="US SOUTH"),COUNTA(Bitacora_2[[#This Row],[PHYTO]:[ISF]],Bitacora_2[[#This Row],[CO]])=7,Bitacora_2[[#This Row],[Clase Expedición]]="SEA",Bitacora_2[[#This Row],[Exportador]]="ECHF"), "Complete", IF(AND(OR(Bitacora_2[[#This Row],[Mercado]]="US WEST",Bitacora_2[[#This Row],[Mercado]]="US EAST",Bitacora_2[[#This Row],[Mercado]]="US SOUTH"),COUNTA(Bitacora_2[[#This Row],[PHYTO]:[ISF]])=6,Bitacora_2[[#This Row],[Clase Expedición]]="SEA",Bitacora_2[[#This Row],[Exportador]]<>"ECHF"), "Complete", IF(AND(OR(Bitacora_2[[#This Row],[Mercado]]="ASIA",Bitacora_2[[#This Row],[Mercado]]="ASIA CN + HK"),COUNTA(Bitacora_2[[#This Row],[PHYTO]:[PL ]],Bitacora_2[[#This Row],[CO]])=6), "Complete","Incomplete")))))))) -> Complete | AM9: =+IF(OR(Bitacora_2[[#This Row],[Exportador]]="INVERSIONES JORDIE",Bitacora_2[[#This Row],[Exportador]]="TAL S.A."), "Tercero", "Propio") -> Propio | AN9: =IF(AND(Bitacora_2[[#This Row],[Clase Expedición]]="AIR",OR(Bitacora_2[[#This Row],[Mercado]]="US EAST",Bitacora_2[[#This Row],[Mercado]]="US WEST",Bitacora_2[[#This Row],[Mercado]]="US SOUTH")),IF(Bitacora_2[[#This Row],[ETD Doc]]<>"","Delivered","Pending"), IF(Bitacora_2[[#This Row],[Clase Expedición]]="AIR","Delivered", IF(AND(Bitacora_2[[#This Row],[ETD Doc]]="",Bitacora_2[[#This Row],[ATA DOC]]=""),"Pending", IF(AND(Bitacora_2[[#This Row],[ETD Doc]]<>"",Bitacora_2[[#This Row],[ATA DOC]]=""),"In transit", IF(AND(Bitacora_2[[#This Row],[ETD Doc]]<>"",Bitacora_2[[#This Row],[ATA DOC]]<>""),"Delivered",""))))) -> Delivered | AO9: Released | AP9: 46204 | AQ9: =IF(I9="SEA",IF(AP9="","On Hold","Released"),"") -> Released | AR9: Demora en revisión de reporte (COSCO + SAG)
A10: RH|0002TTAL S.A.ARANCONVBMOU9893760 | B10: 22 | C10: 46170 | D10: 25 | E10: US EAST | F10: USPHL | G10: PE | H10: TAL S.A. | I10: SEA | J10: ARAN | K10: CONV | L10: RH|0002T | M10: BMOU9893760 | O10: NRF TIER I | P10: CITIKOLD | Q10: SEABOARD VALOR | R10: 46174 | S10: 46188 | U10: =+IF(Bitacora_2[[#This Row],[ATA DOC]]<>"",Bitacora_2[[#This Row],[ATA DOC]], IF(Bitacora_2[[#This Row],[Clase Expedición]]="AIR",Bitacora_2[[#This Row],[ETD Real]], IF(AND(Bitacora_2[[#This Row],[Clase Expedición]]="SEA",Bitacora_2[[#This Row],[Mercado]]="LATAM"), Bitacora_2[[#This Row],[ETD Real]]+3, IF(AND(Bitacora_2[[#This Row],[Clase Expedición]]="SEA",Bitacora_2[[#This Row],[Mercado]]="EUROPE"), Bitacora_2[[#This Row],[ETD Real]]+8, IF(AND(Bitacora_2[[#This Row],[Clase Expedición]]="SEA",Bitacora_2[[#This Row],[Mercado]]="UK"), Bitacora_2[[#This Row],[ETD Real]]+11, IF(AND(Bitacora_2[[#This Row],[Clase Expedición]]="SEA",OR(Bitacora_2[[#This Row],[Mercado]]="ASIA",Bitacora_2[[#This Row],[Mercado]]="ASIA CN + HK")), Bitacora_2[[#This Row],[ETD Real]]+14, IF(AND(Bitacora_2[[#This Row],[Clase Expedición]]="SEA",OR(Bitacora_2[[#This Row],[Mercado]]="US EAST",Bitacora_2[[#This Row],[Mercado]]="US WEST",Bitacora_2[[#This Row],[Mercado]]="US SOUTH")), Bitacora_2[[#This Row],[ETD Real]]+8,""))))))) -> 46178 | V10: 46178 | W10: 46178 | X10: =IF(OR(Bitacora_2[[#This Row],[ETD Real]]="",Bitacora_2[[#This Row],[ETD Doc]]=""),"",Bitacora_2[[#This Row],[ETD Doc]]-Bitacora_2[[#This Row],[ETD Real]]) -> 4 | Y10: =IF(OR(Bitacora_2[[#This Row],[ATA DOC]]="",Bitacora_2[[#This Row],[ETA Real]]=""),"",Bitacora_2[[#This Row],[ETA Real]]-Bitacora_2[[#This Row],[ATA DOC]]) -> 10 | Z10: - | AA10: X | AB10: X | AC10: X | AD10: X | AE10: X | AF10: x | AI10: =IF(AND(OR(E10="US EAST",E10="US WEST",E10="US SOUTH"),I10="SEA",Bitacora_2[[#This Row],[ETD Real]]-TODAY()>=3,Bitacora_2[[#This Row],[ISF]]<>"X"),"Pending", IF(AND(OR(E10="US EAST",E10="US WEST",E10="US SOUTH"),I10="SEA",Bitacora_2[[#This Row],[ETD Real]]-TODAY()=2,Bitacora_2[[#This Row],[ISF]]<>"X"),"Urgente", IF(AND(OR(E10="US EAST",E10="US WEST",E10="US SOUTH"),I10="SEA",Bitacora_2[[#This Row],[ETD Real]]-TODAY()<=1,Bitacora_2[[#This Row],[ISF]]<>"X"),"Muy Urgente", IF(AND(OR(E10="US EAST",E10="US WEST",E10="US SOUTH"),I10="SEA",Bitacora_2[[#This Row],[ISF]]="X"),"Sent","")))) -> Sent | AJ10: =IF(AND(OR(Bitacora_2[[#This Row],[Clase Expedición]]="AIR",Bitacora_2[[#This Row],[Clase Expedición]]="TRK")),"Complete", IF(AND(Bitacora_2[[#This Row],[Mercado]]="LATAM",COUNTA(Bitacora_2[[#This Row],[PHYTO]:[ISF]],Bitacora_2[[#This Row],[CO]])=7,Bitacora_2[[#This Row],[Clase Expedición]]<>"TRK"), "Complete", IF(AND(Bitacora_2[[#This Row],[Mercado]]="LATAM",COUNTA(Bitacora_2[[#This Row],[PHYTO]:[PL ]],Bitacora_2[[#This Row],[CO]])=6,Bitacora_2[[#This Row],[Clase Expedición]]="SEA"), "Complete", IF(AND(OR(Bitacora_2[[#This Row],[Mercado]]="EUROPE",Bitacora_2[[#This Row],[Mercado]]="UK"),COUNTA(Bitacora_2[[#This Row],[PHYTO]],Bitacora_2[[#This Row],[INVOICE]:[PL ]],Bitacora_2[[#This Row],[COI]])=5,Bitacora_2[[#This Row],[Clase Expedición]]="SEA",Bitacora_2[[#This Row],[Manejo]]="ORG"), "Complete", IF(AND(OR(Bitacora_2[[#This Row],[Mercado]]="EUROPE",Bitacora_2[[#This Row],[Mercado]]="UK"),COUNTA(Bitacora_2[[#This Row],[PHYTO]],Bitacora_2[[#This Row],[INVOICE]:[PL ]])=4,Bitacora_2[[#This Row],[Clase Expedición]]="SEA",Bitacora_2[[#This Row],[Manejo]]="CONV"), "Complete", IF(AND(OR(Bitacora_2[[#This Row],[Mercado]]="US WEST",Bitacora_2[[#This Row],[Mercado]]="US EAST",Bitacora_2[[#This Row],[Mercado]]="US SOUTH"),COUNTA(Bitacora_2[[#This Row],[PHYTO]:[ISF]],Bitacora_2[[#This Row],[CO]])=7,Bitacora_2[[#This Row],[Clase Expedición]]="SEA",Bitacora_2[[#This Row],[Exportador]]="ECHF"), "Complete", IF(AND(OR(Bitacora_2[[#This Row],[Mercado]]="US WEST",Bitacora_2[[#This Row],[Mercado]]="US EAST",Bitacora_2[[#This Row],[Mercado]]="US SOUTH"),COUNTA(Bitacora_2[[#This Row],[PHYTO]:[ISF]])=6,Bitacora_2[[#This Row],[Clase Expedición]]="SEA",Bitacora_2[[#This Row],[Exportador]]<>"ECHF"), "Complete", IF(AND(OR(Bitacora_2[[#This Row],[Mercado]]="ASIA",Bitacora_2[[#This Row],[Mercado]]="ASIA CN + HK"),COUNTA(Bitacora_2[[#This Row],[PHYTO]:[PL ]],Bitacora_2[[#This Row],[CO]])=6), "Complete","Incomplete")))))))) -> Complete | AM10: =+IF(OR(Bitacora_2[[#This Row],[Exportador]]="INVERSIONES JORDIE",Bitacora_2[[#This Row],[Exportador]]="TAL S.A."), "Tercero", "Propio") -> Tercero | AN10: =IF(AND(Bitacora_2[[#This Row],[Clase Expedición]]="AIR",OR(Bitacora_2[[#This Row],[Mercado]]="US EAST",Bitacora_2[[#This Row],[Mercado]]="US WEST",Bitacora_2[[#This Row],[Mercado]]="US SOUTH")),IF(Bitacora_2[[#This Row],[ETD Doc]]<>"","Delivered","Pending"), IF(Bitacora_2[[#This Row],[Clase Expedición]]="AIR","Delivered", IF(AND(Bitacora_2[[#This Row],[ETD Doc]]="",Bitacora_2[[#This Row],[ATA DOC]]=""),"Pending", IF(AND(Bitacora_2[[#This Row],[ETD Doc]]<>"",Bitacora_2[[#This Row],[ATA DOC]]=""),"In transit", IF(AND(Bitacora_2[[#This Row],[ETD Doc]]<>"",Bitacora_2[[#This Row],[ATA DOC]]<>""),"Delivered",""))))) -> Delivered | AO10: Released | AP10: 46185 | AQ10: =IF(I10="SEA",IF(AP10="","On Hold","Released"),"") -> Released
A11: PO00000050909TTAL S.A.ARANCONVSZLU9302534 | B11: 22 | C11: 46171 | D11: 25 | E11: US EAST | F11: USPHL | G11: PE | H11: TAL S.A. | I11: SEA | J11: ARAN | K11: CONV | L11: PO00000050909T | M11: SZLU9302534 | O11: NRF TIER I | P11: CITIKOLD | Q11: SEABOARD VALOR | R11: 46177 | S11: 46188 | U11: =+IF(Bitacora_2[[#This Row],[ATA DOC]]<>"",Bitacora_2[[#This Row],[ATA DOC]], IF(Bitacora_2[[#This Row],[Clase Expedición]]="AIR",Bitacora_2[[#This Row],[ETD Real]], IF(AND(Bitacora_2[[#This Row],[Clase Expedición]]="SEA",Bitacora_2[[#This Row],[Mercado]]="LATAM"), Bitacora_2[[#This Row],[ETD Real]]+3, IF(AND(Bitacora_2[[#This Row],[Clase Expedición]]="SEA",Bitacora_2[[#This Row],[Mercado]]="EUROPE"), Bitacora_2[[#This Row],[ETD Real]]+8, IF(AND(Bitacora_2[[#This Row],[Clase Expedición]]="SEA",Bitacora_2[[#This Row],[Mercado]]="UK"), Bitacora_2[[#This Row],[ETD Real]]+11, IF(AND(Bitacora_2[[#This Row],[Clase Expedición]]="SEA",OR(Bitacora_2[[#This Row],[Mercado]]="ASIA",Bitacora_2[[#This Row],[Mercado]]="ASIA CN + HK")), Bitacora_2[[#This Row],[ETD Real]]+14, IF(AND(Bitacora_2[[#This Row],[Clase Expedición]]="SEA",OR(Bitacora_2[[#This Row],[Mercado]]="US EAST",Bitacora_2[[#This Row],[Mercado]]="US WEST",Bitacora_2[[#This Row],[Mercado]]="US SOUTH")), Bitacora_2[[#This Row],[ETD Real]]+8,""))))))) -> 46178 | V11: 46178 | W11: 46178 | X11: =IF(OR(Bitacora_2[[#This Row],[ETD Real]]="",Bitacora_2[[#This Row],[ETD Doc]]=""),"",Bitacora_2[[#This Row],[ETD Doc]]-Bitacora_2[[#This Row],[ETD Real]]) -> 1 | Y11: =IF(OR(Bitacora_2[[#This Row],[ATA DOC]]="",Bitacora_2[[#This Row],[ETA Real]]=""),"",Bitacora_2[[#This Row],[ETA Real]]-Bitacora_2[[#This Row],[ATA DOC]]) -> 10 | Z11: - | AA11: X | AB11: X | AC11: X | AD11: X | AE11: X | AF11: x | AI11: =IF(AND(OR(E11="US EAST",E11="US WEST",E11="US SOUTH"),I11="SEA",Bitacora_2[[#This Row],[ETD Real]]-TODAY()>=3,Bitacora_2[[#This Row],[ISF]]<>"X"),"Pending", IF(AND(OR(E11="US EAST",E11="US WEST",E11="US SOUTH"),I11="SEA",Bitacora_2[[#This Row],[ETD Real]]-TODAY()=2,Bitacora_2[[#This Row],[ISF]]<>"X"),"Urgente", IF(AND(OR(E11="US EAST",E11="US WEST",E11="US SOUTH"),I11="SEA",Bitacora_2[[#This Row],[ETD Real]]-TODAY()<=1,Bitacora_2[[#This Row],[ISF]]<>"X"),"Muy Urgente", IF(AND(OR(E11="US EAST",E11="US WEST",E11="US SOUTH"),I11="SEA",Bitacora_2[[#This Row],[ISF]]="X"),"Sent","")))) -> Sent | AJ11: =IF(AND(OR(Bitacora_2[[#This Row],[Clase Expedición]]="AIR",Bitacora_2[[#This Row],[Clase Expedición]]="TRK")),"Complete", IF(AND(Bitacora_2[[#This Row],[Mercado]]="LATAM",COUNTA(Bitacora_2[[#This Row],[PHYTO]:[ISF]],Bitacora_2[[#This Row],[CO]])=7,Bitacora_2[[#This Row],[Clase Expedición]]<>"TRK"), "Complete", IF(AND(Bitacora_2[[#This Row],[Mercado]]="LATAM",COUNTA(Bitacora_2[[#This Row],[PHYTO]:[PL ]],Bitacora_2[[#This Row],[CO]])=6,Bitacora_2[[#This Row],[Clase Expedición]]="SEA"), "Complete", IF(AND(OR(Bitacora_2[[#This Row],[Mercado]]="EUROPE",Bitacora_2[[#This Row],[Mercado]]="UK"),COUNTA(Bitacora_2[[#This Row],[PHYTO]],Bitacora_2[[#This Row],[INVOICE]:[PL ]],Bitacora_2[[#This Row],[COI]])=5,Bitacora_2[[#This Row],[Clase Expedición]]="SEA",Bitacora_2[[#This Row],[Manejo]]="ORG"), "Complete", IF(AND(OR(Bitacora_2[[#This Row],[Mercado]]="EUROPE",Bitacora_2[[#This Row],[Mercado]]="UK"),COUNTA(Bitacora_2[[#This Row],[PHYTO]],Bitacora_2[[#This Row],[INVOICE]:[PL ]])=4,Bitacora_2[[#This Row],[Clase Expedición]]="SEA",Bitacora_2[[#This Row],[Manejo]]="CONV"), "Complete", IF(AND(OR(Bitacora_2[[#This Row],[Mercado]]="US WEST",Bitacora_2[[#This Row],[Mercado]]="US EAST",Bitacora_2[[#This Row],[Mercado]]="US SOUTH"),COUNTA(Bitacora_2[[#This Row],[PHYTO]:[ISF]],Bitacora_2[[#This Row],[CO]])=7,Bitacora_2[[#This Row],[Clase Expedición]]="SEA",Bitacora_2[[#This Row],[Exportador]]="ECHF"), "Complete", IF(AND(OR(Bitacora_2[[#This Row],[Mercado]]="US WEST",Bitacora_2[[#This Row],[Mercado]]="US EAST",Bitacora_2[[#This Row],[Mercado]]="US SOUTH"),COUNTA(Bitacora_2[[#This Row],[PHYTO]:[ISF]])=6,Bitacora_2[[#This Row],[Clase Expedición]]="SEA",Bitacora_2[[#This Row],[Exportador]]<>"ECHF"), "Complete", IF(AND(OR(Bitacora_2[[#This Row],[Mercado]]="ASIA",Bitacora_2[[#This Row],[Mercado]]="ASIA CN + HK"),COUNTA(Bitacora_2[[#This Row],[PHYTO]:[PL ]],Bitacora_2[[#This Row],[CO]])=6), "Complete","Incomplete")))))))) -> Complete | AM11: =+IF(OR(Bitacora_2[[#This Row],[Exportador]]="INVERSIONES JORDIE",Bitacora_2[[#This Row],[Exportador]]="TAL S.A."), "Tercero", "Propio") -> Tercero | AN11: =IF(AND(Bitacora_2[[#This Row],[Clase Expedición]]="AIR",OR(Bitacora_2[[#This Row],[Mercado]]="US EAST",Bitacora_2[[#This Row],[Mercado]]="US WEST",Bitacora_2[[#This Row],[Mercado]]="US SOUTH")),IF(Bitacora_2[[#This Row],[ETD Doc]]<>"","Delivered","Pending"), IF(Bitacora_2[[#This Row],[Clase Expedición]]="AIR","Delivered", IF(AND(Bitacora_2[[#This Row],[ETD Doc]]="",Bitacora_2[[#This Row],[ATA DOC]]=""),"Pending", IF(AND(Bitacora_2[[#This Row],[ETD Doc]]<>"",Bitacora_2[[#This Row],[ATA DOC]]=""),"In transit", IF(AND(Bitacora_2[[#This Row],[ETD Doc]]<>"",Bitacora_2[[#This Row],[ATA DOC]]<>""),"Delivered",""))))) -> Delivered | AO11: Released | AP11: 46185 | AQ11: =IF(I11="SEA",IF(AP11="","On Hold","Released"),"") -> Released
A12: PO00000050870HFPEARANCONV145-11634044 | B12: 22 | C12: 46172 | D12: 23 | E12: LATAM | F12: BOG | G12: PE | H12: HFPE | I12: AIR | J12: ARAN | K12: CONV | L12: PO00000050870 | M12: 145-11634044 | N12: HORTIFRUT COLOMBIA SAS | O12: HORTIFRUT COLOMBIA | Q12: 24 | R12: 46177 | S12: 46177 | T12: HELLMANN | U12: =+IF(Bitacora_2[[#This Row],[ATA DOC]]<>"",Bitacora_2[[#This Row],[ATA DOC]], IF(Bitacora_2[[#This Row],[Clase Expedición]]="AIR",Bitacora_2[[#This Row],[ETD Real]], IF(AND(Bitacora_2[[#This Row],[Clase Expedición]]="SEA",Bitacora_2[[#This Row],[Mercado]]="LATAM"), Bitacora_2[[#This Row],[ETD Real]]+3, IF(AND(Bitacora_2[[#This Row],[Clase Expedición]]="SEA",Bitacora_2[[#This Row],[Mercado]]="EUROPE"), Bitacora_2[[#This Row],[ETD Real]]+8, IF(AND(Bitacora_2[[#This Row],[Clase Expedición]]="SEA",Bitacora_2[[#This Row],[Mercado]]="UK"), Bitacora_2[[#This Row],[ETD Real]]+11, IF(AND(Bitacora_2[[#This Row],[Clase Expedición]]="SEA",OR(Bitacora_2[[#This Row],[Mercado]]="ASIA",Bitacora_2[[#This Row],[Mercado]]="ASIA CN + HK")), Bitacora_2[[#This Row],[ETD Real]]+14, IF(AND(Bitacora_2[[#This Row],[Clase Expedición]]="SEA",OR(Bitacora_2[[#This Row],[Mercado]]="US EAST",Bitacora_2[[#This Row],[Mercado]]="US WEST",Bitacora_2[[#This Row],[Mercado]]="US SOUTH")), Bitacora_2[[#This Row],[ETD Real]]+8,""))))))) -> 46177 | X12: =IF(OR(Bitacora_2[[#This Row],[ETD Real]]="",Bitacora_2[[#This Row],[ETD Doc]]=""),"",Bitacora_2[[#This Row],[ETD Doc]]-Bitacora_2[[#This Row],[ETD Real]]) | Y12: =IF(OR(Bitacora_2[[#This Row],[ATA DOC]]="",Bitacora_2[[#This Row],[ETA Real]]=""),"",Bitacora_2[[#This Row],[ETA Real]]-Bitacora_2[[#This Row],[ATA DOC]]) | AI12: =IF(AND(OR(E12="US EAST",E12="US WEST",E12="US SOUTH"),I12="SEA",Bitacora_2[[#This Row],[ETD Real]]-TODAY()>=3,Bitacora_2[[#This Row],[ISF]]<>"X"),"Pending", IF(AND(OR(E12="US EAST",E12="US WEST",E12="US SOUTH"),I12="SEA",Bitacora_2[[#This Row],[ETD Real]]-TODAY()=2,Bitacora_2[[#This Row],[ISF]]<>"X"),"Urgente", IF(AND(OR(E12="US EAST",E12="US WEST",E12="US SOUTH"),I12="SEA",Bitacora_2[[#This Row],[ETD Real]]-TODAY()<=1,Bitacora_2[[#This Row],[ISF]]<>"X"),"Muy Urgente", IF(AND(OR(E12="US EAST",E12="US WEST",E12="US SOUTH"),I12="SEA",Bitacora_2[[#This Row],[ISF]]="X"),"Sent","")))) | AJ12: =IF(AND(OR(Bitacora_2[[#This Row],[Clase Expedición]]="AIR",Bitacora_2[[#This Row],[Clase Expedición]]="TRK")),"Complete", IF(AND(Bitacora_2[[#This Row],[Mercado]]="LATAM",COUNTA(Bitacora_2[[#This Row],[PHYTO]:[ISF]],Bitacora_2[[#This Row],[CO]])=7,Bitacora_2[[#This Row],[Clase Expedición]]<>"TRK"), "Complete", IF(AND(Bitacora_2[[#This Row],[Mercado]]="LATAM",COUNTA(Bitacora_2[[#This Row],[PHYTO]:[PL ]],Bitacora_2[[#This Row],[CO]])=6,Bitacora_2[[#This Row],[Clase Expedición]]="SEA"), "Complete", IF(AND(OR(Bitacora_2[[#This Row],[Mercado]]="EUROPE",Bitacora_2[[#This Row],[Mercado]]="UK"),COUNTA(Bitacora_2[[#This Row],[PHYTO]],Bitacora_2[[#This Row],[INVOICE]:[PL ]],Bitacora_2[[#This Row],[COI]])=5,Bitacora_2[[#This Row],[Clase Expedición]]="SEA",Bitacora_2[[#This Row],[Manejo]]="ORG"), "Complete", IF(AND(OR(Bitacora_2[[#This Row],[Mercado]]="EUROPE",Bitacora_2[[#This Row],[Mercado]]="UK"),COUNTA(Bitacora_2[[#This Row],[PHYTO]],Bitacora_2[[#This Row],[INVOICE]:[PL ]])=4,Bitacora_2[[#This Row],[Clase Expedición]]="SEA",Bitacora_2[[#This Row],[Manejo]]="CONV"), "Complete", IF(AND(OR(Bitacora_2[[#This Row],[Mercado]]="US WEST",Bitacora_2[[#This Row],[Mercado]]="US EAST",Bitacora_2[[#This Row],[Mercado]]="US SOUTH"),COUNTA(Bitacora_2[[#This Row],[PHYTO]:[ISF]],Bitacora_2[[#This Row],[CO]])=7,Bitacora_2[[#This Row],[Clase Expedición]]="SEA",Bitacora_2[[#This Row],[Exportador]]="ECHF"), "Complete", IF(AND(OR(Bitacora_2[[#This Row],[Mercado]]="US WEST",Bitacora_2[[#This Row],[Mercado]]="US EAST",Bitacora_2[[#This Row],[Mercado]]="US SOUTH"),COUNTA(Bitacora_2[[#This Row],[PHYTO]:[ISF]])=6,Bitacora_2[[#This Row],[Clase Expedición]]="SEA",Bitacora_2[[#This Row],[Exportador]]<>"ECHF"), "Complete", IF(AND(OR(Bitacora_2[[#This Row],[Mercado]]="ASIA",Bitacora_2[[#This Row],[Mercado]]="ASIA CN + HK"),COUNTA(Bitacora_2[[#This Row],[PHYTO]:[PL ]],Bitacora_2[[#This Row],[CO]])=6), "Complete","Incomplete")))))))) -> Complete | AM12: =+IF(OR(Bitacora_2[[#This Row],[Exportador]]="INVERSIONES JORDIE",Bitacora_2[[#This Row],[Exportador]]="TAL S.A."), "Tercero", "Propio") -> Propio | AN12: =IF(AND(Bitacora_2[[#This Row],[Clase Expedición]]="AIR",OR(Bitacora_2[[#This Row],[Mercado]]="US EAST",Bitacora_2[[#This Row],[Mercado]]="US WEST",Bitacora_2[[#This Row],[Mercado]]="US SOUTH")),IF(Bitacora_2[[#This Row],[ETD Doc]]<>"","Delivered","Pending"), IF(Bitacora_2[[#This Row],[Clase Expedición]]="AIR","Delivered", IF(AND(Bitacora_2[[#This Row],[ETD Doc]]="",Bitacora_2[[#This Row],[ATA DOC]]=""),"Pending", IF(AND(Bitacora_2[[#This Row],[ETD Doc]]<>"",Bitacora_2[[#This Row],[ATA DOC]]=""),"In transit", IF(AND(Bitacora_2[[#This Row],[ETD Doc]]<>"",Bitacora_2[[#This Row],[ATA DOC]]<>""),"Delivered",""))))) -> Delivered | AQ12: =IF(I12="SEA",IF(AP12="","On Hold","Released"),"")
A13: PO00000050871HFPEARANCONV145-11634055 | B13: 22 | C13: 46172 | D13: 23 | E13: LATAM | F13: BOG | G13: PE | H13: HFPE | I13: AIR | J13: ARAN | K13: CONV | L13: PO00000050871 | M13: 145-11634055 | N13: HORTIFRUT COLOMBIA SAS | O13: HORTIFRUT COLOMBIA | Q13: 24 | R13: 46177 | S13: 46177 | T13: HELLMANN | U13: =+IF(Bitacora_2[[#This Row],[ATA DOC]]<>"",Bitacora_2[[#This Row],[ATA DOC]], IF(Bitacora_2[[#This Row],[Clase Expedición]]="AIR",Bitacora_2[[#This Row],[ETD Real]], IF(AND(Bitacora_2[[#This Row],[Clase Expedición]]="SEA",Bitacora_2[[#This Row],[Mercado]]="LATAM"), Bitacora_2[[#This Row],[ETD Real]]+3, IF(AND(Bitacora_2[[#This Row],[Clase Expedición]]="SEA",Bitacora_2[[#This Row],[Mercado]]="EUROPE"), Bitacora_2[[#This Row],[ETD Real]]+8, IF(AND(Bitacora_2[[#This Row],[Clase Expedición]]="SEA",Bitacora_2[[#This Row],[Mercado]]="UK"), Bitacora_2[[#This Row],[ETD Real]]+11, IF(AND(Bitacora_2[[#This Row],[Clase Expedición]]="SEA",OR(Bitacora_2[[#This Row],[Mercado]]="ASIA",Bitacora_2[[#This Row],[Mercado]]="ASIA CN + HK")), Bitacora_2[[#This Row],[ETD Real]]+14, IF(AND(Bitacora_2[[#This Row],[Clase Expedición]]="SEA",OR(Bitacora_2[[#This Row],[Mercado]]="US EAST",Bitacora_2[[#This Row],[Mercado]]="US WEST",Bitacora_2[[#This Row],[Mercado]]="US SOUTH")), Bitacora_2[[#This Row],[ETD Real]]+8,""))))))) -> 46177 | X13: =IF(OR(Bitacora_2[[#This Row],[ETD Real]]="",Bitacora_2[[#This Row],[ETD Doc]]=""),"",Bitacora_2[[#This Row],[ETD Doc]]-Bitacora_2[[#This Row],[ETD Real]]) | Y13: =IF(OR(Bitacora_2[[#This Row],[ATA DOC]]="",Bitacora_2[[#This Row],[ETA Real]]=""),"",Bitacora_2[[#This Row],[ETA Real]]-Bitacora_2[[#This Row],[ATA DOC]]) | AI13: =IF(AND(OR(E13="US EAST",E13="US WEST",E13="US SOUTH"),I13="SEA",Bitacora_2[[#This Row],[ETD Real]]-TODAY()>=3,Bitacora_2[[#This Row],[ISF]]<>"X"),"Pending", IF(AND(OR(E13="US EAST",E13="US WEST",E13="US SOUTH"),I13="SEA",Bitacora_2[[#This Row],[ETD Real]]-TODAY()=2,Bitacora_2[[#This Row],[ISF]]<>"X"),"Urgente", IF(AND(OR(E13="US EAST",E13="US WEST",E13="US SOUTH"),I13="SEA",Bitacora_2[[#This Row],[ETD Real]]-TODAY()<=1,Bitacora_2[[#This Row],[ISF]]<>"X"),"Muy Urgente", IF(AND(OR(E13="US EAST",E13="US WEST",E13="US SOUTH"),I13="SEA",Bitacora_2[[#This Row],[ISF]]="X"),"Sent","")))) | AJ13: =IF(AND(OR(Bitacora_2[[#This Row],[Clase Expedición]]="AIR",Bitacora_2[[#This Row],[Clase Expedición]]="TRK")),"Complete", IF(AND(Bitacora_2[[#This Row],[Mercado]]="LATAM",COUNTA(Bitacora_2[[#This Row],[PHYTO]:[ISF]],Bitacora_2[[#This Row],[CO]])=7,Bitacora_2[[#This Row],[Clase Expedición]]<>"TRK"), "Complete", IF(AND(Bitacora_2[[#This Row],[Mercado]]="LATAM",COUNTA(Bitacora_2[[#This Row],[PHYTO]:[PL ]],Bitacora_2[[#This Row],[CO]])=6,Bitacora_2[[#This Row],[Clase Expedición]]="SEA"), "Complete", IF(AND(OR(Bitacora_2[[#This Row],[Mercado]]="EUROPE",Bitacora_2[[#This Row],[Mercado]]="UK"),COUNTA(Bitacora_2[[#This Row],[PHYTO]],Bitacora_2[[#This Row],[INVOICE]:[PL ]],Bitacora_2[[#This Row],[COI]])=5,Bitacora_2[[#This Row],[Clase Expedición]]="SEA",Bitacora_2[[#This Row],[Manejo]]="ORG"), "Complete", IF(AND(OR(Bitacora_2[[#This Row],[Mercado]]="EUROPE",Bitacora_2[[#This Row],[Mercado]]="UK"),COUNTA(Bitacora_2[[#This Row],[PHYTO]],Bitacora_2[[#This Row],[INVOICE]:[PL ]])=4,Bitacora_2[[#This Row],[Clase Expedición]]="SEA",Bitacora_2[[#This Row],[Manejo]]="CONV"), "Complete", IF(AND(OR(Bitacora_2[[#This Row],[Mercado]]="US WEST",Bitacora_2[[#This Row],[Mercado]]="US EAST",Bitacora_2[[#This Row],[Mercado]]="US SOUTH"),COUNTA(Bitacora_2[[#This Row],[PHYTO]:[ISF]],Bitacora_2[[#This Row],[CO]])=7,Bitacora_2[[#This Row],[Clase Expedición]]="SEA",Bitacora_2[[#This Row],[Exportador]]="ECHF"), "Complete", IF(AND(OR(Bitacora_2[[#This Row],[Mercado]]="US WEST",Bitacora_2[[#This Row],[Mercado]]="US EAST",Bitacora_2[[#This Row],[Mercado]]="US SOUTH"),COUNTA(Bitacora_2[[#This Row],[PHYTO]:[ISF]])=6,Bitacora_2[[#This Row],[Clase Expedición]]="SEA",Bitacora_2[[#This Row],[Exportador]]<>"ECHF"), "Complete", IF(AND(OR(Bitacora_2[[#This Row],[Mercado]]="ASIA",Bitacora_2[[#This Row],[Mercado]]="ASIA CN + HK"),COUNTA(Bitacora_2[[#This Row],[PHYTO]:[PL ]],Bitacora_2[[#This Row],[CO]])=6), "Complete","Incomplete")))))))) -> Complete | AM13: =+IF(OR(Bitacora_2[[#This Row],[Exportador]]="INVERSIONES JORDIE",Bitacora_2[[#This Row],[Exportador]]="TAL S.A."), "Tercero", "Propio") -> Propio | AN13: =IF(AND(Bitacora_2[[#This Row],[Clase Expedición]]="AIR",OR(Bitacora_2[[#This Row],[Mercado]]="US EAST",Bitacora_2[[#This Row],[Mercado]]="US WEST",Bitacora_2[[#This Row],[Mercado]]="US SOUTH")),IF(Bitacora_2[[#This Row],[ETD Doc]]<>"","Delivered","Pending"), IF(Bitacora_2[[#This Row],[Clase Expedición]]="AIR","Delivered", IF(AND(Bitacora_2[[#This Row],[ETD Doc]]="",Bitacora_2[[#This Row],[ATA DOC]]=""),"Pending", IF(AND(Bitacora_2[[#This Row],[ETD Doc]]<>"",Bitacora_2[[#This Row],[ATA DOC]]=""),"In transit", IF(AND(Bitacora_2[[#This Row],[ETD Doc]]<>"",Bitacora_2[[#This Row],[ATA DOC]]<>""),"Delivered",""))))) -> Delivered | AQ13: =IF(I13="SEA",IF(AP13="","On Hold","Released"),"")
A14: RH|0004TTAL S.A.ARANCONV145-12061501 | B14: 22 | C14: 46172 | D14: 23 | E14: LATAM | F14: BOG | G14: PE | H14: TAL S.A. | I14: AIR | J14: ARAN | K14: CONV | L14: RH|0004T | M14: 145-12061501 | O14: HORTIFRUT COLOMBIA SAS | P14: LATAM | R14: 46177 | S14: 46177 | U14: =+IF(Bitacora_2[[#This Row],[ATA DOC]]<>"",Bitacora_2[[#This Row],[ATA DOC]], IF(Bitacora_2[[#This Row],[Clase Expedición]]="AIR",Bitacora_2[[#This Row],[ETD Real]], IF(AND(Bitacora_2[[#This Row],[Clase Expedición]]="SEA",Bitacora_2[[#This Row],[Mercado]]="LATAM"), Bitacora_2[[#This Row],[ETD Real]]+3, IF(AND(Bitacora_2[[#This Row],[Clase Expedición]]="SEA",Bitacora_2[[#This Row],[Mercado]]="EUROPE"), Bitacora_2[[#This Row],[ETD Real]]+8, IF(AND(Bitacora_2[[#This Row],[Clase Expedición]]="SEA",Bitacora_2[[#This Row],[Mercado]]="UK"), Bitacora_2[[#This Row],[ETD Real]]+11, IF(AND(Bitacora_2[[#This Row],[Clase Expedición]]="SEA",OR(Bitacora_2[[#This Row],[Mercado]]="ASIA",Bitacora_2[[#This Row],[Mercado]]="ASIA CN + HK")), Bitacora_2[[#This Row],[ETD Real]]+14, IF(AND(Bitacora_2[[#This Row],[Clase Expedición]]="SEA",OR(Bitacora_2[[#This Row],[Mercado]]="US EAST",Bitacora_2[[#This Row],[Mercado]]="US WEST",Bitacora_2[[#This Row],[Mercado]]="US SOUTH")), Bitacora_2[[#This Row],[ETD Real]]+8,""))))))) -> 46177 | X14: =IF(OR(Bitacora_2[[#This Row],[ETD Real]]="",Bitacora_2[[#This Row],[ETD Doc]]=""),"",Bitacora_2[[#This Row],[ETD Doc]]-Bitacora_2[[#This Row],[ETD Real]]) | Y14: =IF(OR(Bitacora_2[[#This Row],[ATA DOC]]="",Bitacora_2[[#This Row],[ETA Real]]=""),"",Bitacora_2[[#This Row],[ETA Real]]-Bitacora_2[[#This Row],[ATA DOC]]) | AI14: =IF(AND(OR(E14="US EAST",E14="US WEST",E14="US SOUTH"),I14="SEA",Bitacora_2[[#This Row],[ETD Real]]-TODAY()>=3,Bitacora_2[[#This Row],[ISF]]<>"X"),"Pending", IF(AND(OR(E14="US EAST",E14="US WEST",E14="US SOUTH"),I14="SEA",Bitacora_2[[#This Row],[ETD Real]]-TODAY()=2,Bitacora_2[[#This Row],[ISF]]<>"X"),"Urgente", IF(AND(OR(E14="US EAST",E14="US WEST",E14="US SOUTH"),I14="SEA",Bitacora_2[[#This Row],[ETD Real]]-TODAY()<=1,Bitacora_2[[#This Row],[ISF]]<>"X"),"Muy Urgente", IF(AND(OR(E14="US EAST",E14="US WEST",E14="US SOUTH"),I14="SEA",Bitacora_2[[#This Row],[ISF]]="X"),"Sent","")))) | AJ14: =IF(AND(OR(Bitacora_2[[#This Row],[Clase Expedición]]="AIR",Bitacora_2[[#This Row],[Clase Expedición]]="TRK")),"Complete", IF(AND(Bitacora_2[[#This Row],[Mercado]]="LATAM",COUNTA(Bitacora_2[[#This Row],[PHYTO]:[ISF]],Bitacora_2[[#This Row],[CO]])=7,Bitacora_2[[#This Row],[Clase Expedición]]<>"TRK"), "Complete", IF(AND(Bitacora_2[[#This Row],[Mercado]]="LATAM",COUNTA(Bitacora_2[[#This Row],[PHYTO]:[PL ]],Bitacora_2[[#This Row],[CO]])=6,Bitacora_2[[#This Row],[Clase Expedición]]="SEA"), "Complete", IF(AND(OR(Bitacora_2[[#This Row],[Mercado]]="EUROPE",Bitacora_2[[#This Row],[Mercado]]="UK"),COUNTA(Bitacora_2[[#This Row],[PHYTO]],Bitacora_2[[#This Row],[INVOICE]:[PL ]],Bitacora_2[[#This Row],[COI]])=5,Bitacora_2[[#This Row],[Clase Expedición]]="SEA",Bitacora_2[[#This Row],[Manejo]]="ORG"), "Complete", IF(AND(OR(Bitacora_2[[#This Row],[Mercado]]="EUROPE",Bitacora_2[[#This Row],[Mercado]]="UK"),COUNTA(Bitacora_2[[#This Row],[PHYTO]],Bitacora_2[[#This Row],[INVOICE]:[PL ]])=4,Bitacora_2[[#This Row],[Clase Expedición]]="SEA",Bitacora_2[[#This Row],[Manejo]]="CONV"), "Complete", IF(AND(OR(Bitacora_2[[#This Row],[Mercado]]="US WEST",Bitacora_2[[#This Row],[Mercado]]="US EAST",Bitacora_2[[#This Row],[Mercado]]="US SOUTH"),COUNTA(Bitacora_2[[#This Row],[PHYTO]:[ISF]],Bitacora_2[[#This Row],[CO]])=7,Bitacora_2[[#This Row],[Clase Expedición]]="SEA",Bitacora_2[[#This Row],[Exportador]]="ECHF"), "Complete", IF(AND(OR(Bitacora_2[[#This Row],[Mercado]]="US WEST",Bitacora_2[[#This Row],[Mercado]]="US EAST",Bitacora_2[[#This Row],[Mercado]]="US SOUTH"),COUNTA(Bitacora_2[[#This Row],[PHYTO]:[ISF]])=6,Bitacora_2[[#This Row],[Clase Expedición]]="SEA",Bitacora_2[[#This Row],[Exportador]]<>"ECHF"), "Complete", IF(AND(OR(Bitacora_2[[#This Row],[Mercado]]="ASIA",Bitacora_2[[#This Row],[Mercado]]="ASIA CN + HK"),COUNTA(Bitacora_2[[#This Row],[PHYTO]:[PL ]],Bitacora_2[[#This Row],[CO]])=6), "Complete","Incomplete")))))))) -> Complete | AM14: =+IF(OR(Bitacora_2[[#This Row],[Exportador]]="INVERSIONES JORDIE",Bitacora_2[[#This Row],[Exportador]]="TAL S.A."), "Tercero", "Propio") -> Tercero | AN14: =IF(AND(Bitacora_2[[#This Row],[Clase Expedición]]="AIR",OR(Bitacora_2[[#This Row],[Mercado]]="US EAST",Bitacora_2[[#This Row],[Mercado]]="US WEST",Bitacora_2[[#This Row],[Mercado]]="US SOUTH")),IF(Bitacora_2[[#This Row],[ETD Doc]]<>"","Delivered","Pending"), IF(Bitacora_2[[#This Row],[Clase Expedición]]="AIR","Delivered", IF(AND(Bitacora_2[[#This Row],[ETD Doc]]="",Bitacora_2[[#This Row],[ATA DOC]]=""),"Pending", IF(AND(Bitacora_2[[#This Row],[ETD Doc]]<>"",Bitacora_2[[#This Row],[ATA DOC]]=""),"In transit", IF(AND(Bitacora_2[[#This Row],[ETD Doc]]<>"",Bitacora_2[[#This Row],[ATA DOC]]<>""),"Delivered",""))))) -> Delivered | AQ14: =IF(I14="SEA",IF(AP14="","On Hold","Released"),"")
A15: PO00000050872HFPEARANCONVPE691300306 | B15: 23 | C15: 46174 | D15: 25 | E15: LATAM | F15: BAR | G15: PE | H15: HFPE | I15: TRK | J15: ARAN | K15: CONV | L15: PO00000050872 | M15: PE691300306 | N15: BERRYGOOD COM. IMP. E DISTRIBUICAO | O15: BERRYGOOD | P15: TERRESTRE | Q15: 24 | R15: 46174 | S15: 46189 | T15: MILTEX | U15: =+IF(Bitacora_2[[#This Row],[ATA DOC]]<>"",Bitacora_2[[#This Row],[ATA DOC]], IF(Bitacora_2[[#This Row],[Clase Expedición]]="AIR",Bitacora_2[[#This Row],[ETD Real]], IF(AND(Bitacora_2[[#This Row],[Clase Expedición]]="SEA",Bitacora_2[[#This Row],[Mercado]]="LATAM"), Bitacora_2[[#This Row],[ETD Real]]+3, IF(AND(Bitacora_2[[#This Row],[Clase Expedición]]="SEA",Bitacora_2[[#This Row],[Mercado]]="EUROPE"), Bitacora_2[[#This Row],[ETD Real]]+8, IF(AND(Bitacora_2[[#This Row],[Clase Expedición]]="SEA",Bitacora_2[[#This Row],[Mercado]]="UK"), Bitacora_2[[#This Row],[ETD Real]]+11, IF(AND(Bitacora_2[[#This Row],[Clase Expedición]]="SEA",OR(Bitacora_2[[#This Row],[Mercado]]="ASIA",Bitacora_2[[#This Row],[Mercado]]="ASIA CN + HK")), Bitacora_2[[#This Row],[ETD Real]]+14, IF(AND(Bitacora_2[[#This Row],[Clase Expedición]]="SEA",OR(Bitacora_2[[#This Row],[Mercado]]="US EAST",Bitacora_2[[#This Row],[Mercado]]="US WEST",Bitacora_2[[#This Row],[Mercado]]="US SOUTH")), Bitacora_2[[#This Row],[ETD Real]]+8,""))))))) | X15: =IF(OR(Bitacora_2[[#This Row],[ETD Real]]="",Bitacora_2[[#This Row],[ETD Doc]]=""),"",Bitacora_2[[#This Row],[ETD Doc]]-Bitacora_2[[#This Row],[ETD Real]]) | Y15: =IF(OR(Bitacora_2[[#This Row],[ATA DOC]]="",Bitacora_2[[#This Row],[ETA Real]]=""),"",Bitacora_2[[#This Row],[ETA Real]]-Bitacora_2[[#This Row],[ATA DOC]]) | AI15: =IF(AND(OR(E15="US EAST",E15="US WEST",E15="US SOUTH"),I15="SEA",Bitacora_2[[#This Row],[ETD Real]]-TODAY()>=3,Bitacora_2[[#This Row],[ISF]]<>"X"),"Pending", IF(AND(OR(E15="US EAST",E15="US WEST",E15="US SOUTH"),I15="SEA",Bitacora_2[[#This Row],[ETD Real]]-TODAY()=2,Bitacora_2[[#This Row],[ISF]]<>"X"),"Urgente", IF(AND(OR(E15="US EAST",E15="US WEST",E15="US SOUTH"),I15="SEA",Bitacora_2[[#This Row],[ETD Real]]-TODAY()<=1,Bitacora_2[[#This Row],[ISF]]<>"X"),"Muy Urgente", IF(AND(OR(E15="US EAST",E15="US WEST",E15="US SOUTH"),I15="SEA",Bitacora_2[[#This Row],[ISF]]="X"),"Sent","")))) | AJ15: =IF(AND(OR(Bitacora_2[[#This Row],[Clase Expedición]]="AIR",Bitacora_2[[#This Row],[Clase Expedición]]="TRK")),"Complete", IF(AND(Bitacora_2[[#This Row],[Mercado]]="LATAM",COUNTA(Bitacora_2[[#This Row],[PHYTO]:[ISF]],Bitacora_2[[#This Row],[CO]])=7,Bitacora_2[[#This Row],[Clase Expedición]]<>"TRK"), "Complete", IF(AND(Bitacora_2[[#This Row],[Mercado]]="LATAM",COUNTA(Bitacora_2[[#This Row],[PHYTO]:[PL ]],Bitacora_2[[#This Row],[CO]])=6,Bitacora_2[[#This Row],[Clase Expedición]]="SEA"), "Complete", IF(AND(OR(Bitacora_2[[#This Row],[Mercado]]="EUROPE",Bitacora_2[[#This Row],[Mercado]]="UK"),COUNTA(Bitacora_2[[#This Row],[PHYTO]],Bitacora_2[[#This Row],[INVOICE]:[PL ]],Bitacora_2[[#This Row],[COI]])=5,Bitacora_2[[#This Row],[Clase Expedición]]="SEA",Bitacora_2[[#This Row],[Manejo]]="ORG"), "Complete", IF(AND(OR(Bitacora_2[[#This Row],[Mercado]]="EUROPE",Bitacora_2[[#This Row],[Mercado]]="UK"),COUNTA(Bitacora_2[[#This Row],[PHYTO]],Bitacora_2[[#This Row],[INVOICE]:[PL ]])=4,Bitacora_2[[#This Row],[Clase Expedición]]="SEA",Bitacora_2[[#This Row],[Manejo]]="CONV"), "Complete", IF(AND(OR(Bitacora_2[[#This Row],[Mercado]]="US WEST",Bitacora_2[[#This Row],[Mercado]]="US EAST",Bitacora_2[[#This Row],[Mercado]]="US SOUTH"),COUNTA(Bitacora_2[[#This Row],[PHYTO]:[ISF]],Bitacora_2[[#This Row],[CO]])=7,Bitacora_2[[#This Row],[Clase Expedición]]="SEA",Bitacora_2[[#This Row],[Exportador]]="ECHF"), "Complete", IF(AND(OR(Bitacora_2[[#This Row],[Mercado]]="US WEST",Bitacora_2[[#This Row],[Mercado]]="US EAST",Bitacora_2[[#This Row],[Mercado]]="US SOUTH"),COUNTA(Bitacora_2[[#This Row],[PHYTO]:[ISF]])=6,Bitacora_2[[#This Row],[Clase Expedición]]="SEA",Bitacora_2[[#This Row],[Exportador]]<>"ECHF"), "Complete", IF(AND(OR(Bitacora_2[[#This Row],[Mercado]]="ASIA",Bitacora_2[[#This Row],[Mercado]]="ASIA CN + HK"),COUNTA(Bitacora_2[[#This Row],[PHYTO]:[PL ]],Bitacora_2[[#This Row],[CO]])=6), "Complete","Incomplete")))))))) -> Complete | AM15: =+IF(OR(Bitacora_2[[#This Row],[Exportador]]="INVERSIONES JORDIE",Bitacora_2[[#This Row],[Exportador]]="TAL S.A."), "Tercero", "Propio") -> Propio | AN15: =IF(AND(Bitacora_2[[#This Row],[Clase Expedición]]="AIR",OR(Bitacora_2[[#This Row],[Mercado]]="US EAST",Bitacora_2[[#This Row],[Mercado]]="US WEST",Bitacora_2[[#This Row],[Mercado]]="US SOUTH")),IF(Bitacora_2[[#This Row],[ETD Doc]]<>"","Delivered","Pending"), IF(Bitacora_2[[#This Row],[Clase Expedición]]="AIR","Delivered", IF(AND(Bitacora_2[[#This Row],[ETD Doc]]="",Bitacora_2[[#This Row],[ATA DOC]]=""),"Pending", IF(AND(Bitacora_2[[#This Row],[ETD Doc]]<>"",Bitacora_2[[#This Row],[ATA DOC]]=""),"In transit", IF(AND(Bitacora_2[[#This Row],[ETD Doc]]<>"",Bitacora_2[[#This Row],[ATA DOC]]<>""),"Delivered",""))))) -> Pending | AQ15: =IF(I15="SEA",IF(AP15="","On Hold","Released"),"")
A16: PO00000050897HFPEARANCONV145-11634033 | B16: 23 | C16: 46174 | D16: 23 | E16: LATAM | F16: BOG | G16: PE | H16: HFPE | I16: AIR | J16: ARAN | K16: CONV | L16: PO00000050897 | M16: 145-11634033 | N16: HORTIFRUT COLOMBIA SAS | O16: HORTIFRUT COLOMBIA | P16: LATAM | Q16: 24 | R16: 46177 | S16: 46177 | T16: HELLMANN | U16: =+IF(Bitacora_2[[#This Row],[ATA DOC]]<>"",Bitacora_2[[#This Row],[ATA DOC]], IF(Bitacora_2[[#This Row],[Clase Expedición]]="AIR",Bitacora_2[[#This Row],[ETD Real]], IF(AND(Bitacora_2[[#This Row],[Clase Expedición]]="SEA",Bitacora_2[[#This Row],[Mercado]]="LATAM"), Bitacora_2[[#This Row],[ETD Real]]+3, IF(AND(Bitacora_2[[#This Row],[Clase Expedición]]="SEA",Bitacora_2[[#This Row],[Mercado]]="EUROPE"), Bitacora_2[[#This Row],[ETD Real]]+8, IF(AND(Bitacora_2[[#This Row],[Clase Expedición]]="SEA",Bitacora_2[[#This Row],[Mercado]]="UK"), Bitacora_2[[#This Row],[ETD Real]]+11, IF(AND(Bitacora_2[[#This Row],[Clase Expedición]]="SEA",OR(Bitacora_2[[#This Row],[Mercado]]="ASIA",Bitacora_2[[#This Row],[Mercado]]="ASIA CN + HK")), Bitacora_2[[#This Row],[ETD Real]]+14, IF(AND(Bitacora_2[[#This Row],[Clase Expedición]]="SEA",OR(Bitacora_2[[#This Row],[Mercado]]="US EAST",Bitacora_2[[#This Row],[Mercado]]="US WEST",Bitacora_2[[#This Row],[Mercado]]="US SOUTH")), Bitacora_2[[#This Row],[ETD Real]]+8,""))))))) -> 46177 | X16: =IF(OR(Bitacora_2[[#This Row],[ETD Real]]="",Bitacora_2[[#This Row],[ETD Doc]]=""),"",Bitacora_2[[#This Row],[ETD Doc]]-Bitacora_2[[#This Row],[ETD Real]]) | Y16: =IF(OR(Bitacora_2[[#This Row],[ATA DOC]]="",Bitacora_2[[#This Row],[ETA Real]]=""),"",Bitacora_2[[#This Row],[ETA Real]]-Bitacora_2[[#This Row],[ATA DOC]]) | AI16: =IF(AND(OR(E16="US EAST",E16="US WEST",E16="US SOUTH"),I16="SEA",Bitacora_2[[#This Row],[ETD Real]]-TODAY()>=3,Bitacora_2[[#This Row],[ISF]]<>"X"),"Pending", IF(AND(OR(E16="US EAST",E16="US WEST",E16="US SOUTH"),I16="SEA",Bitacora_2[[#This Row],[ETD Real]]-TODAY()=2,Bitacora_2[[#This Row],[ISF]]<>"X"),"Urgente", IF(AND(OR(E16="US EAST",E16="US WEST",E16="US SOUTH"),I16="SEA",Bitacora_2[[#This Row],[ETD Real]]-TODAY()<=1,Bitacora_2[[#This Row],[ISF]]<>"X"),"Muy Urgente", IF(AND(OR(E16="US EAST",E16="US WEST",E16="US SOUTH"),I16="SEA",Bitacora_2[[#This Row],[ISF]]="X"),"Sent","")))) | AJ16: =IF(AND(OR(Bitacora_2[[#This Row],[Clase Expedición]]="AIR",Bitacora_2[[#This Row],[Clase Expedición]]="TRK")),"Complete", IF(AND(Bitacora_2[[#This Row],[Mercado]]="LATAM",COUNTA(Bitacora_2[[#This Row],[PHYTO]:[ISF]],Bitacora_2[[#This Row],[CO]])=7,Bitacora_2[[#This Row],[Clase Expedición]]<>"TRK"), "Complete", IF(AND(Bitacora_2[[#This Row],[Mercado]]="LATAM",COUNTA(Bitacora_2[[#This Row],[PHYTO]:[PL ]],Bitacora_2[[#This Row],[CO]])=6,Bitacora_2[[#This Row],[Clase Expedición]]="SEA"), "Complete", IF(AND(OR(Bitacora_2[[#This Row],[Mercado]]="EUROPE",Bitacora_2[[#This Row],[Mercado]]="UK"),COUNTA(Bitacora_2[[#This Row],[PHYTO]],Bitacora_2[[#This Row],[INVOICE]:[PL ]],Bitacora_2[[#This Row],[COI]])=5,Bitacora_2[[#This Row],[Clase Expedición]]="SEA",Bitacora_2[[#This Row],[Manejo]]="ORG"), "Complete", IF(AND(OR(Bitacora_2[[#This Row],[Mercado]]="EUROPE",Bitacora_2[[#This Row],[Mercado]]="UK"),COUNTA(Bitacora_2[[#This Row],[PHYTO]],Bitacora_2[[#This Row],[INVOICE]:[PL ]])=4,Bitacora_2[[#This Row],[Clase Expedición]]="SEA",Bitacora_2[[#This Row],[Manejo]]="CONV"), "Complete", IF(AND(OR(Bitacora_2[[#This Row],[Mercado]]="US WEST",Bitacora_2[[#This Row],[Mercado]]="US EAST",Bitacora_2[[#This Row],[Mercado]]="US SOUTH"),COUNTA(Bitacora_2[[#This Row],[PHYTO]:[ISF]],Bitacora_2[[#This Row],[CO]])=7,Bitacora_2[[#This Row],[Clase Expedición]]="SEA",Bitacora_2[[#This Row],[Exportador]]="ECHF"), "Complete", IF(AND(OR(Bitacora_2[[#This Row],[Mercado]]="US WEST",Bitacora_2[[#This Row],[Mercado]]="US EAST",Bitacora_2[[#This Row],[Mercado]]="US SOUTH"),COUNTA(Bitacora_2[[#This Row],[PHYTO]:[ISF]])=6,Bitacora_2[[#This Row],[Clase Expedición]]="SEA",Bitacora_2[[#This Row],[Exportador]]<>"ECHF"), "Complete", IF(AND(OR(Bitacora_2[[#This Row],[Mercado]]="ASIA",Bitacora_2[[#This Row],[Mercado]]="ASIA CN + HK"),COUNTA(Bitacora_2[[#This Row],[PHYTO]:[PL ]],Bitacora_2[[#This Row],[CO]])=6), "Complete","Incomplete")))))))) -> Complete | AM16: =+IF(OR(Bitacora_2[[#This Row],[Exportador]]="INVERSIONES JORDIE",Bitacora_2[[#This Row],[Exportador]]="TAL S.A."), "Tercero", "Propio") -> Propio | AN16: =IF(AND(Bitacora_2[[#This Row],[Clase Expedición]]="AIR",OR(Bitacora_2[[#This Row],[Mercado]]="US EAST",Bitacora_2[[#This Row],[Mercado]]="US WEST",Bitacora_2[[#This Row],[Mercado]]="US SOUTH")),IF(Bitacora_2[[#This Row],[ETD Doc]]<>"","Delivered","Pending"), IF(Bitacora_2[[#This Row],[Clase Expedición]]="AIR","Delivered", IF(AND(Bitacora_2[[#This Row],[ETD Doc]]="",Bitacora_2[[#This Row],[ATA DOC]]=""),"Pending", IF(AND(Bitacora_2[[#This Row],[ETD Doc]]<>"",Bitacora_2[[#This Row],[ATA DOC]]=""),"In transit", IF(AND(Bitacora_2[[#This Row],[ETD Doc]]<>"",Bitacora_2[[#This Row],[ATA DOC]]<>""),"Delivered",""))))) -> Delivered | AQ16: =IF(I16="SEA",IF(AP16="","On Hold","Released"),"")
A17: PO00000050898HFPEARANCONV145-11634022 | B17: 23 | C17: 46174 | D17: 23 | E17: LATAM | F17: BOG | G17: PE | H17: HFPE | I17: AIR | J17: ARAN | K17: CONV | L17: PO00000050898 | M17: 145-11634022 | N17: HORTIFRUT COLOMBIA SAS | O17: HORTIFRUT COLOMBIA | P17: LATAM | Q17: 24 | R17: 46177 | S17: 46177 | T17: HELLMANN | U17: =+IF(Bitacora_2[[#This Row],[ATA DOC]]<>"",Bitacora_2[[#This Row],[ATA DOC]], IF(Bitacora_2[[#This Row],[Clase Expedición]]="AIR",Bitacora_2[[#This Row],[ETD Real]], IF(AND(Bitacora_2[[#This Row],[Clase Expedición]]="SEA",Bitacora_2[[#This Row],[Mercado]]="LATAM"), Bitacora_2[[#This Row],[ETD Real]]+3, IF(AND(Bitacora_2[[#This Row],[Clase Expedición]]="SEA",Bitacora_2[[#This Row],[Mercado]]="EUROPE"), Bitacora_2[[#This Row],[ETD Real]]+8, IF(AND(Bitacora_2[[#This Row],[Clase Expedición]]="SEA",Bitacora_2[[#This Row],[Mercado]]="UK"), Bitacora_2[[#This Row],[ETD Real]]+11, IF(AND(Bitacora_2[[#This Row],[Clase Expedición]]="SEA",OR(Bitacora_2[[#This Row],[Mercado]]="ASIA",Bitacora_2[[#This Row],[Mercado]]="ASIA CN + HK")), Bitacora_2[[#This Row],[ETD Real]]+14, IF(AND(Bitacora_2[[#This Row],[Clase Expedición]]="SEA",OR(Bitacora_2[[#This Row],[Mercado]]="US EAST",Bitacora_2[[#This Row],[Mercado]]="US WEST",Bitacora_2[[#This Row],[Mercado]]="US SOUTH")), Bitacora_2[[#This Row],[ETD Real]]+8,""))))))) -> 46177 | X17: =IF(OR(Bitacora_2[[#This Row],[ETD Real]]="",Bitacora_2[[#This Row],[ETD Doc]]=""),"",Bitacora_2[[#This Row],[ETD Doc]]-Bitacora_2[[#This Row],[ETD Real]]) | Y17: =IF(OR(Bitacora_2[[#This Row],[ATA DOC]]="",Bitacora_2[[#This Row],[ETA Real]]=""),"",Bitacora_2[[#This Row],[ETA Real]]-Bitacora_2[[#This Row],[ATA DOC]]) | AI17: =IF(AND(OR(E17="US EAST",E17="US WEST",E17="US SOUTH"),I17="SEA",Bitacora_2[[#This Row],[ETD Real]]-TODAY()>=3,Bitacora_2[[#This Row],[ISF]]<>"X"),"Pending", IF(AND(OR(E17="US EAST",E17="US WEST",E17="US SOUTH"),I17="SEA",Bitacora_2[[#This Row],[ETD Real]]-TODAY()=2,Bitacora_2[[#This Row],[ISF]]<>"X"),"Urgente", IF(AND(OR(E17="US EAST",E17="US WEST",E17="US SOUTH"),I17="SEA",Bitacora_2[[#This Row],[ETD Real]]-TODAY()<=1,Bitacora_2[[#This Row],[ISF]]<>"X"),"Muy Urgente", IF(AND(OR(E17="US EAST",E17="US WEST",E17="US SOUTH"),I17="SEA",Bitacora_2[[#This Row],[ISF]]="X"),"Sent","")))) | AJ17: =IF(AND(OR(Bitacora_2[[#This Row],[Clase Expedición]]="AIR",Bitacora_2[[#This Row],[Clase Expedición]]="TRK")),"Complete", IF(AND(Bitacora_2[[#This Row],[Mercado]]="LATAM",COUNTA(Bitacora_2[[#This Row],[PHYTO]:[ISF]],Bitacora_2[[#This Row],[CO]])=7,Bitacora_2[[#This Row],[Clase Expedición]]<>"TRK"), "Complete", IF(AND(Bitacora_2[[#This Row],[Mercado]]="LATAM",COUNTA(Bitacora_2[[#This Row],[PHYTO]:[PL ]],Bitacora_2[[#This Row],[CO]])=6,Bitacora_2[[#This Row],[Clase Expedición]]="SEA"), "Complete", IF(AND(OR(Bitacora_2[[#This Row],[Mercado]]="EUROPE",Bitacora_2[[#This Row],[Mercado]]="UK"),COUNTA(Bitacora_2[[#This Row],[PHYTO]],Bitacora_2[[#This Row],[INVOICE]:[PL ]],Bitacora_2[[#This Row],[COI]])=5,Bitacora_2[[#This Row],[Clase Expedición]]="SEA",Bitacora_2[[#This Row],[Manejo]]="ORG"), "Complete", IF(AND(OR(Bitacora_2[[#This Row],[Mercado]]="EUROPE",Bitacora_2[[#This Row],[Mercado]]="UK"),COUNTA(Bitacora_2[[#This Row],[PHYTO]],Bitacora_2[[#This Row],[INVOICE]:[PL ]])=4,Bitacora_2[[#This Row],[Clase Expedición]]="SEA",Bitacora_2[[#This Row],[Manejo]]="CONV"), "Complete", IF(AND(OR(Bitacora_2[[#This Row],[Mercado]]="US WEST",Bitacora_2[[#This Row],[Mercado]]="US EAST",Bitacora_2[[#This Row],[Mercado]]="US SOUTH"),COUNTA(Bitacora_2[[#This Row],[PHYTO]:[ISF]],Bitacora_2[[#This Row],[CO]])=7,Bitacora_2[[#This Row],[Clase Expedición]]="SEA",Bitacora_2[[#This Row],[Exportador]]="ECHF"), "Complete", IF(AND(OR(Bitacora_2[[#This Row],[Mercado]]="US WEST",Bitacora_2[[#This Row],[Mercado]]="US EAST",Bitacora_2[[#This Row],[Mercado]]="US SOUTH"),COUNTA(Bitacora_2[[#This Row],[PHYTO]:[ISF]])=6,Bitacora_2[[#This Row],[Clase Expedición]]="SEA",Bitacora_2[[#This Row],[Exportador]]<>"ECHF"), "Complete", IF(AND(OR(Bitacora_2[[#This Row],[Mercado]]="ASIA",Bitacora_2[[#This Row],[Mercado]]="ASIA CN + HK"),COUNTA(Bitacora_2[[#This Row],[PHYTO]:[PL ]],Bitacora_2[[#This Row],[CO]])=6), "Complete","Incomplete")))))))) -> Complete | AM17: =+IF(OR(Bitacora_2[[#This Row],[Exportador]]="INVERSIONES JORDIE",Bitacora_2[[#This Row],[Exportador]]="TAL S.A."), "Tercero", "Propio") -> Propio | AN17: =IF(AND(Bitacora_2[[#This Row],[Clase Expedición]]="AIR",OR(Bitacora_2[[#This Row],[Mercado]]="US EAST",Bitacora_2[[#This Row],[Mercado]]="US WEST",Bitacora_2[[#This Row],[Mercado]]="US SOUTH")),IF(Bitacora_2[[#This Row],[ETD Doc]]<>"","Delivered","Pending"), IF(Bitacora_2[[#This Row],[Clase Expedición]]="AIR","Delivered", IF(AND(Bitacora_2[[#This Row],[ETD Doc]]="",Bitacora_2[[#This Row],[ATA DOC]]=""),"Pending", IF(AND(Bitacora_2[[#This Row],[ETD Doc]]<>"",Bitacora_2[[#This Row],[ATA DOC]]=""),"In transit", IF(AND(Bitacora_2[[#This Row],[ETD Doc]]<>"",Bitacora_2[[#This Row],[ATA DOC]]<>""),"Delivered",""))))) -> Delivered | AQ17: =IF(I17="SEA",IF(AP17="","On Hold","Released"),"")
A18: PO00000050899HFPEARANCONVFBIU5460286 | B18: 23 | C18: 46174 | D18: 27 | E18: LATAM | F18: CLSAI | G18: PE | H18: HFPE | I18: SEA | J18: ARAN | K18: CONV | L18: PO00000050899 | M18: FBIU5460286 | N18: HORTIFRUT COMERCIAL S.A. | O18: HORTIFRUT CHILE | P18: COSCO | Q18: CSCL SATURN 088W | R18: 46198 | S18: 46202 | T18: NWT | U18: =+IF(Bitacora_2[[#This Row],[ATA DOC]]<>"",Bitacora_2[[#This Row],[ATA DOC]], IF(Bitacora_2[[#This Row],[Clase Expedición]]="AIR",Bitacora_2[[#This Row],[ETD Real]], IF(AND(Bitacora_2[[#This Row],[Clase Expedición]]="SEA",Bitacora_2[[#This Row],[Mercado]]="LATAM"), Bitacora_2[[#This Row],[ETD Real]]+3, IF(AND(Bitacora_2[[#This Row],[Clase Expedición]]="SEA",Bitacora_2[[#This Row],[Mercado]]="EUROPE"), Bitacora_2[[#This Row],[ETD Real]]+8, IF(AND(Bitacora_2[[#This Row],[Clase Expedición]]="SEA",Bitacora_2[[#This Row],[Mercado]]="UK"), Bitacora_2[[#This Row],[ETD Real]]+11, IF(AND(Bitacora_2[[#This Row],[Clase Expedición]]="SEA",OR(Bitacora_2[[#This Row],[Mercado]]="ASIA",Bitacora_2[[#This Row],[Mercado]]="ASIA CN + HK")), Bitacora_2[[#This Row],[ETD Real]]+14, IF(AND(Bitacora_2[[#This Row],[Clase Expedición]]="SEA",OR(Bitacora_2[[#This Row],[Mercado]]="US EAST",Bitacora_2[[#This Row],[Mercado]]="US WEST",Bitacora_2[[#This Row],[Mercado]]="US SOUTH")), Bitacora_2[[#This Row],[ETD Real]]+8,""))))))) -> 46196 | V18: 46196 | W18: 46196 | X18: =IF(OR(Bitacora_2[[#This Row],[ETD Real]]="",Bitacora_2[[#This Row],[ETD Doc]]=""),"",Bitacora_2[[#This Row],[ETD Doc]]-Bitacora_2[[#This Row],[ETD Real]]) -> -2 | Y18: =IF(OR(Bitacora_2[[#This Row],[ATA DOC]]="",Bitacora_2[[#This Row],[ETA Real]]=""),"",Bitacora_2[[#This Row],[ETA Real]]-Bitacora_2[[#This Row],[ATA DOC]]) -> 6 | Z18: 9780695525 | AA18: X | AB18: X | AC18: X | AD18: X | AE18: X | AH18: x | AI18: =IF(AND(OR(E18="US EAST",E18="US WEST",E18="US SOUTH"),I18="SEA",Bitacora_2[[#This Row],[ETD Real]]-TODAY()>=3,Bitacora_2[[#This Row],[ISF]]<>"X"),"Pending", IF(AND(OR(E18="US EAST",E18="US WEST",E18="US SOUTH"),I18="SEA",Bitacora_2[[#This Row],[ETD Real]]-TODAY()=2,Bitacora_2[[#This Row],[ISF]]<>"X"),"Urgente", IF(AND(OR(E18="US EAST",E18="US WEST",E18="US SOUTH"),I18="SEA",Bitacora_2[[#This Row],[ETD Real]]-TODAY()<=1,Bitacora_2[[#This Row],[ISF]]<>"X"),"Muy Urgente", IF(AND(OR(E18="US EAST",E18="US WEST",E18="US SOUTH"),I18="SEA",Bitacora_2[[#This Row],[ISF]]="X"),"Sent","")))) | AJ18: =IF(AND(OR(Bitacora_2[[#This Row],[Clase Expedición]]="AIR",Bitacora_2[[#This Row],[Clase Expedición]]="TRK")),"Complete", IF(AND(Bitacora_2[[#This Row],[Mercado]]="LATAM",COUNTA(Bitacora_2[[#This Row],[PHYTO]:[ISF]],Bitacora_2[[#This Row],[CO]])=7,Bitacora_2[[#This Row],[Clase Expedición]]<>"TRK"), "Complete", IF(AND(Bitacora_2[[#This Row],[Mercado]]="LATAM",COUNTA(Bitacora_2[[#This Row],[PHYTO]:[PL ]],Bitacora_2[[#This Row],[CO]])=6,Bitacora_2[[#This Row],[Clase Expedición]]="SEA"), "Complete", IF(AND(OR(Bitacora_2[[#This Row],[Mercado]]="EUROPE",Bitacora_2[[#This Row],[Mercado]]="UK"),COUNTA(Bitacora_2[[#This Row],[PHYTO]],Bitacora_2[[#This Row],[INVOICE]:[PL ]],Bitacora_2[[#This Row],[COI]])=5,Bitacora_2[[#This Row],[Clase Expedición]]="SEA",Bitacora_2[[#This Row],[Manejo]]="ORG"), "Complete", IF(AND(OR(Bitacora_2[[#This Row],[Mercado]]="EUROPE",Bitacora_2[[#This Row],[Mercado]]="UK"),COUNTA(Bitacora_2[[#This Row],[PHYTO]],Bitacora_2[[#This Row],[INVOICE]:[PL ]])=4,Bitacora_2[[#This Row],[Clase Expedición]]="SEA",Bitacora_2[[#This Row],[Manejo]]="CONV"), "Complete", IF(AND(OR(Bitacora_2[[#This Row],[Mercado]]="US WEST",Bitacora_2[[#This Row],[Mercado]]="US EAST",Bitacora_2[[#This Row],[Mercado]]="US SOUTH"),COUNTA(Bitacora_2[[#This Row],[PHYTO]:[ISF]],Bitacora_2[[#This Row],[CO]])=7,Bitacora_2[[#This Row],[Clase Expedición]]="SEA",Bitacora_2[[#This Row],[Exportador]]="ECHF"), "Complete", IF(AND(OR(Bitacora_2[[#This Row],[Mercado]]="US WEST",Bitacora_2[[#This Row],[Mercado]]="US EAST",Bitacora_2[[#This Row],[Mercado]]="US SOUTH"),COUNTA(Bitacora_2[[#This Row],[PHYTO]:[ISF]])=6,Bitacora_2[[#This Row],[Clase Expedición]]="SEA",Bitacora_2[[#This Row],[Exportador]]<>"ECHF"), "Complete", IF(AND(OR(Bitacora_2[[#This Row],[Mercado]]="ASIA",Bitacora_2[[#This Row],[Mercado]]="ASIA CN + HK"),COUNTA(Bitacora_2[[#This Row],[PHYTO]:[PL ]],Bitacora_2[[#This Row],[CO]])=6), "Complete","Incomplete")))))))) -> Complete | AM18: =+IF(OR(Bitacora_2[[#This Row],[Exportador]]="INVERSIONES JORDIE",Bitacora_2[[#This Row],[Exportador]]="TAL S.A."), "Tercero", "Propio") -> Propio | AN18: =IF(AND(Bitacora_2[[#This Row],[Clase Expedición]]="AIR",OR(Bitacora_2[[#This Row],[Mercado]]="US EAST",Bitacora_2[[#This Row],[Mercado]]="US WEST",Bitacora_2[[#This Row],[Mercado]]="US SOUTH")),IF(Bitacora_2[[#This Row],[ETD Doc]]<>"","Delivered","Pending"), IF(Bitacora_2[[#This Row],[Clase Expedición]]="AIR","Delivered", IF(AND(Bitacora_2[[#This Row],[ETD Doc]]="",Bitacora_2[[#This Row],[ATA DOC]]=""),"Pending", IF(AND(Bitacora_2[[#This Row],[ETD Doc]]<>"",Bitacora_2[[#This Row],[ATA DOC]]=""),"In transit", IF(AND(Bitacora_2[[#This Row],[ETD Doc]]<>"",Bitacora_2[[#This Row],[ATA DOC]]<>""),"Delivered",""))))) -> Delivered | AO18: Released | AP18: 46215 | AQ18: =IF(I18="SEA",IF(AP18="","On Hold","Released"),"") -> Released | AR18: Demora en revisión de reporte (COSCO + SAG)
A19: PO00000050909HFPEARANCONVSZLU9302534 | B19: 23 | C19: 46174 | D19: 25 | E19: US EAST | F19: USPHL | G19: PE | H19: HFPE | I19: SEA | J19: ARAN | K19: CONV | L19: PO00000050909 | M19: SZLU9302534 | N19: HORTIFRUT IMPORTS INC. (PHI-BOAT) | O19: NRF TIER I | P19: CITIKOLD | Q19: SEABOARD VALOR 14 | R19: 46177 | S19: 46188 | T19: NWT | U19: =+IF(Bitacora_2[[#This Row],[ATA DOC]]<>"",Bitacora_2[[#This Row],[ATA DOC]], IF(Bitacora_2[[#This Row],[Clase Expedición]]="AIR",Bitacora_2[[#This Row],[ETD Real]], IF(AND(Bitacora_2[[#This Row],[Clase Expedición]]="SEA",Bitacora_2[[#This Row],[Mercado]]="LATAM"), Bitacora_2[[#This Row],[ETD Real]]+3, IF(AND(Bitacora_2[[#This Row],[Clase Expedición]]="SEA",Bitacora_2[[#This Row],[Mercado]]="EUROPE"), Bitacora_2[[#This Row],[ETD Real]]+8, IF(AND(Bitacora_2[[#This Row],[Clase Expedición]]="SEA",Bitacora_2[[#This Row],[Mercado]]="UK"), Bitacora_2[[#This Row],[ETD Real]]+11, IF(AND(Bitacora_2[[#This Row],[Clase Expedición]]="SEA",OR(Bitacora_2[[#This Row],[Mercado]]="ASIA",Bitacora_2[[#This Row],[Mercado]]="ASIA CN + HK")), Bitacora_2[[#This Row],[ETD Real]]+14, IF(AND(Bitacora_2[[#This Row],[Clase Expedición]]="SEA",OR(Bitacora_2[[#This Row],[Mercado]]="US EAST",Bitacora_2[[#This Row],[Mercado]]="US WEST",Bitacora_2[[#This Row],[Mercado]]="US SOUTH")), Bitacora_2[[#This Row],[ETD Real]]+8,""))))))) -> 46178 | V19: 46178 | W19: 46178 | X19: =IF(OR(Bitacora_2[[#This Row],[ETD Real]]="",Bitacora_2[[#This Row],[ETD Doc]]=""),"",Bitacora_2[[#This Row],[ETD Doc]]-Bitacora_2[[#This Row],[ETD Real]]) -> 1 | Y19: =IF(OR(Bitacora_2[[#This Row],[ATA DOC]]="",Bitacora_2[[#This Row],[ETA Real]]=""),"",Bitacora_2[[#This Row],[ETA Real]]-Bitacora_2[[#This Row],[ATA DOC]]) -> 10 | Z19: - | AA19: X | AB19: X | AC19: X | AD19: X | AE19: X | AF19: x | AI19: =IF(AND(OR(E19="US EAST",E19="US WEST",E19="US SOUTH"),I19="SEA",Bitacora_2[[#This Row],[ETD Real]]-TODAY()>=3,Bitacora_2[[#This Row],[ISF]]<>"X"),"Pending", IF(AND(OR(E19="US EAST",E19="US WEST",E19="US SOUTH"),I19="SEA",Bitacora_2[[#This Row],[ETD Real]]-TODAY()=2,Bitacora_2[[#This Row],[ISF]]<>"X"),"Urgente", IF(AND(OR(E19="US EAST",E19="US WEST",E19="US SOUTH"),I19="SEA",Bitacora_2[[#This Row],[ETD Real]]-TODAY()<=1,Bitacora_2[[#This Row],[ISF]]<>"X"),"Muy Urgente", IF(AND(OR(E19="US EAST",E19="US WEST",E19="US SOUTH"),I19="SEA",Bitacora_2[[#This Row],[ISF]]="X"),"Sent","")))) -> Sent | AJ19: =IF(AND(OR(Bitacora_2[[#This Row],[Clase Expedición]]="AIR",Bitacora_2[[#This Row],[Clase Expedición]]="TRK")),"Complete", IF(AND(Bitacora_2[[#This Row],[Mercado]]="LATAM",COUNTA(Bitacora_2[[#This Row],[PHYTO]:[ISF]],Bitacora_2[[#This Row],[CO]])=7,Bitacora_2[[#This Row],[Clase Expedición]]<>"TRK"), "Complete", IF(AND(Bitacora_2[[#This Row],[Mercado]]="LATAM",COUNTA(Bitacora_2[[#This Row],[PHYTO]:[PL ]],Bitacora_2[[#This Row],[CO]])=6,Bitacora_2[[#This Row],[Clase Expedición]]="SEA"), "Complete", IF(AND(OR(Bitacora_2[[#This Row],[Mercado]]="EUROPE",Bitacora_2[[#This Row],[Mercado]]="UK"),COUNTA(Bitacora_2[[#This Row],[PHYTO]],Bitacora_2[[#This Row],[INVOICE]:[PL ]],Bitacora_2[[#This Row],[COI]])=5,Bitacora_2[[#This Row],[Clase Expedición]]="SEA",Bitacora_2[[#This Row],[Manejo]]="ORG"), "Complete", IF(AND(OR(Bitacora_2[[#This Row],[Mercado]]="EUROPE",Bitacora_2[[#This Row],[Mercado]]="UK"),COUNTA(Bitacora_2[[#This Row],[PHYTO]],Bitacora_2[[#This Row],[INVOICE]:[PL ]])=4,Bitacora_2[[#This Row],[Clase Expedición]]="SEA",Bitacora_2[[#This Row],[Manejo]]="CONV"), "Complete", IF(AND(OR(Bitacora_2[[#This Row],[Mercado]]="US WEST",Bitacora_2[[#This Row],[Mercado]]="US EAST",Bitacora_2[[#This Row],[Mercado]]="US SOUTH"),COUNTA(Bitacora_2[[#This Row],[PHYTO]:[ISF]],Bitacora_2[[#This Row],[CO]])=7,Bitacora_2[[#This Row],[Clase Expedición]]="SEA",Bitacora_2[[#This Row],[Exportador]]="ECHF"), "Complete", IF(AND(OR(Bitacora_2[[#This Row],[Mercado]]="US WEST",Bitacora_2[[#This Row],[Mercado]]="US EAST",Bitacora_2[[#This Row],[Mercado]]="US SOUTH"),COUNTA(Bitacora_2[[#This Row],[PHYTO]:[ISF]])=6,Bitacora_2[[#This Row],[Clase Expedición]]="SEA",Bitacora_2[[#This Row],[Exportador]]<>"ECHF"), "Complete", IF(AND(OR(Bitacora_2[[#This Row],[Mercado]]="ASIA",Bitacora_2[[#This Row],[Mercado]]="ASIA CN + HK"),COUNTA(Bitacora_2[[#This Row],[PHYTO]:[PL ]],Bitacora_2[[#This Row],[CO]])=6), "Complete","Incomplete")))))))) -> Complete | AM19: =+IF(OR(Bitacora_2[[#This Row],[Exportador]]="INVERSIONES JORDIE",Bitacora_2[[#This Row],[Exportador]]="TAL S.A."), "Tercero", "Propio") -> Propio | AN19: =IF(AND(Bitacora_2[[#This Row],[Clase Expedición]]="AIR",OR(Bitacora_2[[#This Row],[Mercado]]="US EAST",Bitacora_2[[#This Row],[Mercado]]="US WEST",Bitacora_2[[#This Row],[Mercado]]="US SOUTH")),IF(Bitacora_2[[#This Row],[ETD Doc]]<>"","Delivered","Pending"), IF(Bitacora_2[[#This Row],[Clase Expedición]]="AIR","Delivered", IF(AND(Bitacora_2[[#This Row],[ETD Doc]]="",Bitacora_2[[#This Row],[ATA DOC]]=""),"Pending", IF(AND(Bitacora_2[[#This Row],[ETD Doc]]<>"",Bitacora_2[[#This Row],[ATA DOC]]=""),"In transit", IF(AND(Bitacora_2[[#This Row],[ETD Doc]]<>"",Bitacora_2[[#This Row],[ATA DOC]]<>""),"Delivered",""))))) -> Delivered | AO19: Released | AP19: 46185 | AQ19: =IF(I19="SEA",IF(AP19="","On Hold","Released"),"") -> Released
A20: PO00000050985TTAL S.A.ARANCONVSEKU9424169 | B20: 23 | C20: 46174 | D20: 26 | E20: US EAST | F20: USPHL | G20: PE | H20: TAL S.A. | I20: SEA | J20: ARAN | K20: CONV | L20: PO00000050985T | M20: SEKU9424169 | O20: NRF TIER I | P20: Seaboard | Q20: SEABOARD VOYAGER | R20: 46184 | S20: 46195 | U20: =+IF(Bitacora_2[[#This Row],[ATA DOC]]<>"",Bitacora_2[[#This Row],[ATA DOC]], IF(Bitacora_2[[#This Row],[Clase Expedición]]="AIR",Bitacora_2[[#This Row],[ETD Real]], IF(AND(Bitacora_2[[#This Row],[Clase Expedición]]="SEA",Bitacora_2[[#This Row],[Mercado]]="LATAM"), Bitacora_2[[#This Row],[ETD Real]]+3, IF(AND(Bitacora_2[[#This Row],[Clase Expedición]]="SEA",Bitacora_2[[#This Row],[Mercado]]="EUROPE"), Bitacora_2[[#This Row],[ETD Real]]+8, IF(AND(Bitacora_2[[#This Row],[Clase Expedición]]="SEA",Bitacora_2[[#This Row],[Mercado]]="UK"), Bitacora_2[[#This Row],[ETD Real]]+11, IF(AND(Bitacora_2[[#This Row],[Clase Expedición]]="SEA",OR(Bitacora_2[[#This Row],[Mercado]]="ASIA",Bitacora_2[[#This Row],[Mercado]]="ASIA CN + HK")), Bitacora_2[[#This Row],[ETD Real]]+14, IF(AND(Bitacora_2[[#This Row],[Clase Expedición]]="SEA",OR(Bitacora_2[[#This Row],[Mercado]]="US EAST",Bitacora_2[[#This Row],[Mercado]]="US WEST",Bitacora_2[[#This Row],[Mercado]]="US SOUTH")), Bitacora_2[[#This Row],[ETD Real]]+8,""))))))) -> 46185 | V20: 46185 | W20: 46185 | X20: =IF(OR(Bitacora_2[[#This Row],[ETD Real]]="",Bitacora_2[[#This Row],[ETD Doc]]=""),"",Bitacora_2[[#This Row],[ETD Doc]]-Bitacora_2[[#This Row],[ETD Real]]) -> 1 | Y20: =IF(OR(Bitacora_2[[#This Row],[ATA DOC]]="",Bitacora_2[[#This Row],[ETA Real]]=""),"",Bitacora_2[[#This Row],[ETA Real]]-Bitacora_2[[#This Row],[ATA DOC]]) -> 10 | Z20: - | AA20: X | AB20: X | AC20: X | AD20: X | AE20: X | AF20: x | AI20: =IF(AND(OR(E20="US EAST",E20="US WEST",E20="US SOUTH"),I20="SEA",Bitacora_2[[#This Row],[ETD Real]]-TODAY()>=3,Bitacora_2[[#This Row],[ISF]]<>"X"),"Pending", IF(AND(OR(E20="US EAST",E20="US WEST",E20="US SOUTH"),I20="SEA",Bitacora_2[[#This Row],[ETD Real]]-TODAY()=2,Bitacora_2[[#This Row],[ISF]]<>"X"),"Urgente", IF(AND(OR(E20="US EAST",E20="US WEST",E20="US SOUTH"),I20="SEA",Bitacora_2[[#This Row],[ETD Real]]-TODAY()<=1,Bitacora_2[[#This Row],[ISF]]<>"X"),"Muy Urgente", IF(AND(OR(E20="US EAST",E20="US WEST",E20="US SOUTH"),I20="SEA",Bitacora_2[[#This Row],[ISF]]="X"),"Sent","")))) -> Sent | AJ20: =IF(AND(OR(Bitacora_2[[#This Row],[Clase Expedición]]="AIR",Bitacora_2[[#This Row],[Clase Expedición]]="TRK")),"Complete", IF(AND(Bitacora_2[[#This Row],[Mercado]]="LATAM",COUNTA(Bitacora_2[[#This Row],[PHYTO]:[ISF]],Bitacora_2[[#This Row],[CO]])=7,Bitacora_2[[#This Row],[Clase Expedición]]<>"TRK"), "Complete", IF(AND(Bitacora_2[[#This Row],[Mercado]]="LATAM",COUNTA(Bitacora_2[[#This Row],[PHYTO]:[PL ]],Bitacora_2[[#This Row],[CO]])=6,Bitacora_2[[#This Row],[Clase Expedición]]="SEA"), "Complete", IF(AND(OR(Bitacora_2[[#This Row],[Mercado]]="EUROPE",Bitacora_2[[#This Row],[Mercado]]="UK"),COUNTA(Bitacora_2[[#This Row],[PHYTO]],Bitacora_2[[#This Row],[INVOICE]:[PL ]],Bitacora_2[[#This Row],[COI]])=5,Bitacora_2[[#This Row],[Clase Expedición]]="SEA",Bitacora_2[[#This Row],[Manejo]]="ORG"), "Complete", IF(AND(OR(Bitacora_2[[#This Row],[Mercado]]="EUROPE",Bitacora_2[[#This Row],[Mercado]]="UK"),COUNTA(Bitacora_2[[#This Row],[PHYTO]],Bitacora_2[[#This Row],[INVOICE]:[PL ]])=4,Bitacora_2[[#This Row],[Clase Expedición]]="SEA",Bitacora_2[[#This Row],[Manejo]]="CONV"), "Complete", IF(AND(OR(Bitacora_2[[#This Row],[Mercado]]="US WEST",Bitacora_2[[#This Row],[Mercado]]="US EAST",Bitacora_2[[#This Row],[Mercado]]="US SOUTH"),COUNTA(Bitacora_2[[#This Row],[PHYTO]:[ISF]],Bitacora_2[[#This Row],[CO]])=7,Bitacora_2[[#This Row],[Clase Expedición]]="SEA",Bitacora_2[[#This Row],[Exportador]]="ECHF"), "Complete", IF(AND(OR(Bitacora_2[[#This Row],[Mercado]]="US WEST",Bitacora_2[[#This Row],[Mercado]]="US EAST",Bitacora_2[[#This Row],[Mercado]]="US SOUTH"),COUNTA(Bitacora_2[[#This Row],[PHYTO]:[ISF]])=6,Bitacora_2[[#This Row],[Clase Expedición]]="SEA",Bitacora_2[[#This Row],[Exportador]]<>"ECHF"), "Complete", IF(AND(OR(Bitacora_2[[#This Row],[Mercado]]="ASIA",Bitacora_2[[#This Row],[Mercado]]="ASIA CN + HK"),COUNTA(Bitacora_2[[#This Row],[PHYTO]:[PL ]],Bitacora_2[[#This Row],[CO]])=6), "Complete","Incomplete")))))))) -> Complete | AM20: =+IF(OR(Bitacora_2[[#This Row],[Exportador]]="INVERSIONES JORDIE",Bitacora_2[[#This Row],[Exportador]]="TAL S.A."), "Tercero", "Propio") -> Tercero | AN20: =IF(AND(Bitacora_2[[#This Row],[Clase Expedición]]="AIR",OR(Bitacora_2[[#This Row],[Mercado]]="US EAST",Bitacora_2[[#This Row],[Mercado]]="US WEST",Bitacora_2[[#This Row],[Mercado]]="US SOUTH")),IF(Bitacora_2[[#This Row],[ETD Doc]]<>"","Delivered","Pending"), IF(Bitacora_2[[#This Row],[Clase Expedición]]="AIR","Delivered", IF(AND(Bitacora_2[[#This Row],[ETD Doc]]="",Bitacora_2[[#This Row],[ATA DOC]]=""),"Pending", IF(AND(Bitacora_2[[#This Row],[ETD Doc]]<>"",Bitacora_2[[#This Row],[ATA DOC]]=""),"In transit", IF(AND(Bitacora_2[[#This Row],[ETD Doc]]<>"",Bitacora_2[[#This Row],[ATA DOC]]<>""),"Delivered",""))))) -> Delivered | AO20: Released | AP20: 46192 | AQ20: =IF(I20="SEA",IF(AP20="","On Hold","Released"),"") -> Released
A21: RH-0020T1TAL S.A.ARANCONV145-11634184 | B21: 23 | C21: 46175 | D21: 23 | E21: US EAST | F21: JFK | G21: PE | H21: TAL S.A. | I21: AIR | J21: ARAN | K21: CONV | L21: RH-0020T1 | M21: 145-11634184 | O21: NRF TIER I | P21: LATAM | R21: 46182 | S21: 46178 | U21: =+IF(Bitacora_2[[#This Row],[ATA DOC]]<>"",Bitacora_2[[#This Row],[ATA DOC]], IF(Bitacora_2[[#This Row],[Clase Expedición]]="AIR",Bitacora_2[[#This Row],[ETD Real]], IF(AND(Bitacora_2[[#This Row],[Clase Expedición]]="SEA",Bitacora_2[[#This Row],[Mercado]]="LATAM"), Bitacora_2[[#This Row],[ETD Real]]+3, IF(AND(Bitacora_2[[#This Row],[Clase Expedición]]="SEA",Bitacora_2[[#This Row],[Mercado]]="EUROPE"), Bitacora_2[[#This Row],[ETD Real]]+8, IF(AND(Bitacora_2[[#This Row],[Clase Expedición]]="SEA",Bitacora_2[[#This Row],[Mercado]]="UK"), Bitacora_2[[#This Row],[ETD Real]]+11, IF(AND(Bitacora_2[[#This Row],[Clase Expedición]]="SEA",OR(Bitacora_2[[#This Row],[Mercado]]="ASIA",Bitacora_2[[#This Row],[Mercado]]="ASIA CN + HK")), Bitacora_2[[#This Row],[ETD Real]]+14, IF(AND(Bitacora_2[[#This Row],[Clase Expedición]]="SEA",OR(Bitacora_2[[#This Row],[Mercado]]="US EAST",Bitacora_2[[#This Row],[Mercado]]="US WEST",Bitacora_2[[#This Row],[Mercado]]="US SOUTH")), Bitacora_2[[#This Row],[ETD Real]]+8,""))))))) -> 46182 | X21: =IF(OR(Bitacora_2[[#This Row],[ETD Real]]="",Bitacora_2[[#This Row],[ETD Doc]]=""),"",Bitacora_2[[#This Row],[ETD Doc]]-Bitacora_2[[#This Row],[ETD Real]]) | Y21: =IF(OR(Bitacora_2[[#This Row],[ATA DOC]]="",Bitacora_2[[#This Row],[ETA Real]]=""),"",Bitacora_2[[#This Row],[ETA Real]]-Bitacora_2[[#This Row],[ATA DOC]]) | AI21: =IF(AND(OR(E21="US EAST",E21="US WEST",E21="US SOUTH"),I21="SEA",Bitacora_2[[#This Row],[ETD Real]]-TODAY()>=3,Bitacora_2[[#This Row],[ISF]]<>"X"),"Pending", IF(AND(OR(E21="US EAST",E21="US WEST",E21="US SOUTH"),I21="SEA",Bitacora_2[[#This Row],[ETD Real]]-TODAY()=2,Bitacora_2[[#This Row],[ISF]]<>"X"),"Urgente", IF(AND(OR(E21="US EAST",E21="US WEST",E21="US SOUTH"),I21="SEA",Bitacora_2[[#This Row],[ETD Real]]-TODAY()<=1,Bitacora_2[[#This Row],[ISF]]<>"X"),"Muy Urgente", IF(AND(OR(E21="US EAST",E21="US WEST",E21="US SOUTH"),I21="SEA",Bitacora_2[[#This Row],[ISF]]="X"),"Sent","")))) | AJ21: =IF(AND(OR(Bitacora_2[[#This Row],[Clase Expedición]]="AIR",Bitacora_2[[#This Row],[Clase Expedición]]="TRK")),"Complete", IF(AND(Bitacora_2[[#This Row],[Mercado]]="LATAM",COUNTA(Bitacora_2[[#This Row],[PHYTO]:[ISF]],Bitacora_2[[#This Row],[CO]])=7,Bitacora_2[[#This Row],[Clase Expedición]]<>"TRK"), "Complete", IF(AND(Bitacora_2[[#This Row],[Mercado]]="LATAM",COUNTA(Bitacora_2[[#This Row],[PHYTO]:[PL ]],Bitacora_2[[#This Row],[CO]])=6,Bitacora_2[[#This Row],[Clase Expedición]]="SEA"), "Complete", IF(AND(OR(Bitacora_2[[#This Row],[Mercado]]="EUROPE",Bitacora_2[[#This Row],[Mercado]]="UK"),COUNTA(Bitacora_2[[#This Row],[PHYTO]],Bitacora_2[[#This Row],[INVOICE]:[PL ]],Bitacora_2[[#This Row],[COI]])=5,Bitacora_2[[#This Row],[Clase Expedición]]="SEA",Bitacora_2[[#This Row],[Manejo]]="ORG"), "Complete", IF(AND(OR(Bitacora_2[[#This Row],[Mercado]]="EUROPE",Bitacora_2[[#This Row],[Mercado]]="UK"),COUNTA(Bitacora_2[[#This Row],[PHYTO]],Bitacora_2[[#This Row],[INVOICE]:[PL ]])=4,Bitacora_2[[#This Row],[Clase Expedición]]="SEA",Bitacora_2[[#This Row],[Manejo]]="CONV"), "Complete", IF(AND(OR(Bitacora_2[[#This Row],[Mercado]]="US WEST",Bitacora_2[[#This Row],[Mercado]]="US EAST",Bitacora_2[[#This Row],[Mercado]]="US SOUTH"),COUNTA(Bitacora_2[[#This Row],[PHYTO]:[ISF]],Bitacora_2[[#This Row],[CO]])=7,Bitacora_2[[#This Row],[Clase Expedición]]="SEA",Bitacora_2[[#This Row],[Exportador]]="ECHF"), "Complete", IF(AND(OR(Bitacora_2[[#This Row],[Mercado]]="US WEST",Bitacora_2[[#This Row],[Mercado]]="US EAST",Bitacora_2[[#This Row],[Mercado]]="US SOUTH"),COUNTA(Bitacora_2[[#This Row],[PHYTO]:[ISF]])=6,Bitacora_2[[#This Row],[Clase Expedición]]="SEA",Bitacora_2[[#This Row],[Exportador]]<>"ECHF"), "Complete", IF(AND(OR(Bitacora_2[[#This Row],[Mercado]]="ASIA",Bitacora_2[[#This Row],[Mercado]]="ASIA CN + HK"),COUNTA(Bitacora_2[[#This Row],[PHYTO]:[PL ]],Bitacora_2[[#This Row],[CO]])=6), "Complete","Incomplete")))))))) -> Complete | AM21: =+IF(OR(Bitacora_2[[#This Row],[Exportador]]="INVERSIONES JORDIE",Bitacora_2[[#This Row],[Exportador]]="TAL S.A."), "Tercero", "Propio") -> Tercero | AN21: =IF(AND(Bitacora_2[[#This Row],[Clase Expedición]]="AIR",OR(Bitacora_2[[#This Row],[Mercado]]="US EAST",Bitacora_2[[#This Row],[Mercado]]="US WEST",Bitacora_2[[#This Row],[Mercado]]="US SOUTH")),IF(Bitacora_2[[#This Row],[ETD Doc]]<>"","Delivered","Pending"), IF(Bitacora_2[[#This Row],[Clase Expedición]]="AIR","Delivered", IF(AND(Bitacora_2[[#This Row],[ETD Doc]]="",Bitacora_2[[#This Row],[ATA DOC]]=""),"Pending", IF(AND(Bitacora_2[[#This Row],[ETD Doc]]<>"",Bitacora_2[[#This Row],[ATA DOC]]=""),"In transit", IF(AND(Bitacora_2[[#This Row],[ETD Doc]]<>"",Bitacora_2[[#This Row],[ATA DOC]]<>""),"Delivered",""))))) -> Pending | AQ21: =IF(I21="SEA",IF(AP21="","On Hold","Released"),"")
A22: RH-0020T2TAL S.A.ARANCONV145-11634195 | B22: 23 | C22: 46175 | D22: 23 | E22: US EAST | F22: JFK | G22: PE | H22: TAL S.A. | I22: AIR | J22: ARAN | K22: CONV | L22: RH-0020T2 | M22: 145-11634195 | O22: NRF TIER I | P22: LATAM | R22: 46182 | S22: 46178 | U22: =+IF(Bitacora_2[[#This Row],[ATA DOC]]<>"",Bitacora_2[[#This Row],[ATA DOC]], IF(Bitacora_2[[#This Row],[Clase Expedición]]="AIR",Bitacora_2[[#This Row],[ETD Real]], IF(AND(Bitacora_2[[#This Row],[Clase Expedición]]="SEA",Bitacora_2[[#This Row],[Mercado]]="LATAM"), Bitacora_2[[#This Row],[ETD Real]]+3, IF(AND(Bitacora_2[[#This Row],[Clase Expedición]]="SEA",Bitacora_2[[#This Row],[Mercado]]="EUROPE"), Bitacora_2[[#This Row],[ETD Real]]+8, IF(AND(Bitacora_2[[#This Row],[Clase Expedición]]="SEA",Bitacora_2[[#This Row],[Mercado]]="UK"), Bitacora_2[[#This Row],[ETD Real]]+11, IF(AND(Bitacora_2[[#This Row],[Clase Expedición]]="SEA",OR(Bitacora_2[[#This Row],[Mercado]]="ASIA",Bitacora_2[[#This Row],[Mercado]]="ASIA CN + HK")), Bitacora_2[[#This Row],[ETD Real]]+14, IF(AND(Bitacora_2[[#This Row],[Clase Expedición]]="SEA",OR(Bitacora_2[[#This Row],[Mercado]]="US EAST",Bitacora_2[[#This Row],[Mercado]]="US WEST",Bitacora_2[[#This Row],[Mercado]]="US SOUTH")), Bitacora_2[[#This Row],[ETD Real]]+8,""))))))) -> 46182 | X22: =IF(OR(Bitacora_2[[#This Row],[ETD Real]]="",Bitacora_2[[#This Row],[ETD Doc]]=""),"",Bitacora_2[[#This Row],[ETD Doc]]-Bitacora_2[[#This Row],[ETD Real]]) | Y22: =IF(OR(Bitacora_2[[#This Row],[ATA DOC]]="",Bitacora_2[[#This Row],[ETA Real]]=""),"",Bitacora_2[[#This Row],[ETA Real]]-Bitacora_2[[#This Row],[ATA DOC]]) | AI22: =IF(AND(OR(E22="US EAST",E22="US WEST",E22="US SOUTH"),I22="SEA",Bitacora_2[[#This Row],[ETD Real]]-TODAY()>=3,Bitacora_2[[#This Row],[ISF]]<>"X"),"Pending", IF(AND(OR(E22="US EAST",E22="US WEST",E22="US SOUTH"),I22="SEA",Bitacora_2[[#This Row],[ETD Real]]-TODAY()=2,Bitacora_2[[#This Row],[ISF]]<>"X"),"Urgente", IF(AND(OR(E22="US EAST",E22="US WEST",E22="US SOUTH"),I22="SEA",Bitacora_2[[#This Row],[ETD Real]]-TODAY()<=1,Bitacora_2[[#This Row],[ISF]]<>"X"),"Muy Urgente", IF(AND(OR(E22="US EAST",E22="US WEST",E22="US SOUTH"),I22="SEA",Bitacora_2[[#This Row],[ISF]]="X"),"Sent","")))) | AJ22: =IF(AND(OR(Bitacora_2[[#This Row],[Clase Expedición]]="AIR",Bitacora_2[[#This Row],[Clase Expedición]]="TRK")),"Complete", IF(AND(Bitacora_2[[#This Row],[Mercado]]="LATAM",COUNTA(Bitacora_2[[#This Row],[PHYTO]:[ISF]],Bitacora_2[[#This Row],[CO]])=7,Bitacora_2[[#This Row],[Clase Expedición]]<>"TRK"), "Complete", IF(AND(Bitacora_2[[#This Row],[Mercado]]="LATAM",COUNTA(Bitacora_2[[#This Row],[PHYTO]:[PL ]],Bitacora_2[[#This Row],[CO]])=6,Bitacora_2[[#This Row],[Clase Expedición]]="SEA"), "Complete", IF(AND(OR(Bitacora_2[[#This Row],[Mercado]]="EUROPE",Bitacora_2[[#This Row],[Mercado]]="UK"),COUNTA(Bitacora_2[[#This Row],[PHYTO]],Bitacora_2[[#This Row],[INVOICE]:[PL ]],Bitacora_2[[#This Row],[COI]])=5,Bitacora_2[[#This Row],[Clase Expedición]]="SEA",Bitacora_2[[#This Row],[Manejo]]="ORG"), "Complete", IF(AND(OR(Bitacora_2[[#This Row],[Mercado]]="EUROPE",Bitacora_2[[#This Row],[Mercado]]="UK"),COUNTA(Bitacora_2[[#This Row],[PHYTO]],Bitacora_2[[#This Row],[INVOICE]:[PL ]])=4,Bitacora_2[[#This Row],[Clase Expedición]]="SEA",Bitacora_2[[#This Row],[Manejo]]="CONV"), "Complete", IF(AND(OR(Bitacora_2[[#This Row],[Mercado]]="US WEST",Bitacora_2[[#This Row],[Mercado]]="US EAST",Bitacora_2[[#This Row],[Mercado]]="US SOUTH"),COUNTA(Bitacora_2[[#This Row],[PHYTO]:[ISF]],Bitacora_2[[#This Row],[CO]])=7,Bitacora_2[[#This Row],[Clase Expedición]]="SEA",Bitacora_2[[#This Row],[Exportador]]="ECHF"), "Complete", IF(AND(OR(Bitacora_2[[#This Row],[Mercado]]="US WEST",Bitacora_2[[#This Row],[Mercado]]="US EAST",Bitacora_2[[#This Row],[Mercado]]="US SOUTH"),COUNTA(Bitacora_2[[#This Row],[PHYTO]:[ISF]])=6,Bitacora_2[[#This Row],[Clase Expedición]]="SEA",Bitacora_2[[#This Row],[Exportador]]<>"ECHF"), "Complete", IF(AND(OR(Bitacora_2[[#This Row],[Mercado]]="ASIA",Bitacora_2[[#This Row],[Mercado]]="ASIA CN + HK"),COUNTA(Bitacora_2[[#This Row],[PHYTO]:[PL ]],Bitacora_2[[#This Row],[CO]])=6), "Complete","Incomplete")))))))) -> Complete | AM22: =+IF(OR(Bitacora_2[[#This Row],[Exportador]]="INVERSIONES JORDIE",Bitacora_2[[#This Row],[Exportador]]="TAL S.A."), "Tercero", "Propio") -> Tercero | AN22: =IF(AND(Bitacora_2[[#This Row],[Clase Expedición]]="AIR",OR(Bitacora_2[[#This Row],[Mercado]]="US EAST",Bitacora_2[[#This Row],[Mercado]]="US WEST",Bitacora_2[[#This Row],[Mercado]]="US SOUTH")),IF(Bitacora_2[[#This Row],[ETD Doc]]<>"","Delivered","Pending"), IF(Bitacora_2[[#This Row],[Clase Expedición]]="AIR","Delivered", IF(AND(Bitacora_2[[#This Row],[ETD Doc]]="",Bitacora_2[[#This Row],[ATA DOC]]=""),"Pending", IF(AND(Bitacora_2[[#This Row],[ETD Doc]]<>"",Bitacora_2[[#This Row],[ATA DOC]]=""),"In transit", IF(AND(Bitacora_2[[#This Row],[ETD Doc]]<>"",Bitacora_2[[#This Row],[ATA DOC]]<>""),"Delivered",""))))) -> Pending | AQ22: =IF(I22="SEA",IF(AP22="","On Hold","Released"),"")
A23: RH-0023TTAL S.A.ARANCONVPE368300240 | B23: 23 | C23: 46176 | E23: LATAM | F23: BAR | G23: PE | H23: TAL S.A. | I23: TRK | J23: ARAN | K23: CONV | L23: RH-0023T | M23: PE368300240 | O23: BERRYGOOD | P23: TERRESTRE | R23: 46181 | U23: =+IF(Bitacora_2[[#This Row],[ATA DOC]]<>"",Bitacora_2[[#This Row],[ATA DOC]], IF(Bitacora_2[[#This Row],[Clase Expedición]]="AIR",Bitacora_2[[#This Row],[ETD Real]], IF(AND(Bitacora_2[[#This Row],[Clase Expedición]]="SEA",Bitacora_2[[#This Row],[Mercado]]="LATAM"), Bitacora_2[[#This Row],[ETD Real]]+3, IF(AND(Bitacora_2[[#This Row],[Clase Expedición]]="SEA",Bitacora_2[[#This Row],[Mercado]]="EUROPE"), Bitacora_2[[#This Row],[ETD Real]]+8, IF(AND(Bitacora_2[[#This Row],[Clase Expedición]]="SEA",Bitacora_2[[#This Row],[Mercado]]="UK"), Bitacora_2[[#This Row],[ETD Real]]+11, IF(AND(Bitacora_2[[#This Row],[Clase Expedición]]="SEA",OR(Bitacora_2[[#This Row],[Mercado]]="ASIA",Bitacora_2[[#This Row],[Mercado]]="ASIA CN + HK")), Bitacora_2[[#This Row],[ETD Real]]+14, IF(AND(Bitacora_2[[#This Row],[Clase Expedición]]="SEA",OR(Bitacora_2[[#This Row],[Mercado]]="US EAST",Bitacora_2[[#This Row],[Mercado]]="US WEST",Bitacora_2[[#This Row],[Mercado]]="US SOUTH")), Bitacora_2[[#This Row],[ETD Real]]+8,""))))))) | X23: =IF(OR(Bitacora_2[[#This Row],[ETD Real]]="",Bitacora_2[[#This Row],[ETD Doc]]=""),"",Bitacora_2[[#This Row],[ETD Doc]]-Bitacora_2[[#This Row],[ETD Real]]) | Y23: =IF(OR(Bitacora_2[[#This Row],[ATA DOC]]="",Bitacora_2[[#This Row],[ETA Real]]=""),"",Bitacora_2[[#This Row],[ETA Real]]-Bitacora_2[[#This Row],[ATA DOC]]) | AI23: =IF(AND(OR(E23="US EAST",E23="US WEST",E23="US SOUTH"),I23="SEA",Bitacora_2[[#This Row],[ETD Real]]-TODAY()>=3,Bitacora_2[[#This Row],[ISF]]<>"X"),"Pending", IF(AND(OR(E23="US EAST",E23="US WEST",E23="US SOUTH"),I23="SEA",Bitacora_2[[#This Row],[ETD Real]]-TODAY()=2,Bitacora_2[[#This Row],[ISF]]<>"X"),"Urgente", IF(AND(OR(E23="US EAST",E23="US WEST",E23="US SOUTH"),I23="SEA",Bitacora_2[[#This Row],[ETD Real]]-TODAY()<=1,Bitacora_2[[#This Row],[ISF]]<>"X"),"Muy Urgente", IF(AND(OR(E23="US EAST",E23="US WEST",E23="US SOUTH"),I23="SEA",Bitacora_2[[#This Row],[ISF]]="X"),"Sent","")))) | AJ23: =IF(AND(OR(Bitacora_2[[#This Row],[Clase Expedición]]="AIR",Bitacora_2[[#This Row],[Clase Expedición]]="TRK")),"Complete", IF(AND(Bitacora_2[[#This Row],[Mercado]]="LATAM",COUNTA(Bitacora_2[[#This Row],[PHYTO]:[ISF]],Bitacora_2[[#This Row],[CO]])=7,Bitacora_2[[#This Row],[Clase Expedición]]<>"TRK"), "Complete", IF(AND(Bitacora_2[[#This Row],[Mercado]]="LATAM",COUNTA(Bitacora_2[[#This Row],[PHYTO]:[PL ]],Bitacora_2[[#This Row],[CO]])=6,Bitacora_2[[#This Row],[Clase Expedición]]="SEA"), "Complete", IF(AND(OR(Bitacora_2[[#This Row],[Mercado]]="EUROPE",Bitacora_2[[#This Row],[Mercado]]="UK"),COUNTA(Bitacora_2[[#This Row],[PHYTO]],Bitacora_2[[#This Row],[INVOICE]:[PL ]],Bitacora_2[[#This Row],[COI]])=5,Bitacora_2[[#This Row],[Clase Expedición]]="SEA",Bitacora_2[[#This Row],[Manejo]]="ORG"), "Complete", IF(AND(OR(Bitacora_2[[#This Row],[Mercado]]="EUROPE",Bitacora_2[[#This Row],[Mercado]]="UK"),COUNTA(Bitacora_2[[#This Row],[PHYTO]],Bitacora_2[[#This Row],[INVOICE]:[PL ]])=4,Bitacora_2[[#This Row],[Clase Expedición]]="SEA",Bitacora_2[[#This Row],[Manejo]]="CONV"), "Complete", IF(AND(OR(Bitacora_2[[#This Row],[Mercado]]="US WEST",Bitacora_2[[#This Row],[Mercado]]="US EAST",Bitacora_2[[#This Row],[Mercado]]="US SOUTH"),COUNTA(Bitacora_2[[#This Row],[PHYTO]:[ISF]],Bitacora_2[[#This Row],[CO]])=7,Bitacora_2[[#This Row],[Clase Expedición]]="SEA",Bitacora_2[[#This Row],[Exportador]]="ECHF"), "Complete", IF(AND(OR(Bitacora_2[[#This Row],[Mercado]]="US WEST",Bitacora_2[[#This Row],[Mercado]]="US EAST",Bitacora_2[[#This Row],[Mercado]]="US SOUTH"),COUNTA(Bitacora_2[[#This Row],[PHYTO]:[ISF]])=6,Bitacora_2[[#This Row],[Clase Expedición]]="SEA",Bitacora_2[[#This Row],[Exportador]]<>"ECHF"), "Complete", IF(AND(OR(Bitacora_2[[#This Row],[Mercado]]="ASIA",Bitacora_2[[#This Row],[Mercado]]="ASIA CN + HK"),COUNTA(Bitacora_2[[#This Row],[PHYTO]:[PL ]],Bitacora_2[[#This Row],[CO]])=6), "Complete","Incomplete")))))))) -> Complete | AM23: =+IF(OR(Bitacora_2[[#This Row],[Exportador]]="INVERSIONES JORDIE",Bitacora_2[[#This Row],[Exportador]]="TAL S.A."), "Tercero", "Propio") -> Tercero | AN23: =IF(AND(Bitacora_2[[#This Row],[Clase Expedición]]="AIR",OR(Bitacora_2[[#This Row],[Mercado]]="US EAST",Bitacora_2[[#This Row],[Mercado]]="US WEST",Bitacora_2[[#This Row],[Mercado]]="US SOUTH")),IF(Bitacora_2[[#This Row],[ETD Doc]]<>"","Delivered","Pending"), IF(Bitacora_2[[#This Row],[Clase Expedición]]="AIR","Delivered", IF(AND(Bitacora_2[[#This Row],[ETD Doc]]="",Bitacora_2[[#This Row],[ATA DOC]]=""),"Pending", IF(AND(Bitacora_2[[#This Row],[ETD Doc]]<>"",Bitacora_2[[#This Row],[ATA DOC]]=""),"In transit", IF(AND(Bitacora_2[[#This Row],[ETD Doc]]<>"",Bitacora_2[[#This Row],[ATA DOC]]<>""),"Delivered",""))))) -> Pending | AQ23: =IF(I23="SEA",IF(AP23="","On Hold","Released"),"")
A24: PO00000050955HFPEARANCONV497-24320682 | B24: 23 | C24: 46178 | D24: 23 | E24: LATAM | F24: BOG | G24: PE | H24: HFPE | I24: AIR | J24: ARAN | K24: CONV | L24: PO00000050955 | M24: 497-24320682 | N24: HORTIFRUT COLOMBIA SAS | O24: HORTIFRUT COLOMBIA | P24: AERCARIBE | R24: 46182 | S24: 46178 | T24: HELLMANN | U24: =+IF(Bitacora_2[[#This Row],[ATA DOC]]<>"",Bitacora_2[[#This Row],[ATA DOC]], IF(Bitacora_2[[#This Row],[Clase Expedición]]="AIR",Bitacora_2[[#This Row],[ETD Real]], IF(AND(Bitacora_2[[#This Row],[Clase Expedición]]="SEA",Bitacora_2[[#This Row],[Mercado]]="LATAM"), Bitacora_2[[#This Row],[ETD Real]]+3, IF(AND(Bitacora_2[[#This Row],[Clase Expedición]]="SEA",Bitacora_2[[#This Row],[Mercado]]="EUROPE"), Bitacora_2[[#This Row],[ETD Real]]+8, IF(AND(Bitacora_2[[#This Row],[Clase Expedición]]="SEA",Bitacora_2[[#This Row],[Mercado]]="UK"), Bitacora_2[[#This Row],[ETD Real]]+11, IF(AND(Bitacora_2[[#This Row],[Clase Expedición]]="SEA",OR(Bitacora_2[[#This Row],[Mercado]]="ASIA",Bitacora_2[[#This Row],[Mercado]]="ASIA CN + HK")), Bitacora_2[[#This Row],[ETD Real]]+14, IF(AND(Bitacora_2[[#This Row],[Clase Expedición]]="SEA",OR(Bitacora_2[[#This Row],[Mercado]]="US EAST",Bitacora_2[[#This Row],[Mercado]]="US WEST",Bitacora_2[[#This Row],[Mercado]]="US SOUTH")), Bitacora_2[[#This Row],[ETD Real]]+8,""))))))) -> 46182 | X24: =IF(OR(Bitacora_2[[#This Row],[ETD Real]]="",Bitacora_2[[#This Row],[ETD Doc]]=""),"",Bitacora_2[[#This Row],[ETD Doc]]-Bitacora_2[[#This Row],[ETD Real]]) | Y24: =IF(OR(Bitacora_2[[#This Row],[ATA DOC]]="",Bitacora_2[[#This Row],[ETA Real]]=""),"",Bitacora_2[[#This Row],[ETA Real]]-Bitacora_2[[#This Row],[ATA DOC]]) | AI24: =IF(AND(OR(E24="US EAST",E24="US WEST",E24="US SOUTH"),I24="SEA",Bitacora_2[[#This Row],[ETD Real]]-TODAY()>=3,Bitacora_2[[#This Row],[ISF]]<>"X"),"Pending", IF(AND(OR(E24="US EAST",E24="US WEST",E24="US SOUTH"),I24="SEA",Bitacora_2[[#This Row],[ETD Real]]-TODAY()=2,Bitacora_2[[#This Row],[ISF]]<>"X"),"Urgente", IF(AND(OR(E24="US EAST",E24="US WEST",E24="US SOUTH"),I24="SEA",Bitacora_2[[#This Row],[ETD Real]]-TODAY()<=1,Bitacora_2[[#This Row],[ISF]]<>"X"),"Muy Urgente", IF(AND(OR(E24="US EAST",E24="US WEST",E24="US SOUTH"),I24="SEA",Bitacora_2[[#This Row],[ISF]]="X"),"Sent","")))) | AJ24: =IF(AND(OR(Bitacora_2[[#This Row],[Clase Expedición]]="AIR",Bitacora_2[[#This Row],[Clase Expedición]]="TRK")),"Complete", IF(AND(Bitacora_2[[#This Row],[Mercado]]="LATAM",COUNTA(Bitacora_2[[#This Row],[PHYTO]:[ISF]],Bitacora_2[[#This Row],[CO]])=7,Bitacora_2[[#This Row],[Clase Expedición]]<>"TRK"), "Complete", IF(AND(Bitacora_2[[#This Row],[Mercado]]="LATAM",COUNTA(Bitacora_2[[#This Row],[PHYTO]:[PL ]],Bitacora_2[[#This Row],[CO]])=6,Bitacora_2[[#This Row],[Clase Expedición]]="SEA"), "Complete", IF(AND(OR(Bitacora_2[[#This Row],[Mercado]]="EUROPE",Bitacora_2[[#This Row],[Mercado]]="UK"),COUNTA(Bitacora_2[[#This Row],[PHYTO]],Bitacora_2[[#This Row],[INVOICE]:[PL ]],Bitacora_2[[#This Row],[COI]])=5,Bitacora_2[[#This Row],[Clase Expedición]]="SEA",Bitacora_2[[#This Row],[Manejo]]="ORG"), "Complete", IF(AND(OR(Bitacora_2[[#This Row],[Mercado]]="EUROPE",Bitacora_2[[#This Row],[Mercado]]="UK"),COUNTA(Bitacora_2[[#This Row],[PHYTO]],Bitacora_2[[#This Row],[INVOICE]:[PL ]])=4,Bitacora_2[[#This Row],[Clase Expedición]]="SEA",Bitacora_2[[#This Row],[Manejo]]="CONV"), "Complete", IF(AND(OR(Bitacora_2[[#This Row],[Mercado]]="US WEST",Bitacora_2[[#This Row],[Mercado]]="US EAST",Bitacora_2[[#This Row],[Mercado]]="US SOUTH"),COUNTA(Bitacora_2[[#This Row],[PHYTO]:[ISF]],Bitacora_2[[#This Row],[CO]])=7,Bitacora_2[[#This Row],[Clase Expedición]]="SEA",Bitacora_2[[#This Row],[Exportador]]="ECHF"), "Complete", IF(AND(OR(Bitacora_2[[#This Row],[Mercado]]="US WEST",Bitacora_2[[#This Row],[Mercado]]="US EAST",Bitacora_2[[#This Row],[Mercado]]="US SOUTH"),COUNTA(Bitacora_2[[#This Row],[PHYTO]:[ISF]])=6,Bitacora_2[[#This Row],[Clase Expedición]]="SEA",Bitacora_2[[#This Row],[Exportador]]<>"ECHF"), "Complete", IF(AND(OR(Bitacora_2[[#This Row],[Mercado]]="ASIA",Bitacora_2[[#This Row],[Mercado]]="ASIA CN + HK"),COUNTA(Bitacora_2[[#This Row],[PHYTO]:[PL ]],Bitacora_2[[#This Row],[CO]])=6), "Complete","Incomplete")))))))) -> Complete | AM24: =+IF(OR(Bitacora_2[[#This Row],[Exportador]]="INVERSIONES JORDIE",Bitacora_2[[#This Row],[Exportador]]="TAL S.A."), "Tercero", "Propio") -> Propio | AN24: =IF(AND(Bitacora_2[[#This Row],[Clase Expedición]]="AIR",OR(Bitacora_2[[#This Row],[Mercado]]="US EAST",Bitacora_2[[#This Row],[Mercado]]="US WEST",Bitacora_2[[#This Row],[Mercado]]="US SOUTH")),IF(Bitacora_2[[#This Row],[ETD Doc]]<>"","Delivered","Pending"), IF(Bitacora_2[[#This Row],[Clase Expedición]]="AIR","Delivered", IF(AND(Bitacora_2[[#This Row],[ETD Doc]]="",Bitacora_2[[#This Row],[ATA DOC]]=""),"Pending", IF(AND(Bitacora_2[[#This Row],[ETD Doc]]<>"",Bitacora_2[[#This Row],[ATA DOC]]=""),"In transit", IF(AND(Bitacora_2[[#This Row],[ETD Doc]]<>"",Bitacora_2[[#This Row],[ATA DOC]]<>""),"Delivered",""))))) -> Delivered | AQ24: =IF(I24="SEA",IF(AP24="","On Hold","Released"),"")
A25: PO00000050956HFPEARANCONV497-24320693 | B25: 23 | C25: 46178 | D25: 23 | E25: LATAM | F25: BOG | G25: PE | H25: HFPE | I25: AIR | J25: ARAN | K25: CONV | L25: PO00000050956 | M25: 497-24320693 | N25: HORTIFRUT COLOMBIA SAS | O25: HORTIFRUT COLOMBIA | P25: AERCARIBE | R25: 46182 | S25: 46178 | T25: HELLMANN | U25: =+IF(Bitacora_2[[#This Row],[ATA DOC]]<>"",Bitacora_2[[#This Row],[ATA DOC]], IF(Bitacora_2[[#This Row],[Clase Expedición]]="AIR",Bitacora_2[[#This Row],[ETD Real]], IF(AND(Bitacora_2[[#This Row],[Clase Expedición]]="SEA",Bitacora_2[[#This Row],[Mercado]]="LATAM"), Bitacora_2[[#This Row],[ETD Real]]+3, IF(AND(Bitacora_2[[#This Row],[Clase Expedición]]="SEA",Bitacora_2[[#This Row],[Mercado]]="EUROPE"), Bitacora_2[[#This Row],[ETD Real]]+8, IF(AND(Bitacora_2[[#This Row],[Clase Expedición]]="SEA",Bitacora_2[[#This Row],[Mercado]]="UK"), Bitacora_2[[#This Row],[ETD Real]]+11, IF(AND(Bitacora_2[[#This Row],[Clase Expedición]]="SEA",OR(Bitacora_2[[#This Row],[Mercado]]="ASIA",Bitacora_2[[#This Row],[Mercado]]="ASIA CN + HK")), Bitacora_2[[#This Row],[ETD Real]]+14, IF(AND(Bitacora_2[[#This Row],[Clase Expedición]]="SEA",OR(Bitacora_2[[#This Row],[Mercado]]="US EAST",Bitacora_2[[#This Row],[Mercado]]="US WEST",Bitacora_2[[#This Row],[Mercado]]="US SOUTH")), Bitacora_2[[#This Row],[ETD Real]]+8,""))))))) -> 46182 | X25: =IF(OR(Bitacora_2[[#This Row],[ETD Real]]="",Bitacora_2[[#This Row],[ETD Doc]]=""),"",Bitacora_2[[#This Row],[ETD Doc]]-Bitacora_2[[#This Row],[ETD Real]]) | Y25: =IF(OR(Bitacora_2[[#This Row],[ATA DOC]]="",Bitacora_2[[#This Row],[ETA Real]]=""),"",Bitacora_2[[#This Row],[ETA Real]]-Bitacora_2[[#This Row],[ATA DOC]]) | AI25: =IF(AND(OR(E25="US EAST",E25="US WEST",E25="US SOUTH"),I25="SEA",Bitacora_2[[#This Row],[ETD Real]]-TODAY()>=3,Bitacora_2[[#This Row],[ISF]]<>"X"),"Pending", IF(AND(OR(E25="US EAST",E25="US WEST",E25="US SOUTH"),I25="SEA",Bitacora_2[[#This Row],[ETD Real]]-TODAY()=2,Bitacora_2[[#This Row],[ISF]]<>"X"),"Urgente", IF(AND(OR(E25="US EAST",E25="US WEST",E25="US SOUTH"),I25="SEA",Bitacora_2[[#This Row],[ETD Real]]-TODAY()<=1,Bitacora_2[[#This Row],[ISF]]<>"X"),"Muy Urgente", IF(AND(OR(E25="US EAST",E25="US WEST",E25="US SOUTH"),I25="SEA",Bitacora_2[[#This Row],[ISF]]="X"),"Sent","")))) | AJ25: =IF(AND(OR(Bitacora_2[[#This Row],[Clase Expedición]]="AIR",Bitacora_2[[#This Row],[Clase Expedición]]="TRK")),"Complete", IF(AND(Bitacora_2[[#This Row],[Mercado]]="LATAM",COUNTA(Bitacora_2[[#This Row],[PHYTO]:[ISF]],Bitacora_2[[#This Row],[CO]])=7,Bitacora_2[[#This Row],[Clase Expedición]]<>"TRK"), "Complete", IF(AND(Bitacora_2[[#This Row],[Mercado]]="LATAM",COUNTA(Bitacora_2[[#This Row],[PHYTO]:[PL ]],Bitacora_2[[#This Row],[CO]])=6,Bitacora_2[[#This Row],[Clase Expedición]]="SEA"), "Complete", IF(AND(OR(Bitacora_2[[#This Row],[Mercado]]="EUROPE",Bitacora_2[[#This Row],[Mercado]]="UK"),COUNTA(Bitacora_2[[#This Row],[PHYTO]],Bitacora_2[[#This Row],[INVOICE]:[PL ]],Bitacora_2[[#This Row],[COI]])=5,Bitacora_2[[#This Row],[Clase Expedición]]="SEA",Bitacora_2[[#This Row],[Manejo]]="ORG"), "Complete", IF(AND(OR(Bitacora_2[[#This Row],[Mercado]]="EUROPE",Bitacora_2[[#This Row],[Mercado]]="UK"),COUNTA(Bitacora_2[[#This Row],[PHYTO]],Bitacora_2[[#This Row],[INVOICE]:[PL ]])=4,Bitacora_2[[#This Row],[Clase Expedición]]="SEA",Bitacora_2[[#This Row],[Manejo]]="CONV"), "Complete", IF(AND(OR(Bitacora_2[[#This Row],[Mercado]]="US WEST",Bitacora_2[[#This Row],[Mercado]]="US EAST",Bitacora_2[[#This Row],[Mercado]]="US SOUTH"),COUNTA(Bitacora_2[[#This Row],[PHYTO]:[ISF]],Bitacora_2[[#This Row],[CO]])=7,Bitacora_2[[#This Row],[Clase Expedición]]="SEA",Bitacora_2[[#This Row],[Exportador]]="ECHF"), "Complete", IF(AND(OR(Bitacora_2[[#This Row],[Mercado]]="US WEST",Bitacora_2[[#This Row],[Mercado]]="US EAST",Bitacora_2[[#This Row],[Mercado]]="US SOUTH"),COUNTA(Bitacora_2[[#This Row],[PHYTO]:[ISF]])=6,Bitacora_2[[#This Row],[Clase Expedición]]="SEA",Bitacora_2[[#This Row],[Exportador]]<>"ECHF"), "Complete", IF(AND(OR(Bitacora_2[[#This Row],[Mercado]]="ASIA",Bitacora_2[[#This Row],[Mercado]]="ASIA CN + HK"),COUNTA(Bitacora_2[[#This Row],[PHYTO]:[PL ]],Bitacora_2[[#This Row],[CO]])=6), "Complete","Incomplete")))))))) -> Complete | AM25: =+IF(OR(Bitacora_2[[#This Row],[Exportador]]="INVERSIONES JORDIE",Bitacora_2[[#This Row],[Exportador]]="TAL S.A."), "Tercero", "Propio") -> Propio | AN25: =IF(AND(Bitacora_2[[#This Row],[Clase Expedición]]="AIR",OR(Bitacora_2[[#This Row],[Mercado]]="US EAST",Bitacora_2[[#This Row],[Mercado]]="US WEST",Bitacora_2[[#This Row],[Mercado]]="US SOUTH")),IF(Bitacora_2[[#This Row],[ETD Doc]]<>"","Delivered","Pending"), IF(Bitacora_2[[#This Row],[Clase Expedición]]="AIR","Delivered", IF(AND(Bitacora_2[[#This Row],[ETD Doc]]="",Bitacora_2[[#This Row],[ATA DOC]]=""),"Pending", IF(AND(Bitacora_2[[#This Row],[ETD Doc]]<>"",Bitacora_2[[#This Row],[ATA DOC]]=""),"In transit", IF(AND(Bitacora_2[[#This Row],[ETD Doc]]<>"",Bitacora_2[[#This Row],[ATA DOC]]<>""),"Delivered",""))))) -> Delivered | AQ25: =IF(I25="SEA",IF(AP25="","On Hold","Released"),"")
A26: PO00000050966HFPEARANCONV145-11634103 | B26: 23 | C26: 46178 | D26: 23 | E26: US EAST | F26: JFK | G26: PE | H26: HFPE | I26: AIR | J26: ARAN | K26: CONV | L26: PO00000050966 | M26: 145-11634103 | N26: HORTIFRUT IMPORTS INC. (PHI-BOAT) | O26: NRF TIER I | P26: LATAM | R26: 46181 | S26: 46178 | T26: HELLMANN | U26: =+IF(Bitacora_2[[#This Row],[ATA DOC]]<>"",Bitacora_2[[#This Row],[ATA DOC]], IF(Bitacora_2[[#This Row],[Clase Expedición]]="AIR",Bitacora_2[[#This Row],[ETD Real]], IF(AND(Bitacora_2[[#This Row],[Clase Expedición]]="SEA",Bitacora_2[[#This Row],[Mercado]]="LATAM"), Bitacora_2[[#This Row],[ETD Real]]+3, IF(AND(Bitacora_2[[#This Row],[Clase Expedición]]="SEA",Bitacora_2[[#This Row],[Mercado]]="EUROPE"), Bitacora_2[[#This Row],[ETD Real]]+8, IF(AND(Bitacora_2[[#This Row],[Clase Expedición]]="SEA",Bitacora_2[[#This Row],[Mercado]]="UK"), Bitacora_2[[#This Row],[ETD Real]]+11, IF(AND(Bitacora_2[[#This Row],[Clase Expedición]]="SEA",OR(Bitacora_2[[#This Row],[Mercado]]="ASIA",Bitacora_2[[#This Row],[Mercado]]="ASIA CN + HK")), Bitacora_2[[#This Row],[ETD Real]]+14, IF(AND(Bitacora_2[[#This Row],[Clase Expedición]]="SEA",OR(Bitacora_2[[#This Row],[Mercado]]="US EAST",Bitacora_2[[#This Row],[Mercado]]="US WEST",Bitacora_2[[#This Row],[Mercado]]="US SOUTH")), Bitacora_2[[#This Row],[ETD Real]]+8,""))))))) -> 46181 | X26: =IF(OR(Bitacora_2[[#This Row],[ETD Real]]="",Bitacora_2[[#This Row],[ETD Doc]]=""),"",Bitacora_2[[#This Row],[ETD Doc]]-Bitacora_2[[#This Row],[ETD Real]]) | Y26: =IF(OR(Bitacora_2[[#This Row],[ATA DOC]]="",Bitacora_2[[#This Row],[ETA Real]]=""),"",Bitacora_2[[#This Row],[ETA Real]]-Bitacora_2[[#This Row],[ATA DOC]]) | AI26: =IF(AND(OR(E26="US EAST",E26="US WEST",E26="US SOUTH"),I26="SEA",Bitacora_2[[#This Row],[ETD Real]]-TODAY()>=3,Bitacora_2[[#This Row],[ISF]]<>"X"),"Pending", IF(AND(OR(E26="US EAST",E26="US WEST",E26="US SOUTH"),I26="SEA",Bitacora_2[[#This Row],[ETD Real]]-TODAY()=2,Bitacora_2[[#This Row],[ISF]]<>"X"),"Urgente", IF(AND(OR(E26="US EAST",E26="US WEST",E26="US SOUTH"),I26="SEA",Bitacora_2[[#This Row],[ETD Real]]-TODAY()<=1,Bitacora_2[[#This Row],[ISF]]<>"X"),"Muy Urgente", IF(AND(OR(E26="US EAST",E26="US WEST",E26="US SOUTH"),I26="SEA",Bitacora_2[[#This Row],[ISF]]="X"),"Sent","")))) | AJ26: =IF(AND(OR(Bitacora_2[[#This Row],[Clase Expedición]]="AIR",Bitacora_2[[#This Row],[Clase Expedición]]="TRK")),"Complete", IF(AND(Bitacora_2[[#This Row],[Mercado]]="LATAM",COUNTA(Bitacora_2[[#This Row],[PHYTO]:[ISF]],Bitacora_2[[#This Row],[CO]])=7,Bitacora_2[[#This Row],[Clase Expedición]]<>"TRK"), "Complete", IF(AND(Bitacora_2[[#This Row],[Mercado]]="LATAM",COUNTA(Bitacora_2[[#This Row],[PHYTO]:[PL ]],Bitacora_2[[#This Row],[CO]])=6,Bitacora_2[[#This Row],[Clase Expedición]]="SEA"), "Complete", IF(AND(OR(Bitacora_2[[#This Row],[Mercado]]="EUROPE",Bitacora_2[[#This Row],[Mercado]]="UK"),COUNTA(Bitacora_2[[#This Row],[PHYTO]],Bitacora_2[[#This Row],[INVOICE]:[PL ]],Bitacora_2[[#This Row],[COI]])=5,Bitacora_2[[#This Row],[Clase Expedición]]="SEA",Bitacora_2[[#This Row],[Manejo]]="ORG"), "Complete", IF(AND(OR(Bitacora_2[[#This Row],[Mercado]]="EUROPE",Bitacora_2[[#This Row],[Mercado]]="UK"),COUNTA(Bitacora_2[[#This Row],[PHYTO]],Bitacora_2[[#This Row],[INVOICE]:[PL ]])=4,Bitacora_2[[#This Row],[Clase Expedición]]="SEA",Bitacora_2[[#This Row],[Manejo]]="CONV"), "Complete", IF(AND(OR(Bitacora_2[[#This Row],[Mercado]]="US WEST",Bitacora_2[[#This Row],[Mercado]]="US EAST",Bitacora_2[[#This Row],[Mercado]]="US SOUTH"),COUNTA(Bitacora_2[[#This Row],[PHYTO]:[ISF]],Bitacora_2[[#This Row],[CO]])=7,Bitacora_2[[#This Row],[Clase Expedición]]="SEA",Bitacora_2[[#This Row],[Exportador]]="ECHF"), "Complete", IF(AND(OR(Bitacora_2[[#This Row],[Mercado]]="US WEST",Bitacora_2[[#This Row],[Mercado]]="US EAST",Bitacora_2[[#This Row],[Mercado]]="US SOUTH"),COUNTA(Bitacora_2[[#This Row],[PHYTO]:[ISF]])=6,Bitacora_2[[#This Row],[Clase Expedición]]="SEA",Bitacora_2[[#This Row],[Exportador]]<>"ECHF"), "Complete", IF(AND(OR(Bitacora_2[[#This Row],[Mercado]]="ASIA",Bitacora_2[[#This Row],[Mercado]]="ASIA CN + HK"),COUNTA(Bitacora_2[[#This Row],[PHYTO]:[PL ]],Bitacora_2[[#This Row],[CO]])=6), "Complete","Incomplete")))))))) -> Complete | AM26: =+IF(OR(Bitacora_2[[#This Row],[Exportador]]="INVERSIONES JORDIE",Bitacora_2[[#This Row],[Exportador]]="TAL S.A."), "Tercero", "Propio") -> Propio | AN26: =IF(AND(Bitacora_2[[#This Row],[Clase Expedición]]="AIR",OR(Bitacora_2[[#This Row],[Mercado]]="US EAST",Bitacora_2[[#This Row],[Mercado]]="US WEST",Bitacora_2[[#This Row],[Mercado]]="US SOUTH")),IF(Bitacora_2[[#This Row],[ETD Doc]]<>"","Delivered","Pending"), IF(Bitacora_2[[#This Row],[Clase Expedición]]="AIR","Delivered", IF(AND(Bitacora_2[[#This Row],[ETD Doc]]="",Bitacora_2[[#This Row],[ATA DOC]]=""),"Pending", IF(AND(Bitacora_2[[#This Row],[ETD Doc]]<>"",Bitacora_2[[#This Row],[ATA DOC]]=""),"In transit", IF(AND(Bitacora_2[[#This Row],[ETD Doc]]<>"",Bitacora_2[[#This Row],[ATA DOC]]<>""),"Delivered",""))))) -> Pending | AQ26: =IF(I26="SEA",IF(AP26="","On Hold","Released"),"")
A27: PO00000050967HFPEARANCONV145-11634114 | B27: 23 | C27: 46178 | D27: 23 | E27: US EAST | F27: JFK | G27: PE | H27: HFPE | I27: AIR | J27: ARAN | K27: CONV | L27: PO00000050967 | M27: 145-11634114 | N27: HORTIFRUT IMPORTS INC. (PHI-BOAT) | O27: NRF TIER I | P27: LATAM | R27: 46181 | S27: 46178 | T27: HELLMANN | U27: =+IF(Bitacora_2[[#This Row],[ATA DOC]]<>"",Bitacora_2[[#This Row],[ATA DOC]], IF(Bitacora_2[[#This Row],[Clase Expedición]]="AIR",Bitacora_2[[#This Row],[ETD Real]], IF(AND(Bitacora_2[[#This Row],[Clase Expedición]]="SEA",Bitacora_2[[#This Row],[Mercado]]="LATAM"), Bitacora_2[[#This Row],[ETD Real]]+3, IF(AND(Bitacora_2[[#This Row],[Clase Expedición]]="SEA",Bitacora_2[[#This Row],[Mercado]]="EUROPE"), Bitacora_2[[#This Row],[ETD Real]]+8, IF(AND(Bitacora_2[[#This Row],[Clase Expedición]]="SEA",Bitacora_2[[#This Row],[Mercado]]="UK"), Bitacora_2[[#This Row],[ETD Real]]+11, IF(AND(Bitacora_2[[#This Row],[Clase Expedición]]="SEA",OR(Bitacora_2[[#This Row],[Mercado]]="ASIA",Bitacora_2[[#This Row],[Mercado]]="ASIA CN + HK")), Bitacora_2[[#This Row],[ETD Real]]+14, IF(AND(Bitacora_2[[#This Row],[Clase Expedición]]="SEA",OR(Bitacora_2[[#This Row],[Mercado]]="US EAST",Bitacora_2[[#This Row],[Mercado]]="US WEST",Bitacora_2[[#This Row],[Mercado]]="US SOUTH")), Bitacora_2[[#This Row],[ETD Real]]+8,""))))))) -> 46181 | X27: =IF(OR(Bitacora_2[[#This Row],[ETD Real]]="",Bitacora_2[[#This Row],[ETD Doc]]=""),"",Bitacora_2[[#This Row],[ETD Doc]]-Bitacora_2[[#This Row],[ETD Real]]) | Y27: =IF(OR(Bitacora_2[[#This Row],[ATA DOC]]="",Bitacora_2[[#This Row],[ETA Real]]=""),"",Bitacora_2[[#This Row],[ETA Real]]-Bitacora_2[[#This Row],[ATA DOC]]) | AI27: =IF(AND(OR(E27="US EAST",E27="US WEST",E27="US SOUTH"),I27="SEA",Bitacora_2[[#This Row],[ETD Real]]-TODAY()>=3,Bitacora_2[[#This Row],[ISF]]<>"X"),"Pending", IF(AND(OR(E27="US EAST",E27="US WEST",E27="US SOUTH"),I27="SEA",Bitacora_2[[#This Row],[ETD Real]]-TODAY()=2,Bitacora_2[[#This Row],[ISF]]<>"X"),"Urgente", IF(AND(OR(E27="US EAST",E27="US WEST",E27="US SOUTH"),I27="SEA",Bitacora_2[[#This Row],[ETD Real]]-TODAY()<=1,Bitacora_2[[#This Row],[ISF]]<>"X"),"Muy Urgente", IF(AND(OR(E27="US EAST",E27="US WEST",E27="US SOUTH"),I27="SEA",Bitacora_2[[#This Row],[ISF]]="X"),"Sent","")))) | AJ27: =IF(AND(OR(Bitacora_2[[#This Row],[Clase Expedición]]="AIR",Bitacora_2[[#This Row],[Clase Expedición]]="TRK")),"Complete", IF(AND(Bitacora_2[[#This Row],[Mercado]]="LATAM",COUNTA(Bitacora_2[[#This Row],[PHYTO]:[ISF]],Bitacora_2[[#This Row],[CO]])=7,Bitacora_2[[#This Row],[Clase Expedición]]<>"TRK"), "Complete", IF(AND(Bitacora_2[[#This Row],[Mercado]]="LATAM",COUNTA(Bitacora_2[[#This Row],[PHYTO]:[PL ]],Bitacora_2[[#This Row],[CO]])=6,Bitacora_2[[#This Row],[Clase Expedición]]="SEA"), "Complete", IF(AND(OR(Bitacora_2[[#This Row],[Mercado]]="EUROPE",Bitacora_2[[#This Row],[Mercado]]="UK"),COUNTA(Bitacora_2[[#This Row],[PHYTO]],Bitacora_2[[#This Row],[INVOICE]:[PL ]],Bitacora_2[[#This Row],[COI]])=5,Bitacora_2[[#This Row],[Clase Expedición]]="SEA",Bitacora_2[[#This Row],[Manejo]]="ORG"), "Complete", IF(AND(OR(Bitacora_2[[#This Row],[Mercado]]="EUROPE",Bitacora_2[[#This Row],[Mercado]]="UK"),COUNTA(Bitacora_2[[#This Row],[PHYTO]],Bitacora_2[[#This Row],[INVOICE]:[PL ]])=4,Bitacora_2[[#This Row],[Clase Expedición]]="SEA",Bitacora_2[[#This Row],[Manejo]]="CONV"), "Complete", IF(AND(OR(Bitacora_2[[#This Row],[Mercado]]="US WEST",Bitacora_2[[#This Row],[Mercado]]="US EAST",Bitacora_2[[#This Row],[Mercado]]="US SOUTH"),COUNTA(Bitacora_2[[#This Row],[PHYTO]:[ISF]],Bitacora_2[[#This Row],[CO]])=7,Bitacora_2[[#This Row],[Clase Expedición]]="SEA",Bitacora_2[[#This Row],[Exportador]]="ECHF"), "Complete", IF(AND(OR(Bitacora_2[[#This Row],[Mercado]]="US WEST",Bitacora_2[[#This Row],[Mercado]]="US EAST",Bitacora_2[[#This Row],[Mercado]]="US SOUTH"),COUNTA(Bitacora_2[[#This Row],[PHYTO]:[ISF]])=6,Bitacora_2[[#This Row],[Clase Expedición]]="SEA",Bitacora_2[[#This Row],[Exportador]]<>"ECHF"), "Complete", IF(AND(OR(Bitacora_2[[#This Row],[Mercado]]="ASIA",Bitacora_2[[#This Row],[Mercado]]="ASIA CN + HK"),COUNTA(Bitacora_2[[#This Row],[PHYTO]:[PL ]],Bitacora_2[[#This Row],[CO]])=6), "Complete","Incomplete")))))))) -> Complete | AM27: =+IF(OR(Bitacora_2[[#This Row],[Exportador]]="INVERSIONES JORDIE",Bitacora_2[[#This Row],[Exportador]]="TAL S.A."), "Tercero", "Propio") -> Propio | AN27: =IF(AND(Bitacora_2[[#This Row],[Clase Expedición]]="AIR",OR(Bitacora_2[[#This Row],[Mercado]]="US EAST",Bitacora_2[[#This Row],[Mercado]]="US WEST",Bitacora_2[[#This Row],[Mercado]]="US SOUTH")),IF(Bitacora_2[[#This Row],[ETD Doc]]<>"","Delivered","Pending"), IF(Bitacora_2[[#This Row],[Clase Expedición]]="AIR","Delivered", IF(AND(Bitacora_2[[#This Row],[ETD Doc]]="",Bitacora_2[[#This Row],[ATA DOC]]=""),"Pending", IF(AND(Bitacora_2[[#This Row],[ETD Doc]]<>"",Bitacora_2[[#This Row],[ATA DOC]]=""),"In transit", IF(AND(Bitacora_2[[#This Row],[ETD Doc]]<>"",Bitacora_2[[#This Row],[ATA DOC]]<>""),"Delivered",""))))) -> Pending | AQ27: =IF(I27="SEA",IF(AP27="","On Hold","Released"),"")
A28: PO00000050968HFPEARANCONV145-11470664 | B28: 24 | C28: 46181 | D28: 24 | E28: US EAST | F28: JFK | G28: PE | H28: HFPE | I28: AIR | J28: ARAN | K28: CONV | L28: PO00000050968 | M28: 145-11470664 | N28: HORTIFRUT IMPORTS INC. (PHI-BOAT) | O28: NRF TIER I | P28: LATAM | R28: 46184 | S28: 46184 | T28: DHL | U28: =+IF(Bitacora_2[[#This Row],[ATA DOC]]<>"",Bitacora_2[[#This Row],[ATA DOC]], IF(Bitacora_2[[#This Row],[Clase Expedición]]="AIR",Bitacora_2[[#This Row],[ETD Real]], IF(AND(Bitacora_2[[#This Row],[Clase Expedición]]="SEA",Bitacora_2[[#This Row],[Mercado]]="LATAM"), Bitacora_2[[#This Row],[ETD Real]]+3, IF(AND(Bitacora_2[[#This Row],[Clase Expedición]]="SEA",Bitacora_2[[#This Row],[Mercado]]="EUROPE"), Bitacora_2[[#This Row],[ETD Real]]+8, IF(AND(Bitacora_2[[#This Row],[Clase Expedición]]="SEA",Bitacora_2[[#This Row],[Mercado]]="UK"), Bitacora_2[[#This Row],[ETD Real]]+11, IF(AND(Bitacora_2[[#This Row],[Clase Expedición]]="SEA",OR(Bitacora_2[[#This Row],[Mercado]]="ASIA",Bitacora_2[[#This Row],[Mercado]]="ASIA CN + HK")), Bitacora_2[[#This Row],[ETD Real]]+14, IF(AND(Bitacora_2[[#This Row],[Clase Expedición]]="SEA",OR(Bitacora_2[[#This Row],[Mercado]]="US EAST",Bitacora_2[[#This Row],[Mercado]]="US WEST",Bitacora_2[[#This Row],[Mercado]]="US SOUTH")), Bitacora_2[[#This Row],[ETD Real]]+8,""))))))) -> 46184 | X28: =IF(OR(Bitacora_2[[#This Row],[ETD Real]]="",Bitacora_2[[#This Row],[ETD Doc]]=""),"",Bitacora_2[[#This Row],[ETD Doc]]-Bitacora_2[[#This Row],[ETD Real]]) | Y28: =IF(OR(Bitacora_2[[#This Row],[ATA DOC]]="",Bitacora_2[[#This Row],[ETA Real]]=""),"",Bitacora_2[[#This Row],[ETA Real]]-Bitacora_2[[#This Row],[ATA DOC]]) | AI28: =IF(AND(OR(E28="US EAST",E28="US WEST",E28="US SOUTH"),I28="SEA",Bitacora_2[[#This Row],[ETD Real]]-TODAY()>=3,Bitacora_2[[#This Row],[ISF]]<>"X"),"Pending", IF(AND(OR(E28="US EAST",E28="US WEST",E28="US SOUTH"),I28="SEA",Bitacora_2[[#This Row],[ETD Real]]-TODAY()=2,Bitacora_2[[#This Row],[ISF]]<>"X"),"Urgente", IF(AND(OR(E28="US EAST",E28="US WEST",E28="US SOUTH"),I28="SEA",Bitacora_2[[#This Row],[ETD Real]]-TODAY()<=1,Bitacora_2[[#This Row],[ISF]]<>"X"),"Muy Urgente", IF(AND(OR(E28="US EAST",E28="US WEST",E28="US SOUTH"),I28="SEA",Bitacora_2[[#This Row],[ISF]]="X"),"Sent","")))) | AJ28: =IF(AND(OR(Bitacora_2[[#This Row],[Clase Expedición]]="AIR",Bitacora_2[[#This Row],[Clase Expedición]]="TRK")),"Complete", IF(AND(Bitacora_2[[#This Row],[Mercado]]="LATAM",COUNTA(Bitacora_2[[#This Row],[PHYTO]:[ISF]],Bitacora_2[[#This Row],[CO]])=7,Bitacora_2[[#This Row],[Clase Expedición]]<>"TRK"), "Complete", IF(AND(Bitacora_2[[#This Row],[Mercado]]="LATAM",COUNTA(Bitacora_2[[#This Row],[PHYTO]:[PL ]],Bitacora_2[[#This Row],[CO]])=6,Bitacora_2[[#This Row],[Clase Expedición]]="SEA"), "Complete", IF(AND(OR(Bitacora_2[[#This Row],[Mercado]]="EUROPE",Bitacora_2[[#This Row],[Mercado]]="UK"),COUNTA(Bitacora_2[[#This Row],[PHYTO]],Bitacora_2[[#This Row],[INVOICE]:[PL ]],Bitacora_2[[#This Row],[COI]])=5,Bitacora_2[[#This Row],[Clase Expedición]]="SEA",Bitacora_2[[#This Row],[Manejo]]="ORG"), "Complete", IF(AND(OR(Bitacora_2[[#This Row],[Mercado]]="EUROPE",Bitacora_2[[#This Row],[Mercado]]="UK"),COUNTA(Bitacora_2[[#This Row],[PHYTO]],Bitacora_2[[#This Row],[INVOICE]:[PL ]])=4,Bitacora_2[[#This Row],[Clase Expedición]]="SEA",Bitacora_2[[#This Row],[Manejo]]="CONV"), "Complete", IF(AND(OR(Bitacora_2[[#This Row],[Mercado]]="US WEST",Bitacora_2[[#This Row],[Mercado]]="US EAST",Bitacora_2[[#This Row],[Mercado]]="US SOUTH"),COUNTA(Bitacora_2[[#This Row],[PHYTO]:[ISF]],Bitacora_2[[#This Row],[CO]])=7,Bitacora_2[[#This Row],[Clase Expedición]]="SEA",Bitacora_2[[#This Row],[Exportador]]="ECHF"), "Complete", IF(AND(OR(Bitacora_2[[#This Row],[Mercado]]="US WEST",Bitacora_2[[#This Row],[Mercado]]="US EAST",Bitacora_2[[#This Row],[Mercado]]="US SOUTH"),COUNTA(Bitacora_2[[#This Row],[PHYTO]:[ISF]])=6,Bitacora_2[[#This Row],[Clase Expedición]]="SEA",Bitacora_2[[#This Row],[Exportador]]<>"ECHF"), "Complete", IF(AND(OR(Bitacora_2[[#This Row],[Mercado]]="ASIA",Bitacora_2[[#This Row],[Mercado]]="ASIA CN + HK"),COUNTA(Bitacora_2[[#This Row],[PHYTO]:[PL ]],Bitacora_2[[#This Row],[CO]])=6), "Complete","Incomplete")))))))) -> Complete | AM28: =+IF(OR(Bitacora_2[[#This Row],[Exportador]]="INVERSIONES JORDIE",Bitacora_2[[#This Row],[Exportador]]="TAL S.A."), "Tercero", "Propio") -> Propio | AN28: =IF(AND(Bitacora_2[[#This Row],[Clase Expedición]]="AIR",OR(Bitacora_2[[#This Row],[Mercado]]="US EAST",Bitacora_2[[#This Row],[Mercado]]="US WEST",Bitacora_2[[#This Row],[Mercado]]="US SOUTH")),IF(Bitacora_2[[#This Row],[ETD Doc]]<>"","Delivered","Pending"), IF(Bitacora_2[[#This Row],[Clase Expedición]]="AIR","Delivered", IF(AND(Bitacora_2[[#This Row],[ETD Doc]]="",Bitacora_2[[#This Row],[ATA DOC]]=""),"Pending", IF(AND(Bitacora_2[[#This Row],[ETD Doc]]<>"",Bitacora_2[[#This Row],[ATA DOC]]=""),"In transit", IF(AND(Bitacora_2[[#This Row],[ETD Doc]]<>"",Bitacora_2[[#This Row],[ATA DOC]]<>""),"Delivered",""))))) -> Pending | AQ28: =IF(I28="SEA",IF(AP28="","On Hold","Released"),"")
A29: PO00000050969HFPEARANCONV145-11470690 | B29: 24 | C29: 46181 | D29: 24 | E29: US EAST | F29: JFK | G29: PE | H29: HFPE | I29: AIR | J29: ARAN | K29: CONV | L29: PO00000050969 | M29: 145-11470690 | N29: HORTIFRUT IMPORTS INC. (PHI-BOAT) | O29: NRF TIER I | P29: LATAM | R29: 46185 | S29: 46185 | T29: DHL | U29: =+IF(Bitacora_2[[#This Row],[ATA DOC]]<>"",Bitacora_2[[#This Row],[ATA DOC]], IF(Bitacora_2[[#This Row],[Clase Expedición]]="AIR",Bitacora_2[[#This Row],[ETD Real]], IF(AND(Bitacora_2[[#This Row],[Clase Expedición]]="SEA",Bitacora_2[[#This Row],[Mercado]]="LATAM"), Bitacora_2[[#This Row],[ETD Real]]+3, IF(AND(Bitacora_2[[#This Row],[Clase Expedición]]="SEA",Bitacora_2[[#This Row],[Mercado]]="EUROPE"), Bitacora_2[[#This Row],[ETD Real]]+8, IF(AND(Bitacora_2[[#This Row],[Clase Expedición]]="SEA",Bitacora_2[[#This Row],[Mercado]]="UK"), Bitacora_2[[#This Row],[ETD Real]]+11, IF(AND(Bitacora_2[[#This Row],[Clase Expedición]]="SEA",OR(Bitacora_2[[#This Row],[Mercado]]="ASIA",Bitacora_2[[#This Row],[Mercado]]="ASIA CN + HK")), Bitacora_2[[#This Row],[ETD Real]]+14, IF(AND(Bitacora_2[[#This Row],[Clase Expedición]]="SEA",OR(Bitacora_2[[#This Row],[Mercado]]="US EAST",Bitacora_2[[#This Row],[Mercado]]="US WEST",Bitacora_2[[#This Row],[Mercado]]="US SOUTH")), Bitacora_2[[#This Row],[ETD Real]]+8,""))))))) -> 46185 | X29: =IF(OR(Bitacora_2[[#This Row],[ETD Real]]="",Bitacora_2[[#This Row],[ETD Doc]]=""),"",Bitacora_2[[#This Row],[ETD Doc]]-Bitacora_2[[#This Row],[ETD Real]]) | Y29: =IF(OR(Bitacora_2[[#This Row],[ATA DOC]]="",Bitacora_2[[#This Row],[ETA Real]]=""),"",Bitacora_2[[#This Row],[ETA Real]]-Bitacora_2[[#This Row],[ATA DOC]]) | AI29: =IF(AND(OR(E29="US EAST",E29="US WEST",E29="US SOUTH"),I29="SEA",Bitacora_2[[#This Row],[ETD Real]]-TODAY()>=3,Bitacora_2[[#This Row],[ISF]]<>"X"),"Pending", IF(AND(OR(E29="US EAST",E29="US WEST",E29="US SOUTH"),I29="SEA",Bitacora_2[[#This Row],[ETD Real]]-TODAY()=2,Bitacora_2[[#This Row],[ISF]]<>"X"),"Urgente", IF(AND(OR(E29="US EAST",E29="US WEST",E29="US SOUTH"),I29="SEA",Bitacora_2[[#This Row],[ETD Real]]-TODAY()<=1,Bitacora_2[[#This Row],[ISF]]<>"X"),"Muy Urgente", IF(AND(OR(E29="US EAST",E29="US WEST",E29="US SOUTH"),I29="SEA",Bitacora_2[[#This Row],[ISF]]="X"),"Sent","")))) | AJ29: =IF(AND(OR(Bitacora_2[[#This Row],[Clase Expedición]]="AIR",Bitacora_2[[#This Row],[Clase Expedición]]="TRK")),"Complete", IF(AND(Bitacora_2[[#This Row],[Mercado]]="LATAM",COUNTA(Bitacora_2[[#This Row],[PHYTO]:[ISF]],Bitacora_2[[#This Row],[CO]])=7,Bitacora_2[[#This Row],[Clase Expedición]]<>"TRK"), "Complete", IF(AND(Bitacora_2[[#This Row],[Mercado]]="LATAM",COUNTA(Bitacora_2[[#This Row],[PHYTO]:[PL ]],Bitacora_2[[#This Row],[CO]])=6,Bitacora_2[[#This Row],[Clase Expedición]]="SEA"), "Complete", IF(AND(OR(Bitacora_2[[#This Row],[Mercado]]="EUROPE",Bitacora_2[[#This Row],[Mercado]]="UK"),COUNTA(Bitacora_2[[#This Row],[PHYTO]],Bitacora_2[[#This Row],[INVOICE]:[PL ]],Bitacora_2[[#This Row],[COI]])=5,Bitacora_2[[#This Row],[Clase Expedición]]="SEA",Bitacora_2[[#This Row],[Manejo]]="ORG"), "Complete", IF(AND(OR(Bitacora_2[[#This Row],[Mercado]]="EUROPE",Bitacora_2[[#This Row],[Mercado]]="UK"),COUNTA(Bitacora_2[[#This Row],[PHYTO]],Bitacora_2[[#This Row],[INVOICE]:[PL ]])=4,Bitacora_2[[#This Row],[Clase Expedición]]="SEA",Bitacora_2[[#This Row],[Manejo]]="CONV"), "Complete", IF(AND(OR(Bitacora_2[[#This Row],[Mercado]]="US WEST",Bitacora_2[[#This Row],[Mercado]]="US EAST",Bitacora_2[[#This Row],[Mercado]]="US SOUTH"),COUNTA(Bitacora_2[[#This Row],[PHYTO]:[ISF]],Bitacora_2[[#This Row],[CO]])=7,Bitacora_2[[#This Row],[Clase Expedición]]="SEA",Bitacora_2[[#This Row],[Exportador]]="ECHF"), "Complete", IF(AND(OR(Bitacora_2[[#This Row],[Mercado]]="US WEST",Bitacora_2[[#This Row],[Mercado]]="US EAST",Bitacora_2[[#This Row],[Mercado]]="US SOUTH"),COUNTA(Bitacora_2[[#This Row],[PHYTO]:[ISF]])=6,Bitacora_2[[#This Row],[Clase Expedición]]="SEA",Bitacora_2[[#This Row],[Exportador]]<>"ECHF"), "Complete", IF(AND(OR(Bitacora_2[[#This Row],[Mercado]]="ASIA",Bitacora_2[[#This Row],[Mercado]]="ASIA CN + HK"),COUNTA(Bitacora_2[[#This Row],[PHYTO]:[PL ]],Bitacora_2[[#This Row],[CO]])=6), "Complete","Incomplete")))))))) -> Complete | AM29: =+IF(OR(Bitacora_2[[#This Row],[Exportador]]="INVERSIONES JORDIE",Bitacora_2[[#This Row],[Exportador]]="TAL S.A."), "Tercero", "Propio") -> Propio | AN29: =IF(AND(Bitacora_2[[#This Row],[Clase Expedición]]="AIR",OR(Bitacora_2[[#This Row],[Mercado]]="US EAST",Bitacora_2[[#This Row],[Mercado]]="US WEST",Bitacora_2[[#This Row],[Mercado]]="US SOUTH")),IF(Bitacora_2[[#This Row],[ETD Doc]]<>"","Delivered","Pending"), IF(Bitacora_2[[#This Row],[Clase Expedición]]="AIR","Delivered", IF(AND(Bitacora_2[[#This Row],[ETD Doc]]="",Bitacora_2[[#This Row],[ATA DOC]]=""),"Pending", IF(AND(Bitacora_2[[#This Row],[ETD Doc]]<>"",Bitacora_2[[#This Row],[ATA DOC]]=""),"In transit", IF(AND(Bitacora_2[[#This Row],[ETD Doc]]<>"",Bitacora_2[[#This Row],[ATA DOC]]<>""),"Delivered",""))))) -> Pending | AQ29: =IF(I29="SEA",IF(AP29="","On Hold","Released"),"")
A30: PO00000050972HFPEARANCONVEGSU5056740 | B30: 24 | C30: 46181 | D30: 29 | E30: ASIA CN + HK | F30: CNSZX | G30: PE | H30: HFPE | I30: SEA | J30: ARAN | K30: CONV | L30: PO00000050972 | M30: EGSU5056740 | N30: FRESH GO LIMITED | O30: JOY WING MAU | P30: EVERGREEN | Q30: EVER LUCKY 083W | R30: 46184 | S30: 46220 | T30: NWT | U30: =+IF(Bitacora_2[[#This Row],[ATA DOC]]<>"",Bitacora_2[[#This Row],[ATA DOC]], IF(Bitacora_2[[#This Row],[Clase Expedición]]="AIR",Bitacora_2[[#This Row],[ETD Real]], IF(AND(Bitacora_2[[#This Row],[Clase Expedición]]="SEA",Bitacora_2[[#This Row],[Mercado]]="LATAM"), Bitacora_2[[#This Row],[ETD Real]]+3, IF(AND(Bitacora_2[[#This Row],[Clase Expedición]]="SEA",Bitacora_2[[#This Row],[Mercado]]="EUROPE"), Bitacora_2[[#This Row],[ETD Real]]+8, IF(AND(Bitacora_2[[#This Row],[Clase Expedición]]="SEA",Bitacora_2[[#This Row],[Mercado]]="UK"), Bitacora_2[[#This Row],[ETD Real]]+11, IF(AND(Bitacora_2[[#This Row],[Clase Expedición]]="SEA",OR(Bitacora_2[[#This Row],[Mercado]]="ASIA",Bitacora_2[[#This Row],[Mercado]]="ASIA CN + HK")), Bitacora_2[[#This Row],[ETD Real]]+14, IF(AND(Bitacora_2[[#This Row],[Clase Expedición]]="SEA",OR(Bitacora_2[[#This Row],[Mercado]]="US EAST",Bitacora_2[[#This Row],[Mercado]]="US WEST",Bitacora_2[[#This Row],[Mercado]]="US SOUTH")), Bitacora_2[[#This Row],[ETD Real]]+8,""))))))) -> 46204 | V30: 46197 | W30: 46204 | X30: =IF(OR(Bitacora_2[[#This Row],[ETD Real]]="",Bitacora_2[[#This Row],[ETD Doc]]=""),"",Bitacora_2[[#This Row],[ETD Doc]]-Bitacora_2[[#This Row],[ETD Real]]) -> 13 | Y30: =IF(OR(Bitacora_2[[#This Row],[ATA DOC]]="",Bitacora_2[[#This Row],[ETA Real]]=""),"",Bitacora_2[[#This Row],[ETA Real]]-Bitacora_2[[#This Row],[ATA DOC]]) -> 16 | Z30: 5238849313 | AA30: X | AB30: X | AC30: X | AD30: X | AE30: X | AH30: x | AI30: =IF(AND(OR(E30="US EAST",E30="US WEST",E30="US SOUTH"),I30="SEA",Bitacora_2[[#This Row],[ETD Real]]-TODAY()>=3,Bitacora_2[[#This Row],[ISF]]<>"X"),"Pending", IF(AND(OR(E30="US EAST",E30="US WEST",E30="US SOUTH"),I30="SEA",Bitacora_2[[#This Row],[ETD Real]]-TODAY()=2,Bitacora_2[[#This Row],[ISF]]<>"X"),"Urgente", IF(AND(OR(E30="US EAST",E30="US WEST",E30="US SOUTH"),I30="SEA",Bitacora_2[[#This Row],[ETD Real]]-TODAY()<=1,Bitacora_2[[#This Row],[ISF]]<>"X"),"Muy Urgente", IF(AND(OR(E30="US EAST",E30="US WEST",E30="US SOUTH"),I30="SEA",Bitacora_2[[#This Row],[ISF]]="X"),"Sent","")))) | AJ30: =IF(AND(OR(Bitacora_2[[#This Row],[Clase Expedición]]="AIR",Bitacora_2[[#This Row],[Clase Expedición]]="TRK")),"Complete", IF(AND(Bitacora_2[[#This Row],[Mercado]]="LATAM",COUNTA(Bitacora_2[[#This Row],[PHYTO]:[ISF]],Bitacora_2[[#This Row],[CO]])=7,Bitacora_2[[#This Row],[Clase Expedición]]<>"TRK"), "Complete", IF(AND(Bitacora_2[[#This Row],[Mercado]]="LATAM",COUNTA(Bitacora_2[[#This Row],[PHYTO]:[PL ]],Bitacora_2[[#This Row],[CO]])=6,Bitacora_2[[#This Row],[Clase Expedición]]="SEA"), "Complete", IF(AND(OR(Bitacora_2[[#This Row],[Mercado]]="EUROPE",Bitacora_2[[#This Row],[Mercado]]="UK"),COUNTA(Bitacora_2[[#This Row],[PHYTO]],Bitacora_2[[#This Row],[INVOICE]:[PL ]],Bitacora_2[[#This Row],[COI]])=5,Bitacora_2[[#This Row],[Clase Expedición]]="SEA",Bitacora_2[[#This Row],[Manejo]]="ORG"), "Complete", IF(AND(OR(Bitacora_2[[#This Row],[Mercado]]="EUROPE",Bitacora_2[[#This Row],[Mercado]]="UK"),COUNTA(Bitacora_2[[#This Row],[PHYTO]],Bitacora_2[[#This Row],[INVOICE]:[PL ]])=4,Bitacora_2[[#This Row],[Clase Expedición]]="SEA",Bitacora_2[[#This Row],[Manejo]]="CONV"), "Complete", IF(AND(OR(Bitacora_2[[#This Row],[Mercado]]="US WEST",Bitacora_2[[#This Row],[Mercado]]="US EAST",Bitacora_2[[#This Row],[Mercado]]="US SOUTH"),COUNTA(Bitacora_2[[#This Row],[PHYTO]:[ISF]],Bitacora_2[[#This Row],[CO]])=7,Bitacora_2[[#This Row],[Clase Expedición]]="SEA",Bitacora_2[[#This Row],[Exportador]]="ECHF"), "Complete", IF(AND(OR(Bitacora_2[[#This Row],[Mercado]]="US WEST",Bitacora_2[[#This Row],[Mercado]]="US EAST",Bitacora_2[[#This Row],[Mercado]]="US SOUTH"),COUNTA(Bitacora_2[[#This Row],[PHYTO]:[ISF]])=6,Bitacora_2[[#This Row],[Clase Expedición]]="SEA",Bitacora_2[[#This Row],[Exportador]]<>"ECHF"), "Complete", IF(AND(OR(Bitacora_2[[#This Row],[Mercado]]="ASIA",Bitacora_2[[#This Row],[Mercado]]="ASIA CN + HK"),COUNTA(Bitacora_2[[#This Row],[PHYTO]:[PL ]],Bitacora_2[[#This Row],[CO]])=6), "Complete","Incomplete")))))))) -> Complete | AM30: =+IF(OR(Bitacora_2[[#This Row],[Exportador]]="INVERSIONES JORDIE",Bitacora_2[[#This Row],[Exportador]]="TAL S.A."), "Tercero", "Propio") -> Propio | AN30: =IF(AND(Bitacora_2[[#This Row],[Clase Expedición]]="AIR",OR(Bitacora_2[[#This Row],[Mercado]]="US EAST",Bitacora_2[[#This Row],[Mercado]]="US WEST",Bitacora_2[[#This Row],[Mercado]]="US SOUTH")),IF(Bitacora_2[[#This Row],[ETD Doc]]<>"","Delivered","Pending"), IF(Bitacora_2[[#This Row],[Clase Expedición]]="AIR","Delivered", IF(AND(Bitacora_2[[#This Row],[ETD Doc]]="",Bitacora_2[[#This Row],[ATA DOC]]=""),"Pending", IF(AND(Bitacora_2[[#This Row],[ETD Doc]]<>"",Bitacora_2[[#This Row],[ATA DOC]]=""),"In transit", IF(AND(Bitacora_2[[#This Row],[ETD Doc]]<>"",Bitacora_2[[#This Row],[ATA DOC]]<>""),"Delivered",""))))) -> Delivered | AO30: Released | AP30: 46211 | AQ30: =IF(I30="SEA",IF(AP30="","On Hold","Released"),"") -> Released
A31: PO00000050973HFPEARANCONVEMCU5680947 | B31: 24 | C31: 46181 | D31: 29 | E31: ASIA CN + HK | F31: CNSZX | G31: PE | H31: HFPE | I31: SEA | J31: ARAN | K31: CONV | L31: PO00000050973 | M31: EMCU5680947 | N31: FRESH GO LIMITED | O31: JOY WING MAU | P31: EVERGREEN | Q31: EVER LUCKY 083W | R31: 46184 | S31: 46220 | T31: NWT | U31: =+IF(Bitacora_2[[#This Row],[ATA DOC]]<>"",Bitacora_2[[#This Row],[ATA DOC]], IF(Bitacora_2[[#This Row],[Clase Expedición]]="AIR",Bitacora_2[[#This Row],[ETD Real]], IF(AND(Bitacora_2[[#This Row],[Clase Expedición]]="SEA",Bitacora_2[[#This Row],[Mercado]]="LATAM"), Bitacora_2[[#This Row],[ETD Real]]+3, IF(AND(Bitacora_2[[#This Row],[Clase Expedición]]="SEA",Bitacora_2[[#This Row],[Mercado]]="EUROPE"), Bitacora_2[[#This Row],[ETD Real]]+8, IF(AND(Bitacora_2[[#This Row],[Clase Expedición]]="SEA",Bitacora_2[[#This Row],[Mercado]]="UK"), Bitacora_2[[#This Row],[ETD Real]]+11, IF(AND(Bitacora_2[[#This Row],[Clase Expedición]]="SEA",OR(Bitacora_2[[#This Row],[Mercado]]="ASIA",Bitacora_2[[#This Row],[Mercado]]="ASIA CN + HK")), Bitacora_2[[#This Row],[ETD Real]]+14, IF(AND(Bitacora_2[[#This Row],[Clase Expedición]]="SEA",OR(Bitacora_2[[#This Row],[Mercado]]="US EAST",Bitacora_2[[#This Row],[Mercado]]="US WEST",Bitacora_2[[#This Row],[Mercado]]="US SOUTH")), Bitacora_2[[#This Row],[ETD Real]]+8,""))))))) -> 46204 | V31: 46197 | W31: 46204 | X31: =IF(OR(Bitacora_2[[#This Row],[ETD Real]]="",Bitacora_2[[#This Row],[ETD Doc]]=""),"",Bitacora_2[[#This Row],[ETD Doc]]-Bitacora_2[[#This Row],[ETD Real]]) -> 13 | Y31: =IF(OR(Bitacora_2[[#This Row],[ATA DOC]]="",Bitacora_2[[#This Row],[ETA Real]]=""),"",Bitacora_2[[#This Row],[ETA Real]]-Bitacora_2[[#This Row],[ATA DOC]]) -> 16 | Z31: 5238849313 | AA31: X | AB31: X | AC31: X | AD31: X | AE31: X | AH31: x | AI31: =IF(AND(OR(E31="US EAST",E31="US WEST",E31="US SOUTH"),I31="SEA",Bitacora_2[[#This Row],[ETD Real]]-TODAY()>=3,Bitacora_2[[#This Row],[ISF]]<>"X"),"Pending", IF(AND(OR(E31="US EAST",E31="US WEST",E31="US SOUTH"),I31="SEA",Bitacora_2[[#This Row],[ETD Real]]-TODAY()=2,Bitacora_2[[#This Row],[ISF]]<>"X"),"Urgente", IF(AND(OR(E31="US EAST",E31="US WEST",E31="US SOUTH"),I31="SEA",Bitacora_2[[#This Row],[ETD Real]]-TODAY()<=1,Bitacora_2[[#This Row],[ISF]]<>"X"),"Muy Urgente", IF(AND(OR(E31="US EAST",E31="US WEST",E31="US SOUTH"),I31="SEA",Bitacora_2[[#This Row],[ISF]]="X"),"Sent","")))) | AJ31: =IF(AND(OR(Bitacora_2[[#This Row],[Clase Expedición]]="AIR",Bitacora_2[[#This Row],[Clase Expedición]]="TRK")),"Complete", IF(AND(Bitacora_2[[#This Row],[Mercado]]="LATAM",COUNTA(Bitacora_2[[#This Row],[PHYTO]:[ISF]],Bitacora_2[[#This Row],[CO]])=7,Bitacora_2[[#This Row],[Clase Expedición]]<>"TRK"), "Complete", IF(AND(Bitacora_2[[#This Row],[Mercado]]="LATAM",COUNTA(Bitacora_2[[#This Row],[PHYTO]:[PL ]],Bitacora_2[[#This Row],[CO]])=6,Bitacora_2[[#This Row],[Clase Expedición]]="SEA"), "Complete", IF(AND(OR(Bitacora_2[[#This Row],[Mercado]]="EUROPE",Bitacora_2[[#This Row],[Mercado]]="UK"),COUNTA(Bitacora_2[[#This Row],[PHYTO]],Bitacora_2[[#This Row],[INVOICE]:[PL ]],Bitacora_2[[#This Row],[COI]])=5,Bitacora_2[[#This Row],[Clase Expedición]]="SEA",Bitacora_2[[#This Row],[Manejo]]="ORG"), "Complete", IF(AND(OR(Bitacora_2[[#This Row],[Mercado]]="EUROPE",Bitacora_2[[#This Row],[Mercado]]="UK"),COUNTA(Bitacora_2[[#This Row],[PHYTO]],Bitacora_2[[#This Row],[INVOICE]:[PL ]])=4,Bitacora_2[[#This Row],[Clase Expedición]]="SEA",Bitacora_2[[#This Row],[Manejo]]="CONV"), "Complete", IF(AND(OR(Bitacora_2[[#This Row],[Mercado]]="US WEST",Bitacora_2[[#This Row],[Mercado]]="US EAST",Bitacora_2[[#This Row],[Mercado]]="US SOUTH"),COUNTA(Bitacora_2[[#This Row],[PHYTO]:[ISF]],Bitacora_2[[#This Row],[CO]])=7,Bitacora_2[[#This Row],[Clase Expedición]]="SEA",Bitacora_2[[#This Row],[Exportador]]="ECHF"), "Complete", IF(AND(OR(Bitacora_2[[#This Row],[Mercado]]="US WEST",Bitacora_2[[#This Row],[Mercado]]="US EAST",Bitacora_2[[#This Row],[Mercado]]="US SOUTH"),COUNTA(Bitacora_2[[#This Row],[PHYTO]:[ISF]])=6,Bitacora_2[[#This Row],[Clase Expedición]]="SEA",Bitacora_2[[#This Row],[Exportador]]<>"ECHF"), "Complete", IF(AND(OR(Bitacora_2[[#This Row],[Mercado]]="ASIA",Bitacora_2[[#This Row],[Mercado]]="ASIA CN + HK"),COUNTA(Bitacora_2[[#This Row],[PHYTO]:[PL ]],Bitacora_2[[#This Row],[CO]])=6), "Complete","Incomplete")))))))) -> Complete | AM31: =+IF(OR(Bitacora_2[[#This Row],[Exportador]]="INVERSIONES JORDIE",Bitacora_2[[#This Row],[Exportador]]="TAL S.A."), "Tercero", "Propio") -> Propio | AN31: =IF(AND(Bitacora_2[[#This Row],[Clase Expedición]]="AIR",OR(Bitacora_2[[#This Row],[Mercado]]="US EAST",Bitacora_2[[#This Row],[Mercado]]="US WEST",Bitacora_2[[#This Row],[Mercado]]="US SOUTH")),IF(Bitacora_2[[#This Row],[ETD Doc]]<>"","Delivered","Pending"), IF(Bitacora_2[[#This Row],[Clase Expedición]]="AIR","Delivered", IF(AND(Bitacora_2[[#This Row],[ETD Doc]]="",Bitacora_2[[#This Row],[ATA DOC]]=""),"Pending", IF(AND(Bitacora_2[[#This Row],[ETD Doc]]<>"",Bitacora_2[[#This Row],[ATA DOC]]=""),"In transit", IF(AND(Bitacora_2[[#This Row],[ETD Doc]]<>"",Bitacora_2[[#This Row],[ATA DOC]]<>""),"Delivered",""))))) -> Delivered | AO31: Released | AP31: 46211 | AQ31: =IF(I31="SEA",IF(AP31="","On Hold","Released"),"") -> Released
A32: PO00000050974HFPEARANCONVEMCU5520825 | B32: 24 | C32: 46181 | D32: 29 | E32: ASIA CN + HK | F32: CNSZX | G32: PE | H32: HFPE | I32: SEA | J32: ARAN | K32: CONV | L32: PO00000050974 | M32: EMCU5520825 | N32: FRESH GO LIMITED | O32: JOY WING MAU | P32: EVERGREEN | Q32: EVER LUCKY 083W | R32: 46184 | S32: 46220 | T32: NWT | U32: =+IF(Bitacora_2[[#This Row],[ATA DOC]]<>"",Bitacora_2[[#This Row],[ATA DOC]], IF(Bitacora_2[[#This Row],[Clase Expedición]]="AIR",Bitacora_2[[#This Row],[ETD Real]], IF(AND(Bitacora_2[[#This Row],[Clase Expedición]]="SEA",Bitacora_2[[#This Row],[Mercado]]="LATAM"), Bitacora_2[[#This Row],[ETD Real]]+3, IF(AND(Bitacora_2[[#This Row],[Clase Expedición]]="SEA",Bitacora_2[[#This Row],[Mercado]]="EUROPE"), Bitacora_2[[#This Row],[ETD Real]]+8, IF(AND(Bitacora_2[[#This Row],[Clase Expedición]]="SEA",Bitacora_2[[#This Row],[Mercado]]="UK"), Bitacora_2[[#This Row],[ETD Real]]+11, IF(AND(Bitacora_2[[#This Row],[Clase Expedición]]="SEA",OR(Bitacora_2[[#This Row],[Mercado]]="ASIA",Bitacora_2[[#This Row],[Mercado]]="ASIA CN + HK")), Bitacora_2[[#This Row],[ETD Real]]+14, IF(AND(Bitacora_2[[#This Row],[Clase Expedición]]="SEA",OR(Bitacora_2[[#This Row],[Mercado]]="US EAST",Bitacora_2[[#This Row],[Mercado]]="US WEST",Bitacora_2[[#This Row],[Mercado]]="US SOUTH")), Bitacora_2[[#This Row],[ETD Real]]+8,""))))))) -> 46204 | V32: 46197 | W32: 46204 | X32: =IF(OR(Bitacora_2[[#This Row],[ETD Real]]="",Bitacora_2[[#This Row],[ETD Doc]]=""),"",Bitacora_2[[#This Row],[ETD Doc]]-Bitacora_2[[#This Row],[ETD Real]]) -> 13 | Y32: =IF(OR(Bitacora_2[[#This Row],[ATA DOC]]="",Bitacora_2[[#This Row],[ETA Real]]=""),"",Bitacora_2[[#This Row],[ETA Real]]-Bitacora_2[[#This Row],[ATA DOC]]) -> 16 | Z32: 5238849313 | AA32: X | AB32: X | AC32: X | AD32: X | AE32: X | AH32: x | AI32: =IF(AND(OR(E32="US EAST",E32="US WEST",E32="US SOUTH"),I32="SEA",Bitacora_2[[#This Row],[ETD Real]]-TODAY()>=3,Bitacora_2[[#This Row],[ISF]]<>"X"),"Pending", IF(AND(OR(E32="US EAST",E32="US WEST",E32="US SOUTH"),I32="SEA",Bitacora_2[[#This Row],[ETD Real]]-TODAY()=2,Bitacora_2[[#This Row],[ISF]]<>"X"),"Urgente", IF(AND(OR(E32="US EAST",E32="US WEST",E32="US SOUTH"),I32="SEA",Bitacora_2[[#This Row],[ETD Real]]-TODAY()<=1,Bitacora_2[[#This Row],[ISF]]<>"X"),"Muy Urgente", IF(AND(OR(E32="US EAST",E32="US WEST",E32="US SOUTH"),I32="SEA",Bitacora_2[[#This Row],[ISF]]="X"),"Sent","")))) | AJ32: =IF(AND(OR(Bitacora_2[[#This Row],[Clase Expedición]]="AIR",Bitacora_2[[#This Row],[Clase Expedición]]="TRK")),"Complete", IF(AND(Bitacora_2[[#This Row],[Mercado]]="LATAM",COUNTA(Bitacora_2[[#This Row],[PHYTO]:[ISF]],Bitacora_2[[#This Row],[CO]])=7,Bitacora_2[[#This Row],[Clase Expedición]]<>"TRK"), "Complete", IF(AND(Bitacora_2[[#This Row],[Mercado]]="LATAM",COUNTA(Bitacora_2[[#This Row],[PHYTO]:[PL ]],Bitacora_2[[#This Row],[CO]])=6,Bitacora_2[[#This Row],[Clase Expedición]]="SEA"), "Complete", IF(AND(OR(Bitacora_2[[#This Row],[Mercado]]="EUROPE",Bitacora_2[[#This Row],[Mercado]]="UK"),COUNTA(Bitacora_2[[#This Row],[PHYTO]],Bitacora_2[[#This Row],[INVOICE]:[PL ]],Bitacora_2[[#This Row],[COI]])=5,Bitacora_2[[#This Row],[Clase Expedición]]="SEA",Bitacora_2[[#This Row],[Manejo]]="ORG"), "Complete", IF(AND(OR(Bitacora_2[[#This Row],[Mercado]]="EUROPE",Bitacora_2[[#This Row],[Mercado]]="UK"),COUNTA(Bitacora_2[[#This Row],[PHYTO]],Bitacora_2[[#This Row],[INVOICE]:[PL ]])=4,Bitacora_2[[#This Row],[Clase Expedición]]="SEA",Bitacora_2[[#This Row],[Manejo]]="CONV"), "Complete", IF(AND(OR(Bitacora_2[[#This Row],[Mercado]]="US WEST",Bitacora_2[[#This Row],[Mercado]]="US EAST",Bitacora_2[[#This Row],[Mercado]]="US SOUTH"),COUNTA(Bitacora_2[[#This Row],[PHYTO]:[ISF]],Bitacora_2[[#This Row],[CO]])=7,Bitacora_2[[#This Row],[Clase Expedición]]="SEA",Bitacora_2[[#This Row],[Exportador]]="ECHF"), "Complete", IF(AND(OR(Bitacora_2[[#This Row],[Mercado]]="US WEST",Bitacora_2[[#This Row],[Mercado]]="US EAST",Bitacora_2[[#This Row],[Mercado]]="US SOUTH"),COUNTA(Bitacora_2[[#This Row],[PHYTO]:[ISF]])=6,Bitacora_2[[#This Row],[Clase Expedición]]="SEA",Bitacora_2[[#This Row],[Exportador]]<>"ECHF"), "Complete", IF(AND(OR(Bitacora_2[[#This Row],[Mercado]]="ASIA",Bitacora_2[[#This Row],[Mercado]]="ASIA CN + HK"),COUNTA(Bitacora_2[[#This Row],[PHYTO]:[PL ]],Bitacora_2[[#This Row],[CO]])=6), "Complete","Incomplete")))))))) -> Complete | AM32: =+IF(OR(Bitacora_2[[#This Row],[Exportador]]="INVERSIONES JORDIE",Bitacora_2[[#This Row],[Exportador]]="TAL S.A."), "Tercero", "Propio") -> Propio | AN32: =IF(AND(Bitacora_2[[#This Row],[Clase Expedición]]="AIR",OR(Bitacora_2[[#This Row],[Mercado]]="US EAST",Bitacora_2[[#This Row],[Mercado]]="US WEST",Bitacora_2[[#This Row],[Mercado]]="US SOUTH")),IF(Bitacora_2[[#This Row],[ETD Doc]]<>"","Delivered","Pending"), IF(Bitacora_2[[#This Row],[Clase Expedición]]="AIR","Delivered", IF(AND(Bitacora_2[[#This Row],[ETD Doc]]="",Bitacora_2[[#This Row],[ATA DOC]]=""),"Pending", IF(AND(Bitacora_2[[#This Row],[ETD Doc]]<>"",Bitacora_2[[#This Row],[ATA DOC]]=""),"In transit", IF(AND(Bitacora_2[[#This Row],[ETD Doc]]<>"",Bitacora_2[[#This Row],[ATA DOC]]<>""),"Delivered",""))))) -> Delivered | AO32: Released | AP32: 46211 | AQ32: =IF(I32="SEA",IF(AP32="","On Hold","Released"),"") -> Released
A33: PO00000050985HFPEARANCONVSEKU9424169 | B33: 24 | C33: 46182 | D33: 26 | E33: US EAST | F33: USPHL | G33: PE | H33: HFPE | I33: SEA | J33: ARAN | K33: CONV | L33: PO00000050985 | M33: SEKU9424169 | N33: HORTIFRUT IMPORTS INC. (PHI-BOAT) | O33: NRF TIER I | P33: CITIKOLD | Q33: SEABOARD VOYAGER 27 | R33: 46184 | S33: 46194 | T33: NWT | U33: =+IF(Bitacora_2[[#This Row],[ATA DOC]]<>"",Bitacora_2[[#This Row],[ATA DOC]], IF(Bitacora_2[[#This Row],[Clase Expedición]]="AIR",Bitacora_2[[#This Row],[ETD Real]], IF(AND(Bitacora_2[[#This Row],[Clase Expedición]]="SEA",Bitacora_2[[#This Row],[Mercado]]="LATAM"), Bitacora_2[[#This Row],[ETD Real]]+3, IF(AND(Bitacora_2[[#This Row],[Clase Expedición]]="SEA",Bitacora_2[[#This Row],[Mercado]]="EUROPE"), Bitacora_2[[#This Row],[ETD Real]]+8, IF(AND(Bitacora_2[[#This Row],[Clase Expedición]]="SEA",Bitacora_2[[#This Row],[Mercado]]="UK"), Bitacora_2[[#This Row],[ETD Real]]+11, IF(AND(Bitacora_2[[#This Row],[Clase Expedición]]="SEA",OR(Bitacora_2[[#This Row],[Mercado]]="ASIA",Bitacora_2[[#This Row],[Mercado]]="ASIA CN + HK")), Bitacora_2[[#This Row],[ETD Real]]+14, IF(AND(Bitacora_2[[#This Row],[Clase Expedición]]="SEA",OR(Bitacora_2[[#This Row],[Mercado]]="US EAST",Bitacora_2[[#This Row],[Mercado]]="US WEST",Bitacora_2[[#This Row],[Mercado]]="US SOUTH")), Bitacora_2[[#This Row],[ETD Real]]+8,""))))))) -> 46185 | V33: 46185 | W33: 46185 | X33: =IF(OR(Bitacora_2[[#This Row],[ETD Real]]="",Bitacora_2[[#This Row],[ETD Doc]]=""),"",Bitacora_2[[#This Row],[ETD Doc]]-Bitacora_2[[#This Row],[ETD Real]]) -> 1 | Y33: =IF(OR(Bitacora_2[[#This Row],[ATA DOC]]="",Bitacora_2[[#This Row],[ETA Real]]=""),"",Bitacora_2[[#This Row],[ETA Real]]-Bitacora_2[[#This Row],[ATA DOC]]) -> 9 | Z33: - | AA33: X | AB33: X | AC33: X | AD33: X | AE33: X | AF33: x | AI33: =IF(AND(OR(E33="US EAST",E33="US WEST",E33="US SOUTH"),I33="SEA",Bitacora_2[[#This Row],[ETD Real]]-TODAY()>=3,Bitacora_2[[#This Row],[ISF]]<>"X"),"Pending", IF(AND(OR(E33="US EAST",E33="US WEST",E33="US SOUTH"),I33="SEA",Bitacora_2[[#This Row],[ETD Real]]-TODAY()=2,Bitacora_2[[#This Row],[ISF]]<>"X"),"Urgente", IF(AND(OR(E33="US EAST",E33="US WEST",E33="US SOUTH"),I33="SEA",Bitacora_2[[#This Row],[ETD Real]]-TODAY()<=1,Bitacora_2[[#This Row],[ISF]]<>"X"),"Muy Urgente", IF(AND(OR(E33="US EAST",E33="US WEST",E33="US SOUTH"),I33="SEA",Bitacora_2[[#This Row],[ISF]]="X"),"Sent","")))) -> Sent | AJ33: =IF(AND(OR(Bitacora_2[[#This Row],[Clase Expedición]]="AIR",Bitacora_2[[#This Row],[Clase Expedición]]="TRK")),"Complete", IF(AND(Bitacora_2[[#This Row],[Mercado]]="LATAM",COUNTA(Bitacora_2[[#This Row],[PHYTO]:[ISF]],Bitacora_2[[#This Row],[CO]])=7,Bitacora_2[[#This Row],[Clase Expedición]]<>"TRK"), "Complete", IF(AND(Bitacora_2[[#This Row],[Mercado]]="LATAM",COUNTA(Bitacora_2[[#This Row],[PHYTO]:[PL ]],Bitacora_2[[#This Row],[CO]])=6,Bitacora_2[[#This Row],[Clase Expedición]]="SEA"), "Complete", IF(AND(OR(Bitacora_2[[#This Row],[Mercado]]="EUROPE",Bitacora_2[[#This Row],[Mercado]]="UK"),COUNTA(Bitacora_2[[#This Row],[PHYTO]],Bitacora_2[[#This Row],[INVOICE]:[PL ]],Bitacora_2[[#This Row],[COI]])=5,Bitacora_2[[#This Row],[Clase Expedición]]="SEA",Bitacora_2[[#This Row],[Manejo]]="ORG"), "Complete", IF(AND(OR(Bitacora_2[[#This Row],[Mercado]]="EUROPE",Bitacora_2[[#This Row],[Mercado]]="UK"),COUNTA(Bitacora_2[[#This Row],[PHYTO]],Bitacora_2[[#This Row],[INVOICE]:[PL ]])=4,Bitacora_2[[#This Row],[Clase Expedición]]="SEA",Bitacora_2[[#This Row],[Manejo]]="CONV"), "Complete", IF(AND(OR(Bitacora_2[[#This Row],[Mercado]]="US WEST",Bitacora_2[[#This Row],[Mercado]]="US EAST",Bitacora_2[[#This Row],[Mercado]]="US SOUTH"),COUNTA(Bitacora_2[[#This Row],[PHYTO]:[ISF]],Bitacora_2[[#This Row],[CO]])=7,Bitacora_2[[#This Row],[Clase Expedición]]="SEA",Bitacora_2[[#This Row],[Exportador]]="ECHF"), "Complete", IF(AND(OR(Bitacora_2[[#This Row],[Mercado]]="US WEST",Bitacora_2[[#This Row],[Mercado]]="US EAST",Bitacora_2[[#This Row],[Mercado]]="US SOUTH"),COUNTA(Bitacora_2[[#This Row],[PHYTO]:[ISF]])=6,Bitacora_2[[#This Row],[Clase Expedición]]="SEA",Bitacora_2[[#This Row],[Exportador]]<>"ECHF"), "Complete", IF(AND(OR(Bitacora_2[[#This Row],[Mercado]]="ASIA",Bitacora_2[[#This Row],[Mercado]]="ASIA CN + HK"),COUNTA(Bitacora_2[[#This Row],[PHYTO]:[PL ]],Bitacora_2[[#This Row],[CO]])=6), "Complete","Incomplete")))))))) -> Complete | AM33: =+IF(OR(Bitacora_2[[#This Row],[Exportador]]="INVERSIONES JORDIE",Bitacora_2[[#This Row],[Exportador]]="TAL S.A."), "Tercero", "Propio") -> Propio | AN33: =IF(AND(Bitacora_2[[#This Row],[Clase Expedición]]="AIR",OR(Bitacora_2[[#This Row],[Mercado]]="US EAST",Bitacora_2[[#This Row],[Mercado]]="US WEST",Bitacora_2[[#This Row],[Mercado]]="US SOUTH")),IF(Bitacora_2[[#This Row],[ETD Doc]]<>"","Delivered","Pending"), IF(Bitacora_2[[#This Row],[Clase Expedición]]="AIR","Delivered", IF(AND(Bitacora_2[[#This Row],[ETD Doc]]="",Bitacora_2[[#This Row],[ATA DOC]]=""),"Pending", IF(AND(Bitacora_2[[#This Row],[ETD Doc]]<>"",Bitacora_2[[#This Row],[ATA DOC]]=""),"In transit", IF(AND(Bitacora_2[[#This Row],[ETD Doc]]<>"",Bitacora_2[[#This Row],[ATA DOC]]<>""),"Delivered",""))))) -> Delivered | AO33: Released | AP33: 46192 | AQ33: =IF(I33="SEA",IF(AP33="","On Hold","Released"),"") -> Released
A34: PO00000051017HFPEARANCONVFBIU5340640 | B34: 24 | C34: 46182 | D34: 28 | E34: LATAM | F34: CLSAI | G34: PE | H34: HFPE | I34: SEA | J34: ARAN | K34: CONV | L34: PO00000051017 | M34: FBIU5340640 | N34: HORTIFRUT COMERCIAL S.A. | O34: HORTIFRUT CHILE | P34: COSCO | Q34: COSCO SHIPPING THAMES 039W | R34: 46202 | S34: 46208 | T34: NWT | U34: =+IF(Bitacora_2[[#This Row],[ATA DOC]]<>"",Bitacora_2[[#This Row],[ATA DOC]], IF(Bitacora_2[[#This Row],[Clase Expedición]]="AIR",Bitacora_2[[#This Row],[ETD Real]], IF(AND(Bitacora_2[[#This Row],[Clase Expedición]]="SEA",Bitacora_2[[#This Row],[Mercado]]="LATAM"), Bitacora_2[[#This Row],[ETD Real]]+3, IF(AND(Bitacora_2[[#This Row],[Clase Expedición]]="SEA",Bitacora_2[[#This Row],[Mercado]]="EUROPE"), Bitacora_2[[#This Row],[ETD Real]]+8, IF(AND(Bitacora_2[[#This Row],[Clase Expedición]]="SEA",Bitacora_2[[#This Row],[Mercado]]="UK"), Bitacora_2[[#This Row],[ETD Real]]+11, IF(AND(Bitacora_2[[#This Row],[Clase Expedición]]="SEA",OR(Bitacora_2[[#This Row],[Mercado]]="ASIA",Bitacora_2[[#This Row],[Mercado]]="ASIA CN + HK")), Bitacora_2[[#This Row],[ETD Real]]+14, IF(AND(Bitacora_2[[#This Row],[Clase Expedición]]="SEA",OR(Bitacora_2[[#This Row],[Mercado]]="US EAST",Bitacora_2[[#This Row],[Mercado]]="US WEST",Bitacora_2[[#This Row],[Mercado]]="US SOUTH")), Bitacora_2[[#This Row],[ETD Real]]+8,""))))))) -> 46203 | V34: 46196 | W34: 46203 | X34: =IF(OR(Bitacora_2[[#This Row],[ETD Real]]="",Bitacora_2[[#This Row],[ETD Doc]]=""),"",Bitacora_2[[#This Row],[ETD Doc]]-Bitacora_2[[#This Row],[ETD Real]]) -> -6 | Y34: =IF(OR(Bitacora_2[[#This Row],[ATA DOC]]="",Bitacora_2[[#This Row],[ETA Real]]=""),"",Bitacora_2[[#This Row],[ETA Real]]-Bitacora_2[[#This Row],[ATA DOC]]) -> 5 | Z34: 9780695525 | AA34: X | AB34: X | AC34: X | AD34: X | AE34: X | AH34: x | AI34: =IF(AND(OR(E34="US EAST",E34="US WEST",E34="US SOUTH"),I34="SEA",Bitacora_2[[#This Row],[ETD Real]]-TODAY()>=3,Bitacora_2[[#This Row],[ISF]]<>"X"),"Pending", IF(AND(OR(E34="US EAST",E34="US WEST",E34="US SOUTH"),I34="SEA",Bitacora_2[[#This Row],[ETD Real]]-TODAY()=2,Bitacora_2[[#This Row],[ISF]]<>"X"),"Urgente", IF(AND(OR(E34="US EAST",E34="US WEST",E34="US SOUTH"),I34="SEA",Bitacora_2[[#This Row],[ETD Real]]-TODAY()<=1,Bitacora_2[[#This Row],[ISF]]<>"X"),"Muy Urgente", IF(AND(OR(E34="US EAST",E34="US WEST",E34="US SOUTH"),I34="SEA",Bitacora_2[[#This Row],[ISF]]="X"),"Sent","")))) | AJ34: =IF(AND(OR(Bitacora_2[[#This Row],[Clase Expedición]]="AIR",Bitacora_2[[#This Row],[Clase Expedición]]="TRK")),"Complete", IF(AND(Bitacora_2[[#This Row],[Mercado]]="LATAM",COUNTA(Bitacora_2[[#This Row],[PHYTO]:[ISF]],Bitacora_2[[#This Row],[CO]])=7,Bitacora_2[[#This Row],[Clase Expedición]]<>"TRK"), "Complete", IF(AND(Bitacora_2[[#This Row],[Mercado]]="LATAM",COUNTA(Bitacora_2[[#This Row],[PHYTO]:[PL ]],Bitacora_2[[#This Row],[CO]])=6,Bitacora_2[[#This Row],[Clase Expedición]]="SEA"), "Complete", IF(AND(OR(Bitacora_2[[#This Row],[Mercado]]="EUROPE",Bitacora_2[[#This Row],[Mercado]]="UK"),COUNTA(Bitacora_2[[#This Row],[PHYTO]],Bitacora_2[[#This Row],[INVOICE]:[PL ]],Bitacora_2[[#This Row],[COI]])=5,Bitacora_2[[#This Row],[Clase Expedición]]="SEA",Bitacora_2[[#This Row],[Manejo]]="ORG"), "Complete", IF(AND(OR(Bitacora_2[[#This Row],[Mercado]]="EUROPE",Bitacora_2[[#This Row],[Mercado]]="UK"),COUNTA(Bitacora_2[[#This Row],[PHYTO]],Bitacora_2[[#This Row],[INVOICE]:[PL ]])=4,Bitacora_2[[#This Row],[Clase Expedición]]="SEA",Bitacora_2[[#This Row],[Manejo]]="CONV"), "Complete", IF(AND(OR(Bitacora_2[[#This Row],[Mercado]]="US WEST",Bitacora_2[[#This Row],[Mercado]]="US EAST",Bitacora_2[[#This Row],[Mercado]]="US SOUTH"),COUNTA(Bitacora_2[[#This Row],[PHYTO]:[ISF]],Bitacora_2[[#This Row],[CO]])=7,Bitacora_2[[#This Row],[Clase Expedición]]="SEA",Bitacora_2[[#This Row],[Exportador]]="ECHF"), "Complete", IF(AND(OR(Bitacora_2[[#This Row],[Mercado]]="US WEST",Bitacora_2[[#This Row],[Mercado]]="US EAST",Bitacora_2[[#This Row],[Mercado]]="US SOUTH"),COUNTA(Bitacora_2[[#This Row],[PHYTO]:[ISF]])=6,Bitacora_2[[#This Row],[Clase Expedición]]="SEA",Bitacora_2[[#This Row],[Exportador]]<>"ECHF"), "Complete", IF(AND(OR(Bitacora_2[[#This Row],[Mercado]]="ASIA",Bitacora_2[[#This Row],[Mercado]]="ASIA CN + HK"),COUNTA(Bitacora_2[[#This Row],[PHYTO]:[PL ]],Bitacora_2[[#This Row],[CO]])=6), "Complete","Incomplete")))))))) -> Complete | AM34: =+IF(OR(Bitacora_2[[#This Row],[Exportador]]="INVERSIONES JORDIE",Bitacora_2[[#This Row],[Exportador]]="TAL S.A."), "Tercero", "Propio") -> Propio | AN34: =IF(AND(Bitacora_2[[#This Row],[Clase Expedición]]="AIR",OR(Bitacora_2[[#This Row],[Mercado]]="US EAST",Bitacora_2[[#This Row],[Mercado]]="US WEST",Bitacora_2[[#This Row],[Mercado]]="US SOUTH")),IF(Bitacora_2[[#This Row],[ETD Doc]]<>"","Delivered","Pending"), IF(Bitacora_2[[#This Row],[Clase Expedición]]="AIR","Delivered", IF(AND(Bitacora_2[[#This Row],[ETD Doc]]="",Bitacora_2[[#This Row],[ATA DOC]]=""),"Pending", IF(AND(Bitacora_2[[#This Row],[ETD Doc]]<>"",Bitacora_2[[#This Row],[ATA DOC]]=""),"In transit", IF(AND(Bitacora_2[[#This Row],[ETD Doc]]<>"",Bitacora_2[[#This Row],[ATA DOC]]<>""),"Delivered",""))))) -> Delivered | AO34: Released | AP34: 46211 | AQ34: =IF(I34="SEA",IF(AP34="","On Hold","Released"),"") -> Released | AR34: Demora en revisión de reporte (COSCO + SAG)
A35: PO00000051016HFPEARANCONVPE691300311 | B35: 24 | C35: 46183 | D35: 26 | E35: LATAM | F35: BAR | G35: PE | H35: HFPE | I35: TRK | J35: ARAN | K35: CONV | L35: PO00000051016 | M35: PE691300311 | N35: BERRYGOOD COM. IMP. E DISTRIBUICAO | O35: BERRYGOOD | P35: TERRESTRE | R35: 46182 | S35: 46196 | T35: MILTEX | U35: =+IF(Bitacora_2[[#This Row],[ATA DOC]]<>"",Bitacora_2[[#This Row],[ATA DOC]], IF(Bitacora_2[[#This Row],[Clase Expedición]]="AIR",Bitacora_2[[#This Row],[ETD Real]], IF(AND(Bitacora_2[[#This Row],[Clase Expedición]]="SEA",Bitacora_2[[#This Row],[Mercado]]="LATAM"), Bitacora_2[[#This Row],[ETD Real]]+3, IF(AND(Bitacora_2[[#This Row],[Clase Expedición]]="SEA",Bitacora_2[[#This Row],[Mercado]]="EUROPE"), Bitacora_2[[#This Row],[ETD Real]]+8, IF(AND(Bitacora_2[[#This Row],[Clase Expedición]]="SEA",Bitacora_2[[#This Row],[Mercado]]="UK"), Bitacora_2[[#This Row],[ETD Real]]+11, IF(AND(Bitacora_2[[#This Row],[Clase Expedición]]="SEA",OR(Bitacora_2[[#This Row],[Mercado]]="ASIA",Bitacora_2[[#This Row],[Mercado]]="ASIA CN + HK")), Bitacora_2[[#This Row],[ETD Real]]+14, IF(AND(Bitacora_2[[#This Row],[Clase Expedición]]="SEA",OR(Bitacora_2[[#This Row],[Mercado]]="US EAST",Bitacora_2[[#This Row],[Mercado]]="US WEST",Bitacora_2[[#This Row],[Mercado]]="US SOUTH")), Bitacora_2[[#This Row],[ETD Real]]+8,""))))))) | X35: =IF(OR(Bitacora_2[[#This Row],[ETD Real]]="",Bitacora_2[[#This Row],[ETD Doc]]=""),"",Bitacora_2[[#This Row],[ETD Doc]]-Bitacora_2[[#This Row],[ETD Real]]) | Y35: =IF(OR(Bitacora_2[[#This Row],[ATA DOC]]="",Bitacora_2[[#This Row],[ETA Real]]=""),"",Bitacora_2[[#This Row],[ETA Real]]-Bitacora_2[[#This Row],[ATA DOC]]) | AI35: =IF(AND(OR(E35="US EAST",E35="US WEST",E35="US SOUTH"),I35="SEA",Bitacora_2[[#This Row],[ETD Real]]-TODAY()>=3,Bitacora_2[[#This Row],[ISF]]<>"X"),"Pending", IF(AND(OR(E35="US EAST",E35="US WEST",E35="US SOUTH"),I35="SEA",Bitacora_2[[#This Row],[ETD Real]]-TODAY()=2,Bitacora_2[[#This Row],[ISF]]<>"X"),"Urgente", IF(AND(OR(E35="US EAST",E35="US WEST",E35="US SOUTH"),I35="SEA",Bitacora_2[[#This Row],[ETD Real]]-TODAY()<=1,Bitacora_2[[#This Row],[ISF]]<>"X"),"Muy Urgente", IF(AND(OR(E35="US EAST",E35="US WEST",E35="US SOUTH"),I35="SEA",Bitacora_2[[#This Row],[ISF]]="X"),"Sent","")))) | AJ35: =IF(AND(OR(Bitacora_2[[#This Row],[Clase Expedición]]="AIR",Bitacora_2[[#This Row],[Clase Expedición]]="TRK")),"Complete", IF(AND(Bitacora_2[[#This Row],[Mercado]]="LATAM",COUNTA(Bitacora_2[[#This Row],[PHYTO]:[ISF]],Bitacora_2[[#This Row],[CO]])=7,Bitacora_2[[#This Row],[Clase Expedición]]<>"TRK"), "Complete", IF(AND(Bitacora_2[[#This Row],[Mercado]]="LATAM",COUNTA(Bitacora_2[[#This Row],[PHYTO]:[PL ]],Bitacora_2[[#This Row],[CO]])=6,Bitacora_2[[#This Row],[Clase Expedición]]="SEA"), "Complete", IF(AND(OR(Bitacora_2[[#This Row],[Mercado]]="EUROPE",Bitacora_2[[#This Row],[Mercado]]="UK"),COUNTA(Bitacora_2[[#This Row],[PHYTO]],Bitacora_2[[#This Row],[INVOICE]:[PL ]],Bitacora_2[[#This Row],[COI]])=5,Bitacora_2[[#This Row],[Clase Expedición]]="SEA",Bitacora_2[[#This Row],[Manejo]]="ORG"), "Complete", IF(AND(OR(Bitacora_2[[#This Row],[Mercado]]="EUROPE",Bitacora_2[[#This Row],[Mercado]]="UK"),COUNTA(Bitacora_2[[#This Row],[PHYTO]],Bitacora_2[[#This Row],[INVOICE]:[PL ]])=4,Bitacora_2[[#This Row],[Clase Expedición]]="SEA",Bitacora_2[[#This Row],[Manejo]]="CONV"), "Complete", IF(AND(OR(Bitacora_2[[#This Row],[Mercado]]="US WEST",Bitacora_2[[#This Row],[Mercado]]="US EAST",Bitacora_2[[#This Row],[Mercado]]="US SOUTH"),COUNTA(Bitacora_2[[#This Row],[PHYTO]:[ISF]],Bitacora_2[[#This Row],[CO]])=7,Bitacora_2[[#This Row],[Clase Expedición]]="SEA",Bitacora_2[[#This Row],[Exportador]]="ECHF"), "Complete", IF(AND(OR(Bitacora_2[[#This Row],[Mercado]]="US WEST",Bitacora_2[[#This Row],[Mercado]]="US EAST",Bitacora_2[[#This Row],[Mercado]]="US SOUTH"),COUNTA(Bitacora_2[[#This Row],[PHYTO]:[ISF]])=6,Bitacora_2[[#This Row],[Clase Expedición]]="SEA",Bitacora_2[[#This Row],[Exportador]]<>"ECHF"), "Complete", IF(AND(OR(Bitacora_2[[#This Row],[Mercado]]="ASIA",Bitacora_2[[#This Row],[Mercado]]="ASIA CN + HK"),COUNTA(Bitacora_2[[#This Row],[PHYTO]:[PL ]],Bitacora_2[[#This Row],[CO]])=6), "Complete","Incomplete")))))))) -> Complete | AM35: =+IF(OR(Bitacora_2[[#This Row],[Exportador]]="INVERSIONES JORDIE",Bitacora_2[[#This Row],[Exportador]]="TAL S.A."), "Tercero", "Propio") -> Propio | AN35: =IF(AND(Bitacora_2[[#This Row],[Clase Expedición]]="AIR",OR(Bitacora_2[[#This Row],[Mercado]]="US EAST",Bitacora_2[[#This Row],[Mercado]]="US WEST",Bitacora_2[[#This Row],[Mercado]]="US SOUTH")),IF(Bitacora_2[[#This Row],[ETD Doc]]<>"","Delivered","Pending"), IF(Bitacora_2[[#This Row],[Clase Expedición]]="AIR","Delivered", IF(AND(Bitacora_2[[#This Row],[ETD Doc]]="",Bitacora_2[[#This Row],[ATA DOC]]=""),"Pending", IF(AND(Bitacora_2[[#This Row],[ETD Doc]]<>"",Bitacora_2[[#This Row],[ATA DOC]]=""),"In transit", IF(AND(Bitacora_2[[#This Row],[ETD Doc]]<>"",Bitacora_2[[#This Row],[ATA DOC]]<>""),"Delivered",""))))) -> Pending | AQ35: =IF(I35="SEA",IF(AP35="","On Hold","Released"),"")
A36: PO00000051027HFPEARANCONV145-11650273 | B36: 24 | C36: 46183 | D36: 24 | E36: US EAST | F36: JFK | G36: PE | H36: HFPE | I36: AIR | J36: ARAN | K36: CONV | L36: PO00000051027 | M36: 145-11650273 | N36: HORTIFRUT IMPORTS INC. (PHI-BOAT) | O36: NRF TIER I | P36: LATAM | R36: 46186 | S36: 46186 | T36: DHL | U36: =+IF(Bitacora_2[[#This Row],[ATA DOC]]<>"",Bitacora_2[[#This Row],[ATA DOC]], IF(Bitacora_2[[#This Row],[Clase Expedición]]="AIR",Bitacora_2[[#This Row],[ETD Real]], IF(AND(Bitacora_2[[#This Row],[Clase Expedición]]="SEA",Bitacora_2[[#This Row],[Mercado]]="LATAM"), Bitacora_2[[#This Row],[ETD Real]]+3, IF(AND(Bitacora_2[[#This Row],[Clase Expedición]]="SEA",Bitacora_2[[#This Row],[Mercado]]="EUROPE"), Bitacora_2[[#This Row],[ETD Real]]+8, IF(AND(Bitacora_2[[#This Row],[Clase Expedición]]="SEA",Bitacora_2[[#This Row],[Mercado]]="UK"), Bitacora_2[[#This Row],[ETD Real]]+11, IF(AND(Bitacora_2[[#This Row],[Clase Expedición]]="SEA",OR(Bitacora_2[[#This Row],[Mercado]]="ASIA",Bitacora_2[[#This Row],[Mercado]]="ASIA CN + HK")), Bitacora_2[[#This Row],[ETD Real]]+14, IF(AND(Bitacora_2[[#This Row],[Clase Expedición]]="SEA",OR(Bitacora_2[[#This Row],[Mercado]]="US EAST",Bitacora_2[[#This Row],[Mercado]]="US WEST",Bitacora_2[[#This Row],[Mercado]]="US SOUTH")), Bitacora_2[[#This Row],[ETD Real]]+8,""))))))) -> 46186 | X36: =IF(OR(Bitacora_2[[#This Row],[ETD Real]]="",Bitacora_2[[#This Row],[ETD Doc]]=""),"",Bitacora_2[[#This Row],[ETD Doc]]-Bitacora_2[[#This Row],[ETD Real]]) | Y36: =IF(OR(Bitacora_2[[#This Row],[ATA DOC]]="",Bitacora_2[[#This Row],[ETA Real]]=""),"",Bitacora_2[[#This Row],[ETA Real]]-Bitacora_2[[#This Row],[ATA DOC]]) | AI36: =IF(AND(OR(E36="US EAST",E36="US WEST",E36="US SOUTH"),I36="SEA",Bitacora_2[[#This Row],[ETD Real]]-TODAY()>=3,Bitacora_2[[#This Row],[ISF]]<>"X"),"Pending", IF(AND(OR(E36="US EAST",E36="US WEST",E36="US SOUTH"),I36="SEA",Bitacora_2[[#This Row],[ETD Real]]-TODAY()=2,Bitacora_2[[#This Row],[ISF]]<>"X"),"Urgente", IF(AND(OR(E36="US EAST",E36="US WEST",E36="US SOUTH"),I36="SEA",Bitacora_2[[#This Row],[ETD Real]]-TODAY()<=1,Bitacora_2[[#This Row],[ISF]]<>"X"),"Muy Urgente", IF(AND(OR(E36="US EAST",E36="US WEST",E36="US SOUTH"),I36="SEA",Bitacora_2[[#This Row],[ISF]]="X"),"Sent","")))) | AJ36: =IF(AND(OR(Bitacora_2[[#This Row],[Clase Expedición]]="AIR",Bitacora_2[[#This Row],[Clase Expedición]]="TRK")),"Complete", IF(AND(Bitacora_2[[#This Row],[Mercado]]="LATAM",COUNTA(Bitacora_2[[#This Row],[PHYTO]:[ISF]],Bitacora_2[[#This Row],[CO]])=7,Bitacora_2[[#This Row],[Clase Expedición]]<>"TRK"), "Complete", IF(AND(Bitacora_2[[#This Row],[Mercado]]="LATAM",COUNTA(Bitacora_2[[#This Row],[PHYTO]:[PL ]],Bitacora_2[[#This Row],[CO]])=6,Bitacora_2[[#This Row],[Clase Expedición]]="SEA"), "Complete", IF(AND(OR(Bitacora_2[[#This Row],[Mercado]]="EUROPE",Bitacora_2[[#This Row],[Mercado]]="UK"),COUNTA(Bitacora_2[[#This Row],[PHYTO]],Bitacora_2[[#This Row],[INVOICE]:[PL ]],Bitacora_2[[#This Row],[COI]])=5,Bitacora_2[[#This Row],[Clase Expedición]]="SEA",Bitacora_2[[#This Row],[Manejo]]="ORG"), "Complete", IF(AND(OR(Bitacora_2[[#This Row],[Mercado]]="EUROPE",Bitacora_2[[#This Row],[Mercado]]="UK"),COUNTA(Bitacora_2[[#This Row],[PHYTO]],Bitacora_2[[#This Row],[INVOICE]:[PL ]])=4,Bitacora_2[[#This Row],[Clase Expedición]]="SEA",Bitacora_2[[#This Row],[Manejo]]="CONV"), "Complete", IF(AND(OR(Bitacora_2[[#This Row],[Mercado]]="US WEST",Bitacora_2[[#This Row],[Mercado]]="US EAST",Bitacora_2[[#This Row],[Mercado]]="US SOUTH"),COUNTA(Bitacora_2[[#This Row],[PHYTO]:[ISF]],Bitacora_2[[#This Row],[CO]])=7,Bitacora_2[[#This Row],[Clase Expedición]]="SEA",Bitacora_2[[#This Row],[Exportador]]="ECHF"), "Complete", IF(AND(OR(Bitacora_2[[#This Row],[Mercado]]="US WEST",Bitacora_2[[#This Row],[Mercado]]="US EAST",Bitacora_2[[#This Row],[Mercado]]="US SOUTH"),COUNTA(Bitacora_2[[#This Row],[PHYTO]:[ISF]])=6,Bitacora_2[[#This Row],[Clase Expedición]]="SEA",Bitacora_2[[#This Row],[Exportador]]<>"ECHF"), "Complete", IF(AND(OR(Bitacora_2[[#This Row],[Mercado]]="ASIA",Bitacora_2[[#This Row],[Mercado]]="ASIA CN + HK"),COUNTA(Bitacora_2[[#This Row],[PHYTO]:[PL ]],Bitacora_2[[#This Row],[CO]])=6), "Complete","Incomplete")))))))) -> Complete | AM36: =+IF(OR(Bitacora_2[[#This Row],[Exportador]]="INVERSIONES JORDIE",Bitacora_2[[#This Row],[Exportador]]="TAL S.A."), "Tercero", "Propio") -> Propio | AN36: =IF(AND(Bitacora_2[[#This Row],[Clase Expedición]]="AIR",OR(Bitacora_2[[#This Row],[Mercado]]="US EAST",Bitacora_2[[#This Row],[Mercado]]="US WEST",Bitacora_2[[#This Row],[Mercado]]="US SOUTH")),IF(Bitacora_2[[#This Row],[ETD Doc]]<>"","Delivered","Pending"), IF(Bitacora_2[[#This Row],[Clase Expedición]]="AIR","Delivered", IF(AND(Bitacora_2[[#This Row],[ETD Doc]]="",Bitacora_2[[#This Row],[ATA DOC]]=""),"Pending", IF(AND(Bitacora_2[[#This Row],[ETD Doc]]<>"",Bitacora_2[[#This Row],[ATA DOC]]=""),"In transit", IF(AND(Bitacora_2[[#This Row],[ETD Doc]]<>"",Bitacora_2[[#This Row],[ATA DOC]]<>""),"Delivered",""))))) -> Pending | AQ36: =IF(I36="SEA",IF(AP36="","On Hold","Released"),"")
A37: RH-0037TTAL S.A.ARANCONV145-11651404 | B37: 24 | C37: 46184 | D37: 25 | E37: US EAST | F37: JFK | G37: PE | H37: TAL S.A. | I37: AIR | J37: ARAN | K37: CONV | L37: RH-0037T | M37: 145-11651404 | O37: NRF TIER I | P37: LATAM | R37: 46189 | S37: 46189 | U37: =+IF(Bitacora_2[[#This Row],[ATA DOC]]<>"",Bitacora_2[[#This Row],[ATA DOC]], IF(Bitacora_2[[#This Row],[Clase Expedición]]="AIR",Bitacora_2[[#This Row],[ETD Real]], IF(AND(Bitacora_2[[#This Row],[Clase Expedición]]="SEA",Bitacora_2[[#This Row],[Mercado]]="LATAM"), Bitacora_2[[#This Row],[ETD Real]]+3, IF(AND(Bitacora_2[[#This Row],[Clase Expedición]]="SEA",Bitacora_2[[#This Row],[Mercado]]="EUROPE"), Bitacora_2[[#This Row],[ETD Real]]+8, IF(AND(Bitacora_2[[#This Row],[Clase Expedición]]="SEA",Bitacora_2[[#This Row],[Mercado]]="UK"), Bitacora_2[[#This Row],[ETD Real]]+11, IF(AND(Bitacora_2[[#This Row],[Clase Expedición]]="SEA",OR(Bitacora_2[[#This Row],[Mercado]]="ASIA",Bitacora_2[[#This Row],[Mercado]]="ASIA CN + HK")), Bitacora_2[[#This Row],[ETD Real]]+14, IF(AND(Bitacora_2[[#This Row],[Clase Expedición]]="SEA",OR(Bitacora_2[[#This Row],[Mercado]]="US EAST",Bitacora_2[[#This Row],[Mercado]]="US WEST",Bitacora_2[[#This Row],[Mercado]]="US SOUTH")), Bitacora_2[[#This Row],[ETD Real]]+8,""))))))) -> 46189 | X37: =IF(OR(Bitacora_2[[#This Row],[ETD Real]]="",Bitacora_2[[#This Row],[ETD Doc]]=""),"",Bitacora_2[[#This Row],[ETD Doc]]-Bitacora_2[[#This Row],[ETD Real]]) | Y37: =IF(OR(Bitacora_2[[#This Row],[ATA DOC]]="",Bitacora_2[[#This Row],[ETA Real]]=""),"",Bitacora_2[[#This Row],[ETA Real]]-Bitacora_2[[#This Row],[ATA DOC]]) | AI37: =IF(AND(OR(E37="US EAST",E37="US WEST",E37="US SOUTH"),I37="SEA",Bitacora_2[[#This Row],[ETD Real]]-TODAY()>=3,Bitacora_2[[#This Row],[ISF]]<>"X"),"Pending", IF(AND(OR(E37="US EAST",E37="US WEST",E37="US SOUTH"),I37="SEA",Bitacora_2[[#This Row],[ETD Real]]-TODAY()=2,Bitacora_2[[#This Row],[ISF]]<>"X"),"Urgente", IF(AND(OR(E37="US EAST",E37="US WEST",E37="US SOUTH"),I37="SEA",Bitacora_2[[#This Row],[ETD Real]]-TODAY()<=1,Bitacora_2[[#This Row],[ISF]]<>"X"),"Muy Urgente", IF(AND(OR(E37="US EAST",E37="US WEST",E37="US SOUTH"),I37="SEA",Bitacora_2[[#This Row],[ISF]]="X"),"Sent","")))) | AJ37: =IF(AND(OR(Bitacora_2[[#This Row],[Clase Expedición]]="AIR",Bitacora_2[[#This Row],[Clase Expedición]]="TRK")),"Complete", IF(AND(Bitacora_2[[#This Row],[Mercado]]="LATAM",COUNTA(Bitacora_2[[#This Row],[PHYTO]:[ISF]],Bitacora_2[[#This Row],[CO]])=7,Bitacora_2[[#This Row],[Clase Expedición]]<>"TRK"), "Complete", IF(AND(Bitacora_2[[#This Row],[Mercado]]="LATAM",COUNTA(Bitacora_2[[#This Row],[PHYTO]:[PL ]],Bitacora_2[[#This Row],[CO]])=6,Bitacora_2[[#This Row],[Clase Expedición]]="SEA"), "Complete", IF(AND(OR(Bitacora_2[[#This Row],[Mercado]]="EUROPE",Bitacora_2[[#This Row],[Mercado]]="UK"),COUNTA(Bitacora_2[[#This Row],[PHYTO]],Bitacora_2[[#This Row],[INVOICE]:[PL ]],Bitacora_2[[#This Row],[COI]])=5,Bitacora_2[[#This Row],[Clase Expedición]]="SEA",Bitacora_2[[#This Row],[Manejo]]="ORG"), "Complete", IF(AND(OR(Bitacora_2[[#This Row],[Mercado]]="EUROPE",Bitacora_2[[#This Row],[Mercado]]="UK"),COUNTA(Bitacora_2[[#This Row],[PHYTO]],Bitacora_2[[#This Row],[INVOICE]:[PL ]])=4,Bitacora_2[[#This Row],[Clase Expedición]]="SEA",Bitacora_2[[#This Row],[Manejo]]="CONV"), "Complete", IF(AND(OR(Bitacora_2[[#This Row],[Mercado]]="US WEST",Bitacora_2[[#This Row],[Mercado]]="US EAST",Bitacora_2[[#This Row],[Mercado]]="US SOUTH"),COUNTA(Bitacora_2[[#This Row],[PHYTO]:[ISF]],Bitacora_2[[#This Row],[CO]])=7,Bitacora_2[[#This Row],[Clase Expedición]]="SEA",Bitacora_2[[#This Row],[Exportador]]="ECHF"), "Complete", IF(AND(OR(Bitacora_2[[#This Row],[Mercado]]="US WEST",Bitacora_2[[#This Row],[Mercado]]="US EAST",Bitacora_2[[#This Row],[Mercado]]="US SOUTH"),COUNTA(Bitacora_2[[#This Row],[PHYTO]:[ISF]])=6,Bitacora_2[[#This Row],[Clase Expedición]]="SEA",Bitacora_2[[#This Row],[Exportador]]<>"ECHF"), "Complete", IF(AND(OR(Bitacora_2[[#This Row],[Mercado]]="ASIA",Bitacora_2[[#This Row],[Mercado]]="ASIA CN + HK"),COUNTA(Bitacora_2[[#This Row],[PHYTO]:[PL ]],Bitacora_2[[#This Row],[CO]])=6), "Complete","Incomplete")))))))) -> Complete | AM37: =+IF(OR(Bitacora_2[[#This Row],[Exportador]]="INVERSIONES JORDIE",Bitacora_2[[#This Row],[Exportador]]="TAL S.A."), "Tercero", "Propio") -> Tercero | AN37: =IF(AND(Bitacora_2[[#This Row],[Clase Expedición]]="AIR",OR(Bitacora_2[[#This Row],[Mercado]]="US EAST",Bitacora_2[[#This Row],[Mercado]]="US WEST",Bitacora_2[[#This Row],[Mercado]]="US SOUTH")),IF(Bitacora_2[[#This Row],[ETD Doc]]<>"","Delivered","Pending"), IF(Bitacora_2[[#This Row],[Clase Expedición]]="AIR","Delivered", IF(AND(Bitacora_2[[#This Row],[ETD Doc]]="",Bitacora_2[[#This Row],[ATA DOC]]=""),"Pending", IF(AND(Bitacora_2[[#This Row],[ETD Doc]]<>"",Bitacora_2[[#This Row],[ATA DOC]]=""),"In transit", IF(AND(Bitacora_2[[#This Row],[ETD Doc]]<>"",Bitacora_2[[#This Row],[ATA DOC]]<>""),"Delivered",""))))) -> Pending | AQ37: =IF(I37="SEA",IF(AP37="","On Hold","Released"),"")
A38: PO00000050869HFPEARANCONVCXRU1529150 | B38: 24 | C38: 46185 | D38: 27 | E38: UK | F38: GBDVR | G38: PE | H38: HFPE | I38: SEA | J38: ARAN | K38: CONV | L38: PO00000050869 | M38: CXRU1529150 | N38: HORTIFRUT MARKETING EMEA S.A. | O38: SAINSBURYS | P38: ANKASEA | Q38: CHARLES ISLAND SR26020 | R38: 46187 | S38: 46202 | T38: SRL | U38: =+IF(Bitacora_2[[#This Row],[ATA DOC]]<>"",Bitacora_2[[#This Row],[ATA DOC]], IF(Bitacora_2[[#This Row],[Clase Expedición]]="AIR",Bitacora_2[[#This Row],[ETD Real]], IF(AND(Bitacora_2[[#This Row],[Clase Expedición]]="SEA",Bitacora_2[[#This Row],[Mercado]]="LATAM"), Bitacora_2[[#This Row],[ETD Real]]+3, IF(AND(Bitacora_2[[#This Row],[Clase Expedición]]="SEA",Bitacora_2[[#This Row],[Mercado]]="EUROPE"), Bitacora_2[[#This Row],[ETD Real]]+8, IF(AND(Bitacora_2[[#This Row],[Clase Expedición]]="SEA",Bitacora_2[[#This Row],[Mercado]]="UK"), Bitacora_2[[#This Row],[ETD Real]]+11, IF(AND(Bitacora_2[[#This Row],[Clase Expedición]]="SEA",OR(Bitacora_2[[#This Row],[Mercado]]="ASIA",Bitacora_2[[#This Row],[Mercado]]="ASIA CN + HK")), Bitacora_2[[#This Row],[ETD Real]]+14, IF(AND(Bitacora_2[[#This Row],[Clase Expedición]]="SEA",OR(Bitacora_2[[#This Row],[Mercado]]="US EAST",Bitacora_2[[#This Row],[Mercado]]="US WEST",Bitacora_2[[#This Row],[Mercado]]="US SOUTH")), Bitacora_2[[#This Row],[ETD Real]]+8,""))))))) -> 46197 | V38: 46192 | W38: 46197 | X38: =IF(OR(Bitacora_2[[#This Row],[ETD Real]]="",Bitacora_2[[#This Row],[ETD Doc]]=""),"",Bitacora_2[[#This Row],[ETD Doc]]-Bitacora_2[[#This Row],[ETD Real]]) -> 5 | Y38: =IF(OR(Bitacora_2[[#This Row],[ATA DOC]]="",Bitacora_2[[#This Row],[ETA Real]]=""),"",Bitacora_2[[#This Row],[ETA Real]]-Bitacora_2[[#This Row],[ATA DOC]]) -> 5 | Z38: 5982892101 | AA38: X | AC38: X | AD38: X | AE38: X | AI38: =IF(AND(OR(E38="US EAST",E38="US WEST",E38="US SOUTH"),I38="SEA",Bitacora_2[[#This Row],[ETD Real]]-TODAY()>=3,Bitacora_2[[#This Row],[ISF]]<>"X"),"Pending", IF(AND(OR(E38="US EAST",E38="US WEST",E38="US SOUTH"),I38="SEA",Bitacora_2[[#This Row],[ETD Real]]-TODAY()=2,Bitacora_2[[#This Row],[ISF]]<>"X"),"Urgente", IF(AND(OR(E38="US EAST",E38="US WEST",E38="US SOUTH"),I38="SEA",Bitacora_2[[#This Row],[ETD Real]]-TODAY()<=1,Bitacora_2[[#This Row],[ISF]]<>"X"),"Muy Urgente", IF(AND(OR(E38="US EAST",E38="US WEST",E38="US SOUTH"),I38="SEA",Bitacora_2[[#This Row],[ISF]]="X"),"Sent","")))) | AJ38: =IF(AND(OR(Bitacora_2[[#This Row],[Clase Expedición]]="AIR",Bitacora_2[[#This Row],[Clase Expedición]]="TRK")),"Complete", IF(AND(Bitacora_2[[#This Row],[Mercado]]="LATAM",COUNTA(Bitacora_2[[#This Row],[PHYTO]:[ISF]],Bitacora_2[[#This Row],[CO]])=7,Bitacora_2[[#This Row],[Clase Expedición]]<>"TRK"), "Complete", IF(AND(Bitacora_2[[#This Row],[Mercado]]="LATAM",COUNTA(Bitacora_2[[#This Row],[PHYTO]:[PL ]],Bitacora_2[[#This Row],[CO]])=6,Bitacora_2[[#This Row],[Clase Expedición]]="SEA"), "Complete", IF(AND(OR(Bitacora_2[[#This Row],[Mercado]]="EUROPE",Bitacora_2[[#This Row],[Mercado]]="UK"),COUNTA(Bitacora_2[[#This Row],[PHYTO]],Bitacora_2[[#This Row],[INVOICE]:[PL ]],Bitacora_2[[#This Row],[COI]])=5,Bitacora_2[[#This Row],[Clase Expedición]]="SEA",Bitacora_2[[#This Row],[Manejo]]="ORG"), "Complete", IF(AND(OR(Bitacora_2[[#This Row],[Mercado]]="EUROPE",Bitacora_2[[#This Row],[Mercado]]="UK"),COUNTA(Bitacora_2[[#This Row],[PHYTO]],Bitacora_2[[#This Row],[INVOICE]:[PL ]])=4,Bitacora_2[[#This Row],[Clase Expedición]]="SEA",Bitacora_2[[#This Row],[Manejo]]="CONV"), "Complete", IF(AND(OR(Bitacora_2[[#This Row],[Mercado]]="US WEST",Bitacora_2[[#This Row],[Mercado]]="US EAST",Bitacora_2[[#This Row],[Mercado]]="US SOUTH"),COUNTA(Bitacora_2[[#This Row],[PHYTO]:[ISF]],Bitacora_2[[#This Row],[CO]])=7,Bitacora_2[[#This Row],[Clase Expedición]]="SEA",Bitacora_2[[#This Row],[Exportador]]="ECHF"), "Complete", IF(AND(OR(Bitacora_2[[#This Row],[Mercado]]="US WEST",Bitacora_2[[#This Row],[Mercado]]="US EAST",Bitacora_2[[#This Row],[Mercado]]="US SOUTH"),COUNTA(Bitacora_2[[#This Row],[PHYTO]:[ISF]])=6,Bitacora_2[[#This Row],[Clase Expedición]]="SEA",Bitacora_2[[#This Row],[Exportador]]<>"ECHF"), "Complete", IF(AND(OR(Bitacora_2[[#This Row],[Mercado]]="ASIA",Bitacora_2[[#This Row],[Mercado]]="ASIA CN + HK"),COUNTA(Bitacora_2[[#This Row],[PHYTO]:[PL ]],Bitacora_2[[#This Row],[CO]])=6), "Complete","Incomplete")))))))) -> Complete | AM38: =+IF(OR(Bitacora_2[[#This Row],[Exportador]]="INVERSIONES JORDIE",Bitacora_2[[#This Row],[Exportador]]="TAL S.A."), "Tercero", "Propio") -> Propio | AN38: =IF(AND(Bitacora_2[[#This Row],[Clase Expedición]]="AIR",OR(Bitacora_2[[#This Row],[Mercado]]="US EAST",Bitacora_2[[#This Row],[Mercado]]="US WEST",Bitacora_2[[#This Row],[Mercado]]="US SOUTH")),IF(Bitacora_2[[#This Row],[ETD Doc]]<>"","Delivered","Pending"), IF(Bitacora_2[[#This Row],[Clase Expedición]]="AIR","Delivered", IF(AND(Bitacora_2[[#This Row],[ETD Doc]]="",Bitacora_2[[#This Row],[ATA DOC]]=""),"Pending", IF(AND(Bitacora_2[[#This Row],[ETD Doc]]<>"",Bitacora_2[[#This Row],[ATA DOC]]=""),"In transit", IF(AND(Bitacora_2[[#This Row],[ETD Doc]]<>"",Bitacora_2[[#This Row],[ATA DOC]]<>""),"Delivered",""))))) -> Delivered | AO38: Released | AP38: 46194 | AQ38: =IF(I38="SEA",IF(AP38="","On Hold","Released"),"") -> Released
A39: PO00000051046HFPEARANCONV145-11651452 | B39: 24 | C39: 46185 | D39: 25 | E39: LATAM | F39: BOG | G39: PE | H39: HFPE | I39: AIR | J39: ARAN | K39: CONV | L39: PO00000051046 | M39: 145-11651452 | N39: HORTIFRUT COLOMBIA SAS | O39: HORTIFRUT COLOMBIA | P39: LATAM | R39: 46187 | S39: 46188 | T39: Hellmann | U39: =+IF(Bitacora_2[[#This Row],[ATA DOC]]<>"",Bitacora_2[[#This Row],[ATA DOC]], IF(Bitacora_2[[#This Row],[Clase Expedición]]="AIR",Bitacora_2[[#This Row],[ETD Real]], IF(AND(Bitacora_2[[#This Row],[Clase Expedición]]="SEA",Bitacora_2[[#This Row],[Mercado]]="LATAM"), Bitacora_2[[#This Row],[ETD Real]]+3, IF(AND(Bitacora_2[[#This Row],[Clase Expedición]]="SEA",Bitacora_2[[#This Row],[Mercado]]="EUROPE"), Bitacora_2[[#This Row],[ETD Real]]+8, IF(AND(Bitacora_2[[#This Row],[Clase Expedición]]="SEA",Bitacora_2[[#This Row],[Mercado]]="UK"), Bitacora_2[[#This Row],[ETD Real]]+11, IF(AND(Bitacora_2[[#This Row],[Clase Expedición]]="SEA",OR(Bitacora_2[[#This Row],[Mercado]]="ASIA",Bitacora_2[[#This Row],[Mercado]]="ASIA CN + HK")), Bitacora_2[[#This Row],[ETD Real]]+14, IF(AND(Bitacora_2[[#This Row],[Clase Expedición]]="SEA",OR(Bitacora_2[[#This Row],[Mercado]]="US EAST",Bitacora_2[[#This Row],[Mercado]]="US WEST",Bitacora_2[[#This Row],[Mercado]]="US SOUTH")), Bitacora_2[[#This Row],[ETD Real]]+8,""))))))) -> 46187 | X39: =IF(OR(Bitacora_2[[#This Row],[ETD Real]]="",Bitacora_2[[#This Row],[ETD Doc]]=""),"",Bitacora_2[[#This Row],[ETD Doc]]-Bitacora_2[[#This Row],[ETD Real]]) | Y39: =IF(OR(Bitacora_2[[#This Row],[ATA DOC]]="",Bitacora_2[[#This Row],[ETA Real]]=""),"",Bitacora_2[[#This Row],[ETA Real]]-Bitacora_2[[#This Row],[ATA DOC]]) | AI39: =IF(AND(OR(E39="US EAST",E39="US WEST",E39="US SOUTH"),I39="SEA",Bitacora_2[[#This Row],[ETD Real]]-TODAY()>=3,Bitacora_2[[#This Row],[ISF]]<>"X"),"Pending", IF(AND(OR(E39="US EAST",E39="US WEST",E39="US SOUTH"),I39="SEA",Bitacora_2[[#This Row],[ETD Real]]-TODAY()=2,Bitacora_2[[#This Row],[ISF]]<>"X"),"Urgente", IF(AND(OR(E39="US EAST",E39="US WEST",E39="US SOUTH"),I39="SEA",Bitacora_2[[#This Row],[ETD Real]]-TODAY()<=1,Bitacora_2[[#This Row],[ISF]]<>"X"),"Muy Urgente", IF(AND(OR(E39="US EAST",E39="US WEST",E39="US SOUTH"),I39="SEA",Bitacora_2[[#This Row],[ISF]]="X"),"Sent","")))) | AJ39: =IF(AND(OR(Bitacora_2[[#This Row],[Clase Expedición]]="AIR",Bitacora_2[[#This Row],[Clase Expedición]]="TRK")),"Complete", IF(AND(Bitacora_2[[#This Row],[Mercado]]="LATAM",COUNTA(Bitacora_2[[#This Row],[PHYTO]:[ISF]],Bitacora_2[[#This Row],[CO]])=7,Bitacora_2[[#This Row],[Clase Expedición]]<>"TRK"), "Complete", IF(AND(Bitacora_2[[#This Row],[Mercado]]="LATAM",COUNTA(Bitacora_2[[#This Row],[PHYTO]:[PL ]],Bitacora_2[[#This Row],[CO]])=6,Bitacora_2[[#This Row],[Clase Expedición]]="SEA"), "Complete", IF(AND(OR(Bitacora_2[[#This Row],[Mercado]]="EUROPE",Bitacora_2[[#This Row],[Mercado]]="UK"),COUNTA(Bitacora_2[[#This Row],[PHYTO]],Bitacora_2[[#This Row],[INVOICE]:[PL ]],Bitacora_2[[#This Row],[COI]])=5,Bitacora_2[[#This Row],[Clase Expedición]]="SEA",Bitacora_2[[#This Row],[Manejo]]="ORG"), "Complete", IF(AND(OR(Bitacora_2[[#This Row],[Mercado]]="EUROPE",Bitacora_2[[#This Row],[Mercado]]="UK"),COUNTA(Bitacora_2[[#This Row],[PHYTO]],Bitacora_2[[#This Row],[INVOICE]:[PL ]])=4,Bitacora_2[[#This Row],[Clase Expedición]]="SEA",Bitacora_2[[#This Row],[Manejo]]="CONV"), "Complete", IF(AND(OR(Bitacora_2[[#This Row],[Mercado]]="US WEST",Bitacora_2[[#This Row],[Mercado]]="US EAST",Bitacora_2[[#This Row],[Mercado]]="US SOUTH"),COUNTA(Bitacora_2[[#This Row],[PHYTO]:[ISF]],Bitacora_2[[#This Row],[CO]])=7,Bitacora_2[[#This Row],[Clase Expedición]]="SEA",Bitacora_2[[#This Row],[Exportador]]="ECHF"), "Complete", IF(AND(OR(Bitacora_2[[#This Row],[Mercado]]="US WEST",Bitacora_2[[#This Row],[Mercado]]="US EAST",Bitacora_2[[#This Row],[Mercado]]="US SOUTH"),COUNTA(Bitacora_2[[#This Row],[PHYTO]:[ISF]])=6,Bitacora_2[[#This Row],[Clase Expedición]]="SEA",Bitacora_2[[#This Row],[Exportador]]<>"ECHF"), "Complete", IF(AND(OR(Bitacora_2[[#This Row],[Mercado]]="ASIA",Bitacora_2[[#This Row],[Mercado]]="ASIA CN + HK"),COUNTA(Bitacora_2[[#This Row],[PHYTO]:[PL ]],Bitacora_2[[#This Row],[CO]])=6), "Complete","Incomplete")))))))) -> Complete | AM39: =+IF(OR(Bitacora_2[[#This Row],[Exportador]]="INVERSIONES JORDIE",Bitacora_2[[#This Row],[Exportador]]="TAL S.A."), "Tercero", "Propio") -> Propio | AN39: =IF(AND(Bitacora_2[[#This Row],[Clase Expedición]]="AIR",OR(Bitacora_2[[#This Row],[Mercado]]="US EAST",Bitacora_2[[#This Row],[Mercado]]="US WEST",Bitacora_2[[#This Row],[Mercado]]="US SOUTH")),IF(Bitacora_2[[#This Row],[ETD Doc]]<>"","Delivered","Pending"), IF(Bitacora_2[[#This Row],[Clase Expedición]]="AIR","Delivered", IF(AND(Bitacora_2[[#This Row],[ETD Doc]]="",Bitacora_2[[#This Row],[ATA DOC]]=""),"Pending", IF(AND(Bitacora_2[[#This Row],[ETD Doc]]<>"",Bitacora_2[[#This Row],[ATA DOC]]=""),"In transit", IF(AND(Bitacora_2[[#This Row],[ETD Doc]]<>"",Bitacora_2[[#This Row],[ATA DOC]]<>""),"Delivered",""))))) -> Delivered | AQ39: =IF(I39="SEA",IF(AP39="","On Hold","Released"),"")
